Workbook
Name _Loc1: [3]Request!$M$125
Name _Loc10: [4]Request!$M$134
Name _Loc11: [4]Request!$M$135
Name _Loc12: [4]Request!$M$136
Name _Loc13: [4]Request!$M$137
Name _Loc14: [4]Request!$M$138
Name _Loc15: [4]Request!$M$139
Name _Loc16: [4]Request!$M$140
Name _Loc17: [4]Request!$M$141
Name _Loc18: [4]Request!$M$142
Name _Loc19: [4]Request!$M$143
Name _Loc2: [4]Request!$M$126
Name _Loc20: [4]Request!$M$144
Name _Loc21: [4]Request!$M$145
Name _Loc22: [4]Request!$M$146
Name _Loc23: [4]Request!$M$147
Name _Loc24: [4]Request!$M$148
Name _Loc25: [4]Request!$M$149
Name _Loc26: [4]Request!$M$150
Name _Loc3: [4]Request!$M$127
Name _Loc4: [4]Request!$M$128
Name _Loc5: [4]Request!$M$129
Name _Loc6: [4]Request!$M$130
Name _Loc7: [4]Request!$M$131
Name _Loc8: [4]Request!$M$132
Name _Loc9: [4]Request!$M$133
Name Account: [4]Request!$B$17
Name Acct_number: [5]Summary!$E$2
Name AFD: #REF!
Name Agent: [4]Request!$A$60
Name Agent_Comm: [4]Request!$E$64
Name Agent_Delivery: [4]Request!$O$62
Name Agent_Involved: [4]Request!$P$62
Name Agent_Pickup: [4]Request!$N$62
Name Agent_Services: [4]Request!$E$66
Name AgentQ: [4]Request!$L$62
Name Alph_countries: [7]zones_input!$A$2:$A$214
Name anakg: '[4]Shipments - kg current'!$D$1
Name analb: '[4]Shipments - lb current'!$D$1
Name ApDsctKgADNR: #REF!
Name ApDsctKgComm: #REF!
Name ApDsctKgH1: #REF!
Name ApDsctKgH2: #REF!
Name ApDsctKgIEAppCurDisct: #REF!
Name ApDsctKgIEAppMin: #REF!
Name ApDsctKgIEReqCurDisct: #REF!
Name ApDsctKgIEReqMin: #REF!
Name ApDsctKgIERestore: #REF!
Name ApDsctKgIPAppCurDisct: #REF!
Name ApDsctKgIPAppMin: #REF!
Name ApDsctKgIPReqCurDisct: #REF!
Name ApDsctKgIPReqMin: #REF!
Name ApDsctKgIPRestore: #REF!
Name ApDsctKgLR: #REF!
Name ApDsctKgLR1: #REF!
Name ApDsctKgQ1: #REF!
Name ApDsctKgQ10: #REF!
Name ApDsctKgQ2: #REF!
Name ApDsctKgQ3: #REF!
Name ApDsctKgQ4: #REF!

Sheet Detailed Calculation table
A1: 产品编码 (Product Original RMB Cost) | B1: G00701-JA | C1: 利润（Profit） | F1: 0.07 | G1: 计算数量Quantity | L1: 1 | M1: 2 | N1: 3 | O1: 本期安全汇率 (Current safe exchange rate) | P1: 7.1 | Q1: Shipping Category运费参考表 | R1: 顺邮宝挂号
A3: 国家/地区Country | B3: 缩写Country abbreviation | C3: 1PCS美元总报价 (USD Quoation Price) | D3: 2PCS美元总报价 (USD Quoation Price) | E3: 3PCS美元总报价 (USD Quoation Price) | F3: 1PCS总运费(USD) (Total Freight) | G3: 2PCS总运费(USD) (Total Freight) | H3: 3PCS总运费(USD) (Total Freight) | I3: 1PCS产品成本（美金）(Product Original Cost USD) | J3: 2PCS产品成本（美金）(Product Original Cost USD) | K3: 3PCS产品成本（美金）(Product Original Cost USD) | L3: 1pcs产品总重量 (Total Product Weight) (KG) | M3: 2pcs产品总重量 (Total Product Weight) (KG) | N3: 3pcs产品总重量 (Total Product Weight) (KG) | O3: 1PCS总运费(RMB)(Total Freight) | P3: 2PCS总运费(RMB)(Total Freight) | Q3: 3PCS总运费(RMB)(Total Freight)
A4: 美国 | B4: US | C4: =(F4+I4)*(1+$F$1) -> 10.541761 | D4: =(G4+J4)*(1+$F$1) -> 15.055352 | E4: =(H4+K4)*(1+$F$1) -> 19.568944 | F4: =O4/$P$1 -> 7.8802817 | G4: =P4/$P$1 -> 10.126761 | H4: =Q4/$P$1 -> 12.373239 | I4: =(VLOOKUP($B$1,'Product Procurement Sheet'!B:I,8,0)*$L$1)/$P$1 -> 1.971831 | J4: =(VLOOKUP($B$1,'Product Procurement Sheet'!B:I,8,0)*$M$1)/$P$1 -> 3.943662 | K4: =(VLOOKUP($B$1,'Product Procurement Sheet'!B:I,8,0)*$N$1)/$P$1 -> 5.915493 | L4: =VLOOKUP($B$1,'Product Procurement Sheet'!B:D,3,FALSE)*$L$1 -> 0.11 | M4: =VLOOKUP($B$1,'Product Procurement Sheet'!B:D,3,FALSE)*$M$1 -> 0.22 | N4: =VLOOKUP($B$1,'Product Procurement Sheet'!B:D,3,FALSE)*$N$1 -> 0.33 | O4: {=(_xlfn.SINGLE(_xlfn.XLOOKUP(1,(INDIRECT($R$1&"!$C:$C")=B4)*(INDIRECT($R$1&"!$G:$G")<L4)*(INDIRECT($R$1&"!$H:$H")>=L4),INDIRECT($R$1&"!$K:$K"))))*L4+(_xlfn.SINGLE(_xlfn.XLOOKUP(1,(INDIRECT($R$1&"!$C:$C")=B4)*(INDIRECT($R$1&"!$G:$G")<L4)*(INDIRECT($R$1&"!$H:$H")>=L4),INDIRECT($R$1&"!$L:$L"))))} -> 55.95 | P4: {=(_xlfn.SINGLE(_xlfn.XLOOKUP(1,(INDIRECT($R$1&"!$C:$C")=B4)*(INDIRECT($R$1&"!$G:$G")<M4)*(INDIRECT($R$1&"!$H:$H")>=M4),INDIRECT($R$1&"!$K:$K"))))*M4+(_xlfn.SINGLE(_xlfn.XLOOKUP(1,(INDIRECT($R$1&"!$C:$C")=B4)*(INDIRECT($R$1&"!$G:$G")<M4)*(INDIRECT($R$1&"!$H:$H")>=M4),INDIRECT($R$1&"!$L:$L"))))} -> 71.9 | Q4: {=(_xlfn.SINGLE(_xlfn.XLOOKUP(1,(INDIRECT($R$1&"!$C:$C")=B4)*(INDIRECT($R$1&"!$G:$G")<N4)*(INDIRECT($R$1&"!$H:$H")>=N4),INDIRECT($R$1&"!$K:$K"))))*N4+(_xlfn.SINGLE(_xlfn.XLOOKUP(1,(INDIRECT($R$1&"!$C:$C")=B4)*(INDIRECT($R$1&"!$G:$G")<N4)*(INDIRECT($R$1&"!$H:$H")>=N4),INDIRECT($R$1&"!$L:$L"))))} -> 87.85
A5: 英国 | B5: UK/GB | C5: =(F5+I5)*(1+$F$1) -> #N/A | D5: =(G5+J5)*(1+$F$1) -> #N/A | E5: =(H5+K5)*(1+$F$1) -> #N/A | F5: =O5/$P$1 -> #N/A | G5: =P5/$P$1 -> #N/A | H5: =Q5/$P$1 -> #N/A | I5: =(VLOOKUP($B$1,'Product Procurement Sheet'!B:I,8,0)*$L$1)/$P$1 -> 1.971831 | J5: =(VLOOKUP($B$1,'Product Procurement Sheet'!B:I,8,0)*$M$1)/$P$1 -> 3.943662 | K5: =(VLOOKUP($B$1,'Product Procurement Sheet'!B:I,8,0)*$N$1)/$P$1 -> 5.915493 | L5: =VLOOKUP($B$1,'Product Procurement Sheet'!B:D,3,FALSE)*$L$1 -> 0.11 | M5: =VLOOKUP($B$1,'Product Procurement Sheet'!B:D,3,FALSE)*$M$1 -> 0.22 | N5: =VLOOKUP($B$1,'Product Procurement Sheet'!B:D,3,FALSE)*$N$1 -> 0.33 | O5: {=(_xlfn.SINGLE(_xlfn.XLOOKUP(1,(INDIRECT($R$1&"!$C:$C")=B5)*(INDIRECT($R$1&"!$G:$G")<L5)*(INDIRECT($R$1&"!$H:$H")>=L5),INDIRECT($R$1&"!$K:$K"))))*L5+(_xlfn.SINGLE(_xlfn.XLOOKUP(1,(INDIRECT($R$1&"!$C:$C")=B5)*(INDIRECT($R$1&"!$G:$G")<L5)*(INDIRECT($R$1&"!$H:$H")>=L5),INDIRECT($R$1&"!$L:$L"))))} -> #N/A | P5: {=(_xlfn.SINGLE(_xlfn.XLOOKUP(1,(INDIRECT($R$1&"!$C:$C")=B5)*(INDIRECT($R$1&"!$G:$G")<M5)*(INDIRECT($R$1&"!$H:$H")>=M5),INDIRECT($R$1&"!$K:$K"))))*M5+(_xlfn.SINGLE(_xlfn.XLOOKUP(1,(INDIRECT($R$1&"!$C:$C")=B5)*(INDIRECT($R$1&"!$G:$G")<M5)*(INDIRECT($R$1&"!$H:$H")>=M5),INDIRECT($R$1&"!$L:$L"))))} -> #N/A | Q5: {=(_xlfn.SINGLE(_xlfn.XLOOKUP(1,(INDIRECT($R$1&"!$C:$C")=B5)*(INDIRECT($R$1&"!$G:$G")<N5)*(INDIRECT($R$1&"!$H:$H")>=N5),INDIRECT($R$1&"!$K:$K"))))*N5+(_xlfn.SINGLE(_xlfn.XLOOKUP(1,(INDIRECT($R$1&"!$C:$C")=B5)*(INDIRECT($R$1&"!$G:$G")<N5)*(INDIRECT($R$1&"!$H:$H")>=N5),INDIRECT($R$1&"!$L:$L"))))} -> #N/A
A6: 法国 | B6: FR | C6: =(F6+I6)*(1+$F$1) -> 6.3823239 | D6: =(G6+J6)*(1+$F$1) -> 9.9012676 | E6: =(H6+K6)*(1+$F$1) -> 13.420211 | F6: =O6/$P$1 -> 3.9929577 | G6: =P6/$P$1 -> 5.3098592 | H6: =Q6/$P$1 -> 6.6267606 | I6: =(VLOOKUP($B$1,'Product Procurement Sheet'!B:I,8,0)*$L$1)/$P$1 -> 1.971831 | J6: =(VLOOKUP($B$1,'Product Procurement Sheet'!B:I,8,0)*$M$1)/$P$1 -> 3.943662 | K6: =(VLOOKUP($B$1,'Product Procurement Sheet'!B:I,8,0)*$N$1)/$P$1 -> 5.915493 | L6: =VLOOKUP($B$1,'Product Procurement Sheet'!B:D,3,FALSE)*$L$1 -> 0.11 | M6: =VLOOKUP($B$1,'Product Procurement Sheet'!B:D,3,FALSE)*$M$1 -> 0.22 | N6: =VLOOKUP($B$1,'Product Procurement Sheet'!B:D,3,FALSE)*$N$1 -> 0.33 | O6: {=(_xlfn.SINGLE(_xlfn.XLOOKUP(1,(INDIRECT($R$1&"!$C:$C")=B6)*(INDIRECT($R$1&"!$G:$G")<L6)*(INDIRECT($R$1&"!$H:$H")>=L6),INDIRECT($R$1&"!$K:$K"))))*L6+(_xlfn.SINGLE(_xlfn.XLOOKUP(1,(INDIRECT($R$1&"!$C:$C")=B6)*(INDIRECT($R$1&"!$G:$G")<L6)*(INDIRECT($R$1&"!$H:$H")>=L6),INDIRECT($R$1&"!$L:$L"))))} -> 28.35 | P6: {=(_xlfn.SINGLE(_xlfn.XLOOKUP(1,(INDIRECT($R$1&"!$C:$C")=B6)*(INDIRECT($R$1&"!$G:$G")<M6)*(INDIRECT($R$1&"!$H:$H")>=M6),INDIRECT($R$1&"!$K:$K"))))*M6+(_xlfn.SINGLE(_xlfn.XLOOKUP(1,(INDIRECT($R$1&"!$C:$C")=B6)*(INDIRECT($R$1&"!$G:$G")<M6)*(INDIRECT($R$1&"!$H:$H")>=M6),INDIRECT($R$1&"!$L:$L"))))} -> 37.7 | Q6: {=(_xlfn.SINGLE(_xlfn.XLOOKUP(1,(INDIRECT($R$1&"!$C:$C")=B6)*(INDIRECT($R$1&"!$G:$G")<N6)*(INDIRECT($R$1&"!$H:$H")>=N6),INDIRECT($R$1&"!$K:$K"))))*N6+(_xlfn.SINGLE(_xlfn.XLOOKUP(1,(INDIRECT($R$1&"!$C:$C")=B6)*(INDIRECT($R$1&"!$G:$G")<N6)*(INDIRECT($R$1&"!$H:$H")>=N6),INDIRECT($R$1&"!$L:$L"))))} -> 47.05
A7: 奥地利 | B7: AT | C7: =(F7+I7)*(1+$F$1) -> 7.5728873 | D7: =(G7+J7)*(1+$F$1) -> 10.926056 | E7: =(H7+K7)*(1+$F$1) -> 14.279225 | F7: =O7/$P$1 -> 5.1056338 | G7: =P7/$P$1 -> 6.2676056 | H7: =Q7/$P$1 -> 7.4295775 | I7: =(VLOOKUP($B$1,'Product Procurement Sheet'!B:I,8,0)*$L$1)/$P$1 -> 1.971831 | J7: =(VLOOKUP($B$1,'Product Procurement Sheet'!B:I,8,0)*$M$1)/$P$1 -> 3.943662 | K7: =(VLOOKUP($B$1,'Product Procurement Sheet'!B:I,8,0)*$N$1)/$P$1 -> 5.915493 | L7: =VLOOKUP($B$1,'Product Procurement Sheet'!B:D,3,FALSE)*$L$1 -> 0.11 | M7: =VLOOKUP($B$1,'Product Procurement Sheet'!B:D,3,FALSE)*$M$1 -> 0.22 | N7: =VLOOKUP($B$1,'Product Procurement Sheet'!B:D,3,FALSE)*$N$1 -> 0.33 | O7: {=(_xlfn.SINGLE(_xlfn.XLOOKUP(1,(INDIRECT($R$1&"!$C:$C")=B7)*(INDIRECT($R$1&"!$G:$G")<L7)*(INDIRECT($R$1&"!$H:$H")>=L7),INDIRECT($R$1&"!$K:$K"))))*L7+(_xlfn.SINGLE(_xlfn.XLOOKUP(1,(INDIRECT($R$1&"!$C:$C")=B7)*(INDIRECT($R$1&"!$G:$G")<L7)*(INDIRECT($R$1&"!$H:$H")>=L7),INDIRECT($R$1&"!$L:$L"))))} -> 36.25 | P7: {=(_xlfn.SINGLE(_xlfn.XLOOKUP(1,(INDIRECT($R$1&"!$C:$C")=B7)*(INDIRECT($R$1&"!$G:$G")<M7)*(INDIRECT($R$1&"!$H:$H")>=M7),INDIRECT($R$1&"!$K:$K"))))*M7+(_xlfn.SINGLE(_xlfn.XLOOKUP(1,(INDIRECT($R$1&"!$C:$C")=B7)*(INDIRECT($R$1&"!$G:$G")<M7)*(INDIRECT($R$1&"!$H:$H")>=M7),INDIRECT($R$1&"!$L:$L"))))} -> 44.5 | Q7: {=(_xlfn.SINGLE(_xlfn.XLOOKUP(1,(INDIRECT($R$1&"!$C:$C")=B7)*(INDIRECT($R$1&"!$G:$G")<N7)*(INDIRECT($R$1&"!$H:$H")>=N7),INDIRECT($R$1&"!$K:$K"))))*N7+(_xlfn.SINGLE(_xlfn.XLOOKUP(1,(INDIRECT($R$1&"!$C:$C")=B7)*(INDIRECT($R$1&"!$G:$G")<N7)*(INDIRECT($R$1&"!$H:$H")>=N7),INDIRECT($R$1&"!$L:$L"))))} -> 52.75
A8: 意大利 | B8: IT | C8: =(F8+I8)*(1+$F$1) -> 7.1057042 | D8: =(G8+J8)*(1+$F$1) -> 10.293099 | E8: =(H8+K8)*(1+$F$1) -> 13.480493 | F8: =O8/$P$1 -> 4.6690141 | G8: =P8/$P$1 -> 5.6760563 | H8: =Q8/$P$1 -> 6.6830986 | I8: =(VLOOKUP($B$1,'Product Procurement Sheet'!B:I,8,0)*$L$1)/$P$1 -> 1.971831 | J8: =(VLOOKUP($B$1,'Product Procurement Sheet'!B:I,8,0)*$M$1)/$P$1 -> 3.943662 | K8: =(VLOOKUP($B$1,'Product Procurement Sheet'!B:I,8,0)*$N$1)/$P$1 -> 5.915493 | L8: =VLOOKUP($B$1,'Product Procurement Sheet'!B:D,3,FALSE)*$L$1 -> 0.11 | M8: =VLOOKUP($B$1,'Product Procurement Sheet'!B:D,3,FALSE)*$M$1 -> 0.22 | N8: =VLOOKUP($B$1,'Product Procurement Sheet'!B:D,3,FALSE)*$N$1 -> 0.33 | O8: {=(_xlfn.SINGLE(_xlfn.XLOOKUP(1,(INDIRECT($R$1&"!$C:$C")=B8)*(INDIRECT($R$1&"!$G:$G")<L8)*(INDIRECT($R$1&"!$H:$H")>=L8),INDIRECT($R$1&"!$K:$K"))))*L8+(_xlfn.SINGLE(_xlfn.XLOOKUP(1,(INDIRECT($R$1&"!$C:$C")=B8)*(INDIRECT($R$1&"!$G:$G")<L8)*(INDIRECT($R$1&"!$H:$H")>=L8),INDIRECT($R$1&"!$L:$L"))))} -> 33.15 | P8: {=(_xlfn.SINGLE(_xlfn.XLOOKUP(1,(INDIRECT($R$1&"!$C:$C")=B8)*(INDIRECT($R$1&"!$G:$G")<M8)*(INDIRECT($R$1&"!$H:$H")>=M8),INDIRECT($R$1&"!$K:$K"))))*M8+(_xlfn.SINGLE(_xlfn.XLOOKUP(1,(INDIRECT($R$1&"!$C:$C")=B8)*(INDIRECT($R$1&"!$G:$G")<M8)*(INDIRECT($R$1&"!$H:$H")>=M8),INDIRECT($R$1&"!$L:$L"))))} -> 40.3 | Q8: {=(_xlfn.SINGLE(_xlfn.XLOOKUP(1,(INDIRECT($R$1&"!$C:$C")=B8)*(INDIRECT($R$1&"!$G:$G")<N8)*(INDIRECT($R$1&"!$H:$H")>=N8),INDIRECT($R$1&"!$K:$K"))))*N8+(_xlfn.SINGLE(_xlfn.XLOOKUP(1,(INDIRECT($R$1&"!$C:$C")=B8)*(INDIRECT($R$1&"!$G:$G")<N8)*(INDIRECT($R$1&"!$H:$H")>=N8),INDIRECT($R$1&"!$L:$L"))))} -> 47.45
A9: 西班牙 | B9: ES | C9: =(F9+I9)*(1+$F$1) -> 5.9000704 | D9: =(G9+J9)*(1+$F$1) -> 9.0874648 | E9: =(H9+K9)*(1+$F$1) -> 12.274859 | F9: =O9/$P$1 -> 3.5422535 | G9: =P9/$P$1 -> 4.5492958 | H9: =Q9/$P$1 -> 5.556338 | I9: =(VLOOKUP($B$1,'Product Procurement Sheet'!B:I,8,0)*$L$1)/$P$1 -> 1.971831 | J9: =(VLOOKUP($B$1,'Product Procurement Sheet'!B:I,8,0)*$M$1)/$P$1 -> 3.943662 | K9: =(VLOOKUP($B$1,'Product Procurement Sheet'!B:I,8,0)*$N$1)/$P$1 -> 5.915493 | L9: =VLOOKUP($B$1,'Product Procurement Sheet'!B:D,3,FALSE)*$L$1 -> 0.11 | M9: =VLOOKUP($B$1,'Product Procurement Sheet'!B:D,3,FALSE)*$M$1 -> 0.22 | N9: =VLOOKUP($B$1,'Product Procurement Sheet'!B:D,3,FALSE)*$N$1 -> 0.33 | O9: {=(_xlfn.SINGLE(_xlfn.XLOOKUP(1,(INDIRECT($R$1&"!$C:$C")=B9)*(INDIRECT($R$1&"!$G:$G")<L9)*(INDIRECT($R$1&"!$H:$H")>=L9),INDIRECT($R$1&"!$K:$K"))))*L9+(_xlfn.SINGLE(_xlfn.XLOOKUP(1,(INDIRECT($R$1&"!$C:$C")=B9)*(INDIRECT($R$1&"!$G:$G")<L9)*(INDIRECT($R$1&"!$H:$H")>=L9),INDIRECT($R$1&"!$L:$L"))))} -> 25.15 | P9: {=(_xlfn.SINGLE(_xlfn.XLOOKUP(1,(INDIRECT($R$1&"!$C:$C")=B9)*(INDIRECT($R$1&"!$G:$G")<M9)*(INDIRECT($R$1&"!$H:$H")>=M9),INDIRECT($R$1&"!$K:$K"))))*M9+(_xlfn.SINGLE(_xlfn.XLOOKUP(1,(INDIRECT($R$1&"!$C:$C")=B9)*(INDIRECT($R$1&"!$G:$G")<M9)*(INDIRECT($R$1&"!$H:$H")>=M9),INDIRECT($R$1&"!$L:$L"))))} -> 32.3 | Q9: {=(_xlfn.SINGLE(_xlfn.XLOOKUP(1,(INDIRECT($R$1&"!$C:$C")=B9)*(INDIRECT($R$1&"!$G:$G")<N9)*(INDIRECT($R$1&"!$H:$H")>=N9),INDIRECT($R$1&"!$K:$K"))))*N9+(_xlfn.SINGLE(_xlfn.XLOOKUP(1,(INDIRECT($R$1&"!$C:$C")=B9)*(INDIRECT($R$1&"!$G:$G")<N9)*(INDIRECT($R$1&"!$H:$H")>=N9),INDIRECT($R$1&"!$L:$L"))))} -> 39.45
A10: 比利时 | B10: BE | C10: =(F10+I10)*(1+$F$1) -> 7.0152817 | D10: =(G10+J10)*(1+$F$1) -> 10.865775 | E10: =(H10+K10)*(1+$F$1) -> 14.716268 | F10: =O10/$P$1 -> 4.584507 | G10: =P10/$P$1 -> 6.2112676 | H10: =Q10/$P$1 -> 7.8380282 | I10: =(VLOOKUP($B$1,'Product Procurement Sheet'!B:I,8,0)*$L$1)/$P$1 -> 1.971831 | J10: =(VLOOKUP($B$1,'Product Procurement Sheet'!B:I,8,0)*$M$1)/$P$1 -> 3.943662 | K10: =(VLOOKUP($B$1,'Product Procurement Sheet'!B:I,8,0)*$N$1)/$P$1 -> 5.915493 | L10: =VLOOKUP($B$1,'Product Procurement Sheet'!B:D,3,FALSE)*$L$1 -> 0.11 | M10: =VLOOKUP($B$1,'Product Procurement Sheet'!B:D,3,FALSE)*$M$1 -> 0.22 | N10: =VLOOKUP($B$1,'Product Procurement Sheet'!B:D,3,FALSE)*$N$1 -> 0.33 | O10: {=(_xlfn.SINGLE(_xlfn.XLOOKUP(1,(INDIRECT($R$1&"!$C:$C")=B10)*(INDIRECT($R$1&"!$G:$G")<L10)*(INDIRECT($R$1&"!$H:$H")>=L10),INDIRECT($R$1&"!$K:$K"))))*L10+(_xlfn.SINGLE(_xlfn.XLOOKUP(1,(INDIRECT($R$1&"!$C:$C")=B10)*(INDIRECT($R$1&"!$G:$G")<L10)*(INDIRECT($R$1&"!$H:$H")>=L10),INDIRECT($R$1&"!$L:$L"))))} -> 32.55 | P10: {=(_xlfn.SINGLE(_xlfn.XLOOKUP(1,(INDIRECT($R$1&"!$C:$C")=B10)*(INDIRECT($R$1&"!$G:$G")<M10)*(INDIRECT($R$1&"!$H:$H")>=M10),INDIRECT($R$1&"!$K:$K"))))*M10+(_xlfn.SINGLE(_xlfn.XLOOKUP(1,(INDIRECT($R$1&"!$C:$C")=B10)*(INDIRECT($R$1&"!$G:$G")<M10)*(INDIRECT($R$1&"!$H:$H")>=M10),INDIRECT($R$1&"!$L:$L"))))} -> 44.1 | Q10: {=(_xlfn.SINGLE(_xlfn.XLOOKUP(1,(INDIRECT($R$1&"!$C:$C")=B10)*(INDIRECT($R$1&"!$G:$G")<N10)*(INDIRECT($R$1&"!$H:$H")>=N10),INDIRECT($R$1&"!$K:$K"))))*N10+(_xlfn.SINGLE(_xlfn.XLOOKUP(1,(INDIRECT($R$1&"!$C:$C")=B10)*(INDIRECT($R$1&"!$G:$G")<N10)*(INDIRECT($R$1&"!$H:$H")>=N10),INDIRECT($R$1&"!$L:$L"))))} -> 55.65
A11: 瑞士 | B11: CH | C11: =(F11+I11)*(1+$F$1) -> 7.1057042 | D11: =(G11+J11)*(1+$F$1) -> 10.293099 | E11: =(H11+K11)*(1+$F$1) -> 13.480493 | F11: =O11/$P$1 -> 4.6690141 | G11: =P11/$P$1 -> 5.6760563 | H11: =Q11/$P$1 -> 6.6830986 | I11: =(VLOOKUP($B$1,'Product Procurement Sheet'!B:I,8,0)*$L$1)/$P$1 -> 1.971831 | J11: =(VLOOKUP($B$1,'Product Procurement Sheet'!B:I,8,0)*$M$1)/$P$1 -> 3.943662 | K11: =(VLOOKUP($B$1,'Product Procurement Sheet'!B:I,8,0)*$N$1)/$P$1 -> 5.915493 | L11: =VLOOKUP($B$1,'Product Procurement Sheet'!B:D,3,FALSE)*$L$1 -> 0.11 | M11: =VLOOKUP($B$1,'Product Procurement Sheet'!B:D,3,FALSE)*$M$1 -> 0.22 | N11: =VLOOKUP($B$1,'Product Procurement Sheet'!B:D,3,FALSE)*$N$1 -> 0.33 | O11: {=(_xlfn.SINGLE(_xlfn.XLOOKUP(1,(INDIRECT($R$1&"!$C:$C")=B11)*(INDIRECT($R$1&"!$G:$G")<L11)*(INDIRECT($R$1&"!$H:$H")>=L11),INDIRECT($R$1&"!$K:$K"))))*L11+(_xlfn.SINGLE(_xlfn.XLOOKUP(1,(INDIRECT($R$1&"!$C:$C")=B11)*(INDIRECT($R$1&"!$G:$G")<L11)*(INDIRECT($R$1&"!$H:$H")>=L11),INDIRECT($R$1&"!$L:$L"))))} -> 33.15 | P11: {=(_xlfn.SINGLE(_xlfn.XLOOKUP(1,(INDIRECT($R$1&"!$C:$C")=B11)*(INDIRECT($R$1&"!$G:$G")<M11)*(INDIRECT($R$1&"!$H:$H")>=M11),INDIRECT($R$1&"!$K:$K"))))*M11+(_xlfn.SINGLE(_xlfn.XLOOKUP(1,(INDIRECT($R$1&"!$C:$C")=B11)*(INDIRECT($R$1&"!$G:$G")<M11)*(INDIRECT($R$1&"!$H:$H")>=M11),INDIRECT($R$1&"!$L:$L"))))} -> 40.3 | Q11: {=(_xlfn.SINGLE(_xlfn.XLOOKUP(1,(INDIRECT($R$1&"!$C:$C")=B11)*(INDIRECT($R$1&"!$G:$G")<N11)*(INDIRECT($R$1&"!$H:$H")>=N11),INDIRECT($R$1&"!$K:$K"))))*N11+(_xlfn.SINGLE(_xlfn.XLOOKUP(1,(INDIRECT($R$1&"!$C:$C")=B11)*(INDIRECT($R$1&"!$G:$G")<N11)*(INDIRECT($R$1&"!$H:$H")>=N11),INDIRECT($R$1&"!$L:$L"))))} -> 47.45
A12: 卢森堡 | B12: LU | C12: =(F12+I12)*(1+$F$1) -> 7.5728873 | D12: =(G12+J12)*(1+$F$1) -> 10.926056 | E12: =(H12+K12)*(1+$F$1) -> 14.279225 | F12: =O12/$P$1 -> 5.1056338 | G12: =P12/$P$1 -> 6.2676056 | H12: =Q12/$P$1 -> 7.4295775 | I12: =(VLOOKUP($B$1,'Product Procurement Sheet'!B:I,8,0)*$L$1)/$P$1 -> 1.971831 | J12: =(VLOOKUP($B$1,'Product Procurement Sheet'!B:I,8,0)*$M$1)/$P$1 -> 3.943662 | K12: =(VLOOKUP($B$1,'Product Procurement Sheet'!B:I,8,0)*$N$1)/$P$1 -> 5.915493 | L12: =VLOOKUP($B$1,'Product Procurement Sheet'!B:D,3,FALSE)*$L$1 -> 0.11 | M12: =VLOOKUP($B$1,'Product Procurement Sheet'!B:D,3,FALSE)*$M$1 -> 0.22 | N12: =VLOOKUP($B$1,'Product Procurement Sheet'!B:D,3,FALSE)*$N$1 -> 0.33 | O12: {=(_xlfn.SINGLE(_xlfn.XLOOKUP(1,(INDIRECT($R$1&"!$C:$C")=B12)*(INDIRECT($R$1&"!$G:$G")<L12)*(INDIRECT($R$1&"!$H:$H")>=L12),INDIRECT($R$1&"!$K:$K"))))*L12+(_xlfn.SINGLE(_xlfn.XLOOKUP(1,(INDIRECT($R$1&"!$C:$C")=B12)*(INDIRECT($R$1&"!$G:$G")<L12)*(INDIRECT($R$1&"!$H:$H")>=L12),INDIRECT($R$1&"!$L:$L"))))} -> 36.25 | P12: {=(_xlfn.SINGLE(_xlfn.XLOOKUP(1,(INDIRECT($R$1&"!$C:$C")=B12)*(INDIRECT($R$1&"!$G:$G")<M12)*(INDIRECT($R$1&"!$H:$H")>=M12),INDIRECT($R$1&"!$K:$K"))))*M12+(_xlfn.SINGLE(_xlfn.XLOOKUP(1,(INDIRECT($R$1&"!$C:$C")=B12)*(INDIRECT($R$1&"!$G:$G")<M12)*(INDIRECT($R$1&"!$H:$H")>=M12),INDIRECT($R$1&"!$L:$L"))))} -> 44.5 | Q12: {=(_xlfn.SINGLE(_xlfn.XLOOKUP(1,(INDIRECT($R$1&"!$C:$C")=B12)*(INDIRECT($R$1&"!$G:$G")<N12)*(INDIRECT($R$1&"!$H:$H")>=N12),INDIRECT($R$1&"!$K:$K"))))*N12+(_xlfn.SINGLE(_xlfn.XLOOKUP(1,(INDIRECT($R$1&"!$C:$C")=B12)*(INDIRECT($R$1&"!$G:$G")<N12)*(INDIRECT($R$1&"!$H:$H")>=N12),INDIRECT($R$1&"!$L:$L"))))} -> 52.75
A13: 爱尔兰 | B13: IE | C13: =(F13+I13)*(1+$F$1) -> 6.955 | D13: =(G13+J13)*(1+$F$1) -> 10.142394 | E13: =(H13+K13)*(1+$F$1) -> 13.329789 | F13: =O13/$P$1 -> 4.528169 | G13: =P13/$P$1 -> 5.5352113 | H13: =Q13/$P$1 -> 6.5422535 | I13: =(VLOOKUP($B$1,'Product Procurement Sheet'!B:I,8,0)*$L$1)/$P$1 -> 1.971831 | J13: =(VLOOKUP($B$1,'Product Procurement Sheet'!B:I,8,0)*$M$1)/$P$1 -> 3.943662 | K13: =(VLOOKUP($B$1,'Product Procurement Sheet'!B:I,8,0)*$N$1)/$P$1 -> 5.915493 | L13: =VLOOKUP($B$1,'Product Procurement Sheet'!B:D,3,FALSE)*$L$1 -> 0.11 | M13: =VLOOKUP($B$1,'Product Procurement Sheet'!B:D,3,FALSE)*$M$1 -> 0.22 | N13: =VLOOKUP($B$1,'Product Procurement Sheet'!B:D,3,FALSE)*$N$1 -> 0.33 | O13: {=(_xlfn.SINGLE(_xlfn.XLOOKUP(1,(INDIRECT($R$1&"!$C:$C")=B13)*(INDIRECT($R$1&"!$G:$G")<L13)*(INDIRECT($R$1&"!$H:$H")>=L13),INDIRECT($R$1&"!$K:$K"))))*L13+(_xlfn.SINGLE(_xlfn.XLOOKUP(1,(INDIRECT($R$1&"!$C:$C")=B13)*(INDIRECT($R$1&"!$G:$G")<L13)*(INDIRECT($R$1&"!$H:$H")>=L13),INDIRECT($R$1&"!$L:$L"))))} -> 32.15 | P13: {=(_xlfn.SINGLE(_xlfn.XLOOKUP(1,(INDIRECT($R$1&"!$C:$C")=B13)*(INDIRECT($R$1&"!$G:$G")<M13)*(INDIRECT($R$1&"!$H:$H")>=M13),INDIRECT($R$1&"!$K:$K"))))*M13+(_xlfn.SINGLE(_xlfn.XLOOKUP(1,(INDIRECT($R$1&"!$C:$C")=B13)*(INDIRECT($R$1&"!$G:$G")<M13)*(INDIRECT($R$1&"!$H:$H")>=M13),INDIRECT($R$1&"!$L:$L"))))} -> 39.3 | Q13: {=(_xlfn.SINGLE(_xlfn.XLOOKUP(1,(INDIRECT($R$1&"!$C:$C")=B13)*(INDIRECT($R$1&"!$G:$G")<N13)*(INDIRECT($R$1&"!$H:$H")>=N13),INDIRECT($R$1&"!$K:$K"))))*N13+(_xlfn.SINGLE(_xlfn.XLOOKUP(1,(INDIRECT($R$1&"!$C:$C")=B13)*(INDIRECT($R$1&"!$G:$G")<N13)*(INDIRECT($R$1&"!$H:$H")>=N13),INDIRECT($R$1&"!$L:$L"))))} -> 46.45
A14: 保加利亚 | B14: BG | C14: =(F14+I14)*(1+$F$1) -> 4.7245775 | D14: =(G14+J14)*(1+$F$1) -> 8.2435211 | E14: =(H14+K14)*(1+$F$1) -> 11.762465 | F14: =O14/$P$1 -> 2.443662 | G14: =P14/$P$1 -> 3.7605634 | H14: =Q14/$P$1 -> 5.0774648 | I14: =(VLOOKUP($B$1,'Product Procurement Sheet'!B:I,8,0)*$L$1)/$P$1 -> 1.971831 | J14: =(VLOOKUP($B$1,'Product Procurement Sheet'!B:I,8,0)*$M$1)/$P$1 -> 3.943662 | K14: =(VLOOKUP($B$1,'Product Procurement Sheet'!B:I,8,0)*$N$1)/$P$1 -> 5.915493 | L14: =VLOOKUP($B$1,'Product Procurement Sheet'!B:D,3,FALSE)*$L$1 -> 0.11 | M14: =VLOOKUP($B$1,'Product Procurement Sheet'!B:D,3,FALSE)*$M$1 -> 0.22 | N14: =VLOOKUP($B$1,'Product Procurement Sheet'!B:D,3,FALSE)*$N$1 -> 0.33 | O14: {=(_xlfn.SINGLE(_xlfn.XLOOKUP(1,(INDIRECT($R$1&"!$C:$C")=B14)*(INDIRECT($R$1&"!$G:$G")<L14)*(INDIRECT($R$1&"!$H:$H")>=L14),INDIRECT($R$1&"!$K:$K"))))*L14+(_xlfn.SINGLE(_xlfn.XLOOKUP(1,(INDIRECT($R$1&"!$C:$C")=B14)*(INDIRECT($R$1&"!$G:$G")<L14)*(INDIRECT($R$1&"!$H:$H")>=L14),INDIRECT($R$1&"!$L:$L"))))} -> 17.35 | P14: {=(_xlfn.SINGLE(_xlfn.XLOOKUP(1,(INDIRECT($R$1&"!$C:$C")=B14)*(INDIRECT($R$1&"!$G:$G")<M14)*(INDIRECT($R$1&"!$H:$H")>=M14),INDIRECT($R$1&"!$K:$K"))))*M14+(_xlfn.SINGLE(_xlfn.XLOOKUP(1,(INDIRECT($R$1&"!$C:$C")=B14)*(INDIRECT($R$1&"!$G:$G")<M14)*(INDIRECT($R$1&"!$H:$H")>=M14),INDIRECT($R$1&"!$L:$L"))))} -> 26.7 | Q14: {=(_xlfn.SINGLE(_xlfn.XLOOKUP(1,(INDIRECT($R$1&"!$C:$C")=B14)*(INDIRECT($R$1&"!$G:$G")<N14)*(INDIRECT($R$1&"!$H:$H")>=N14),INDIRECT($R$1&"!$K:$K"))))*N14+(_xlfn.SINGLE(_xlfn.XLOOKUP(1,(INDIRECT($R$1&"!$C:$C")=B14)*(INDIRECT($R$1&"!$G:$G")<N14)*(INDIRECT($R$1&"!$H:$H")>=N14),INDIRECT($R$1&"!$L:$L"))))} -> 36.05
A15: 克罗地亚 | B15: CRO | C15: =(F15+I15)*(1+$F$1) -> #N/A | D15: =(G15+J15)*(1+$F$1) -> #N/A | E15: =(H15+K15)*(1+$F$1) -> #N/A | F15: =O15/$P$1 -> #N/A | G15: =P15/$P$1 -> #N/A | H15: =Q15/$P$1 -> #N/A | I15: =(VLOOKUP($B$1,'Product Procurement Sheet'!B:I,8,0)*$L$1)/$P$1 -> 1.971831 | J15: =(VLOOKUP($B$1,'Product Procurement Sheet'!B:I,8,0)*$M$1)/$P$1 -> 3.943662 | K15: =(VLOOKUP($B$1,'Product Procurement Sheet'!B:I,8,0)*$N$1)/$P$1 -> 5.915493 | L15: =VLOOKUP($B$1,'Product Procurement Sheet'!B:D,3,FALSE)*$L$1 -> 0.11 | M15: =VLOOKUP($B$1,'Product Procurement Sheet'!B:D,3,FALSE)*$M$1 -> 0.22 | N15: =VLOOKUP($B$1,'Product Procurement Sheet'!B:D,3,FALSE)*$N$1 -> 0.33 | O15: {=(_xlfn.SINGLE(_xlfn.XLOOKUP(1,(INDIRECT($R$1&"!$C:$C")=B15)*(INDIRECT($R$1&"!$G:$G")<L15)*(INDIRECT($R$1&"!$H:$H")>=L15),INDIRECT($R$1&"!$K:$K"))))*L15+(_xlfn.SINGLE(_xlfn.XLOOKUP(1,(INDIRECT($R$1&"!$C:$C")=B15)*(INDIRECT($R$1&"!$G:$G")<L15)*(INDIRECT($R$1&"!$H:$H")>=L15),INDIRECT($R$1&"!$L:$L"))))} -> #N/A | P15: {=(_xlfn.SINGLE(_xlfn.XLOOKUP(1,(INDIRECT($R$1&"!$C:$C")=B15)*(INDIRECT($R$1&"!$G:$G")<M15)*(INDIRECT($R$1&"!$H:$H")>=M15),INDIRECT($R$1&"!$K:$K"))))*M15+(_xlfn.SINGLE(_xlfn.XLOOKUP(1,(INDIRECT($R$1&"!$C:$C")=B15)*(INDIRECT($R$1&"!$G:$G")<M15)*(INDIRECT($R$1&"!$H:$H")>=M15),INDIRECT($R$1&"!$L:$L"))))} -> #N/A | Q15: {=(_xlfn.SINGLE(_xlfn.XLOOKUP(1,(INDIRECT($R$1&"!$C:$C")=B15)*(INDIRECT($R$1&"!$G:$G")<N15)*(INDIRECT($R$1&"!$H:$H")>=N15),INDIRECT($R$1&"!$K:$K"))))*N15+(_xlfn.SINGLE(_xlfn.XLOOKUP(1,(INDIRECT($R$1&"!$C:$C")=B15)*(INDIRECT($R$1&"!$G:$G")<N15)*(INDIRECT($R$1&"!$H:$H")>=N15),INDIRECT($R$1&"!$L:$L"))))} -> #N/A
... A221: 俄罗斯 | B221: RU | C221: =(F221+I221)*(1+$F$1) -> 4.3478169 | D221: =(G221+J221)*(1+$F$1) -> 7.0378873 | E221: =(H221+K221)*(1+$F$1) -> 9.7279577 | F221: =O221/$P$1 -> 2.0915493 | G221: =P221/$P$1 -> 2.6338028 | H221: =Q221/$P$1 -> 3.1760563 | I221: =(VLOOKUP($B$1,'Product Procurement Sheet'!B:I,8,0)*$L$1)/$P$1 -> 1.971831 | J221: =(VLOOKUP($B$1,'Product Procurement Sheet'!B:I,8,0)*$M$1)/$P$1 -> 3.943662 | K221: =(VLOOKUP($B$1,'Product Procurement Sheet'!B:I,8,0)*$N$1)/$P$1 -> 5.915493 | L221: =VLOOKUP($B$1,'Product Procurement Sheet'!B:D,3,FALSE)*$L$1 -> 0.11 | M221: =VLOOKUP($B$1,'Product Procurement Sheet'!B:D,3,FALSE)*$M$1 -> 0.22 | N221: =VLOOKUP($B$1,'Product Procurement Sheet'!B:D,3,FALSE)*$N$1 -> 0.33 | O221: {=(_xlfn.SINGLE(_xlfn.XLOOKUP(1,(INDIRECT($R$1&"!$C:$C")=B221)*(INDIRECT($R$1&"!$G:$G")<L221)*(INDIRECT($R$1&"!$H:$H")>=L221),INDIRECT($R$1&"!$K:$K"))))*L221+(_xlfn.SINGLE(_xlfn.XLOOKUP(1,(INDIRECT($R$1&"!$C:$C")=B221)*(INDIRECT($R$1&"!$G:$G")<L221)*(INDIRECT($R$1&"!$H:$H")>=L221),INDIRECT($R$1&"!$L:$L"))))} -> 14.85 | P221: {=(_xlfn.SINGLE(_xlfn.XLOOKUP(1,(INDIRECT($R$1&"!$C:$C")=B221)*(INDIRECT($R$1&"!$G:$G")<M221)*(INDIRECT($R$1&"!$H:$H")>=M221),INDIRECT($R$1&"!$K:$K"))))*M221+(_xlfn.SINGLE(_xlfn.XLOOKUP(1,(INDIRECT($R$1&"!$C:$C")=B221)*(INDIRECT($R$1&"!$G:$G")<M221)*(INDIRECT($R$1&"!$H:$H")>=M221),INDIRECT($R$1&"!$L:$L"))))} -> 18.7 | Q221: {=(_xlfn.SINGLE(_xlfn.XLOOKUP(1,(INDIRECT($R$1&"!$C:$C")=B221)*(INDIRECT($R$1&"!$G:$G")<N221)*(INDIRECT($R$1&"!$H:$H")>=N221),INDIRECT($R$1&"!$K:$K"))))*N221+(_xlfn.SINGLE(_xlfn.XLOOKUP(1,(INDIRECT($R$1&"!$C:$C")=B221)*(INDIRECT($R$1&"!$G:$G")<N221)*(INDIRECT($R$1&"!$H:$H")>=N221),INDIRECT($R$1&"!$L:$L"))))} -> 22.55

Sheet Product Procurement Sheet
A1: 产品名字（Product name） | B1: 产品编码Product type | C1: 产品图片Product image | D1: 计算重量Calculate weight | E1: unit weight单个重量KG | F1: 材积重Volume weight | G1: 包装尺寸Size | H1: 产品尺寸 | I1: unit price商品价格 | J1: shipping fee to warehouse报价运费 | K1: Real shipping cost真实运费 | L1: Client name客户名称 | M1: 报价产品参考链接Quote product reference link | N1: 颜色color | O1: 英文标题English title | P1: 1688link链接 | Q1: 报价员 | R1: 是否在售
A2: Electric Guasha Scraping Massage Tool | B2: EQU0530001A | C2: =_xlfn.DISPIMG("ID_3364B878065D4633BFDA16464000B2C5",1) -> =DISPIMG("ID_3364B878065D4633BFDA16464000B2C5",1) | D2: =MAX(E2,F2) -> 0.49 | E2: 0.49 | F2: =15*15*12/8000 -> 0.3375 | G2: 72.5*19*44cm | H2: 13*12cm | I2: =K2+J2 -> 55 | J2: 55 | K2: 0 | M2: 下单后2天左右发货 | P2: https://detail.1688.com/offer/667310265863.html?spm=a26352.b28411319.offerlist.16.1e291e62ZadNuJ | R2: =_xlfn.DISPIMG("ID_E506C151F08B445E982424171EA278F5",1) -> =DISPIMG("ID_E506C151F08B445E982424171EA278F5",1) | S2: =_xlfn.DISPIMG("ID_9060D06700234D73A40A37F2370E2234",1) -> =DISPIMG("ID_9060D06700234D73A40A37F2370E2234",1) | T2: =_xlfn.DISPIMG("ID_0489DDD773654DA19EF5D2F7E6CFF583",1) -> =DISPIMG("ID_0489DDD773654DA19EF5D2F7E6CFF583",1)
B3: EQU0530002A | D3: =MAX(E3,F3) -> 0.49 | E3: 0.49 | F3: =15*15*12/8000 -> 0.3375 | G3: 72.5*19*44cm | H3: 13*12cm | I3: =K3+J3 -> 52 | J3: 52 | K3: 0
B4: EQU0530001B | C4: 捆绑价格 | D4: =MAX(E4,F4) -> 0.59 | E4: =0.1+E2 -> 0.59 | F4: =17*17*11/8000 -> 0.397375 | G4: 17*17*11cm | I4: 57 | J4: 60
B5: EQU0530002B | C5: 1+A | D5: =MAX(E5,F5) -> 0.59 | E5: =0.1+E3 -> 0.59 | F5: =17*17*11/8000 -> 0.397375 | I5: 60 | J5: 57
B6: EQU0530001C | C6: 1+2A | D6: =MAX(E6,F6) -> 1.404 | E6: =0.65 -> 0.65 | F6: =26*18*15/5000 -> 1.404 | G6: 26*18*15 | I6: 65
B7: EQU0530002C | D7: =MAX(E7,F7) -> 1.404 | E7: =0.65 -> 0.65 | F7: =26*18*15/5000 -> 1.404 | I7: 72
B8: EQU0530001D | D8: =MAX(E8,F8) -> 0 | I8: 73 | J8: 68
B9: EQU0530002D | D9: =MAX(E9,F9) -> 0 | I9: 80 | J9: 65
D10: =MAX(E10,F10) -> 0
D11: =MAX(E11,F11) -> 0
D12: =MAX(E12,F12) -> 0
D13: =MAX(E13,F13) -> 0
B14: E001 | C14: 1+1纸箱 | D14: =MAX(E14,F14) -> 1.4976 | E14: 0.58 | F14: =16*26*18/5000 -> 1.4976 | G14: 16*26*18 | I14: 60
B15: ZK001 | C15: 折扣 | D15: =MAX(E15,F15) -> 1.4976 | E15: 0.58 | F15: =16*26*18/5000 -> 1.4976 | G15: 16*26*18 | I15: 57
B16: E002 | C16: 1+2纸箱 | D16: =MAX(E16,F16) -> 1.4976 | E16: 0.65 | F16: =16*26*18/5000 -> 1.4976 | I16: 65
B17: ZK002 | C17: 折扣 | D17: =MAX(E17,F17) -> 1.4976 | E17: 0.65 | F17: =16*26*18/5000 -> 1.4976 | I17: 62
B18: E003 | C18: 1+1气泡袋 | D18: =MAX(E18,F18) -> 0.8228 | E18: 0.55 | F18: =22*11*17/5000 -> 0.8228 | I18: 60
A19: ZK003 | B19: ZK003 | C19: 折扣 | D19: =MAX(E19,F19) -> 0.8228 | E19: 0.55 | F19: =22*11*17/5000 -> 0.8228 | I19: 57
A20: ZK004 | B20: E004 | C20: 1+2气泡袋 | D20: =MAX(E20,F20) -> 0.8228 | E20: 0.6 | F20: =22*11*17/5000 -> 0.8228 | I20: 65
A21: ZK005 | B21: ZK004 | C21: 折扣 | D21: =MAX(E21,F21) -> 0.8228 | E21: 0.6 | F21: =22*11*17/5000 -> 0.8228 | I21: 62
A22: ZK006 | B22: E005 | C22: 1+1塑料袋 | D22: =MAX(E22,F22) -> 0.9936 | E22: 0.57 | F22: =23*12*18/5000 -> 0.9936 | I22: 60
B23: ZK005 | C23: 折扣 | D23: =MAX(E23,F23) -> 0.9936 | E23: 0.57 | F23: =23*12*18/5000 -> 0.9936 | I23: 57
B24: E006 | C24: 1+2塑料袋 | D24: =MAX(E24,F24) -> 0.9936 | E24: 0.64 | F24: =23*12*18/5000 -> 0.9936 | I24: 65
B25: ZK006 | C25: 折扣 | D25: =MAX(E25,F25) -> 0.9936 | E25: 0.64 | F25: =23*12*18/5000 -> 0.9936 | I25: 62
A26: Oil of Oregano | B26: 相似款 | C26: =_xlfn.DISPIMG("ID_4CEC0291335C40FEA5F4AE73D1DA7B81",1) -> =DISPIMG("ID_4CEC0291335C40FEA5F4AE73D1DA7B81",1) | D26: =MAX(E26,F26) -> 0.11 | E26: 0.11 | G26: 高19.5宽13.5cm | I26: =K26+J26 -> 46 | J26: 38 | K26: 8 | M26: https://resilia.shop/collections/best-sellers/products/resilia%E2%84%A2-oil-of-oregano-softgels | P26: https://detail.1688.com/offer/910982119982.html?spm=a26352.b28411319.offerlist.1.6b2d1e62zrDVua | R26: =_xlfn.DISPIMG("ID_C09B1D0D3170446FA4B66A36A8211A98",1) -> =DISPIMG("ID_C09B1D0D3170446FA4B66A36A8211A98",1) | T26: 牛至油180粒，牛至油300粒，有两种
A27: SafeMag™ | Auto-Telefonhalterung [Letzter Tag Rabatt] | B27: GQU0623007相似款 | C27: =_xlfn.DISPIMG("ID_D346022E158E415E8753332547B85756",1) -> =DISPIMG("ID_D346022E158E415E8753332547B85756",1) | D27: =MAX(E27,F27) -> 0.3 | E27: 0.3 | F27: 0.032 | G27: 16×8×2 | H27: =_xlfn.DISPIMG("ID_43E8A72E216946CD9CCF379A4D4FD3B1",1) -> =DISPIMG("ID_43E8A72E216946CD9CCF379A4D4FD3B1",1) | I27: =K27+J27 -> 14.8 | J27: 11.8 | K27: 3 | M27: https://cendura.de/products/safemag-auto-telefonhalterung-letzter-tag-rabatt?_pos=1&_sid=8f51d7273&_ss=r%3Fvariant%3D55375716974970&variant=55375716974970 | P27: https://detail.1688.com/offer/879429116969.html?spm=a26352.b28411319.offerlist.214.6ac71e627r4aTM | R27: =_xlfn.DISPIMG("ID_BB0EFDFF97E64B3FB5389E91B896FF87",1) -> =DISPIMG("ID_BB0EFDFF97E64B3FB5389E91B896FF87",1)
A28: a) Handwinding Steel Watch (no electronics!) b) Book | B28: CQU0623001 | D28: =MAX(E28,F28) -> 0.6 | E28: 0.6 | F28: =22*15*8/5000 -> 0.528 | G28: 22*15*8 | I28: =K28+J28 -> 0 | J28: 0
A29: Handwinding Steel Watch (no electronics!) | B29: CQU0623110 | D29: =MAX(E29,F29) -> 0.4 | E29: 0.4 | F29: =19*12*6/5000 -> 0.2736 | G29: 19*12*6 | I29: =K29+J29 -> 0 | J29: 0
A30: Pedicure set + foot cream + 3*socks | B30: G0101-ME | C30: =_xlfn.DISPIMG("ID_1C9B3D3D817644D4B78D65D02A3FCDC7",1) -> =DISPIMG("ID_1C9B3D3D817644D4B78D65D02A3FCDC7",1) | D30: =MAX(E30,F30) -> 1.40625 | E30: 1 | F30: =30*25*15/8000 -> 1.40625 | G30: 30*25*15 | I30: 89
C31: =_xlfn.DISPIMG("ID_1AAD8B113C5F40939CCB0D9A51D1A44E",1) -> =DISPIMG("ID_1AAD8B113C5F40939CCB0D9A51D1A44E",1)
C32: =_xlfn.DISPIMG("ID_CA728C4165EF4B59886C0000AA4B8871",1) -> =DISPIMG("ID_CA728C4165EF4B59886C0000AA4B8871",1)
B33: E011 | C33: 1+1纸箱 | D33: =MAX(E33,F33) -> 1.4976 | E33: 0.58 | F33: =16*26*18/5000 -> 1.4976 | G33: 16*26*18 | I33: 0
B34: E013 | C34: 1+1塑料袋 | D34: =MAX(E34,F34) -> 0.8228 | E34: 0.55 | F34: =22*11*17/5000 -> 0.8228 | I34: 0
B35: E015 | C35: 1+1气泡袋 | D35: =MAX(E35,F35) -> 0.9936 | E35: 0.57 | F35: =23*12*18/5000 -> 0.9936 | I35: 0
A36: SkinGuard（1+1） | B36: GQU0630007 | C36: =_xlfn.DISPIMG("ID_76C88E4864A1475AAEDF103B5BDFD722",1) -> =DISPIMG("ID_76C88E4864A1475AAEDF103B5BDFD722",1) | D36: =MAX(E36,F36) -> 0.2 | E36: 0.2 | F36: =4*4*13/8000 -> 0.026 | G36: 4*4*13 | I36: =K36+J36 -> 26 | J36: 18 | K36: 8 | M36: https://lettucepets.com/products/pet-skin-treatment-spray-for-fungal-bacterial-infections?fbclid=IwY2xjawLPJKZleHRuA2FlbQIxMABicmlkETFJSU9yaTNBWEpjMkJpOXYxAR4shII-NJrs6eU9LWfVqSfPIsAB3IHewhA5WNMVKYeYQhsg0Q3816RR9wV9bw_aem_Nu3h6lEgB8GK2w8WlMLxrQ&variant=51233243562268 | P36: https://detail.1688.com/offer/940558935118.html?spm=a26352.b28411319.offerlist.1.6a001e620BDgLt | R36: =_xlfn.DISPIMG("ID_E00E39BEDCA14554BDB0F00C36D2FA85",1) -> =DISPIMG("ID_E00E39BEDCA14554BDB0F00C36D2FA85",1) | S36: =_xlfn.DISPIMG("ID_54B898D5F6A64BE89EAF26AC2C7026BF",1) -> =DISPIMG("ID_54B898D5F6A64BE89EAF26AC2C7026BF",1) | T36: =_xlfn.DISPIMG("ID_2598C4EDDE854AAEAAB7E65068067D87",1) -> =DISPIMG("ID_2598C4EDDE854AAEAAB7E65068067D87",1)
A37: Neck Pain Patches | B37: GQU0630008 | C37: =_xlfn.DISPIMG("ID_21427AE04695476D86E80F4D9BA814FA",1) -> =DISPIMG("ID_21427AE04695476D86E80F4D9BA814FA",1) | D37: =MAX(E37,F37) -> 0.03 | E37: 0.03 | I37: =K37+J37 -> 3.7 | J37: 0.5 | K37: 3.2 | M37: https://www.amazon.com/iShanCare-Neck-Pain-Relief-Patch/dp/B0BKL4NRMQ/ref=sims_dp_d_dex_ai_rank_model_feedback_d_v1_d_sccl_1_2/136-0509895-9428936?pd_rd_w=A2qmS&content-id=amzn1.sym.5daa61ea-dedc-4cc4-b84a-9865d4f36e97&pf_rd_p=5daa61ea-dedc-4cc4-b84a-9865d4f36e97&pf_rd_r=CB9PPYGYQ1H0HQRB9ZJR&pd_rd_wg=m4Buk&pd_rd_r=ceb79ee7-5477-49d7-85aa-c32ec9c0073e&pd_rd_i=B0BKL4NRMQ&th=1 | P37: https://detail.1688.com/offer/937927916764.html?spm=a26352.b28411319.offerlist.1.3da51e62IS8wCp | R37: =_xlfn.DISPIMG("ID_A9FB0D7102DA4F0A8B4AB78C8A981922",1) -> =DISPIMG("ID_A9FB0D7102DA4F0A8B4AB78C8A981922",1) | S37: =_xlfn.DISPIMG("ID_04BAE11DCE934B8FA61B08075A755D2A",1) -> =DISPIMG("ID_04BAE11DCE934B8FA61B08075A755D2A",1)
A38: Combined Quote （1 massager+ 1pack patches） "Blue Neck Massager Neck Pain Patches" | B38: GQU0630009 | C38: =_xlfn.DISPIMG("ID_75473907AF9F4913A71673C19029E4A6",1) -> =DISPIMG("ID_75473907AF9F4913A71673C19029E4A6",1) | D38: =MAX(E38,F38) -> 1.125 | E38: 0.8 | F38: =24*25*15/8000 -> 1.125 | G38: 24*25*15cm | I38: =K38+J38 -> 133.7 | J38: 130.5 | K38: 3.2 | M38: https://www.amazon.com/iShanCare-Neck-Pain-Relief-Patch/dp/B0BKL4NRMQ/ref=sims_dp_d_dex_ai_rank_model_feedback_d_v1_d_sccl_1_2/136-0509895-9428936?pd_rd_w=A2qmS&content-id=amzn1.sym.5daa61ea-dedc-4cc4-b84a-9865d4f36e97&pf_rd_p=5daa61ea-dedc-4cc4-b84a-9865d4f36e97&pf_rd_r=CB9PPYGYQ1H0HQRB9ZJR&pd_rd_wg=m4Buk&pd_rd_r=ceb79ee7-5477-49d7-85aa-c32ec9c0073e&pd_rd_i=B0BKL4NRMQ&th=1 | P38: https://detail.1688.com/offer/937927916764.html?spm=a26352.b28411319.offerlist.1.3da51e62IS8wCp | R38: =_xlfn.DISPIMG("ID_A9FB0D7102DA4F0A8B4AB78C8A981922",1) -> =DISPIMG("ID_A9FB0D7102DA4F0A8B4AB78C8A981922",1) | S38: =_xlfn.DISPIMG("ID_04BAE11DCE934B8FA61B08075A755D2A",1) -> =DISPIMG("ID_04BAE11DCE934B8FA61B08075A755D2A",1)
C39: =_xlfn.DISPIMG("ID_CE8BDEC5B531425692465B8395A482C6",1) -> =DISPIMG("ID_CE8BDEC5B531425692465B8395A482C6",1) | I39: =K39+J39 -> 0
A40: Gluco Gone Blood Sugar Regulating Drops | B40: LQU0702101 | C40: =_xlfn.DISPIMG("ID_95B666FFAE3449AFA339E29AA544F9C8",1) -> =DISPIMG("ID_95B666FFAE3449AFA339E29AA544F9C8",1) | D40: =MAX(E40,F40) -> 0.2 | E40: 0.2 | F40: =15*5*5/5000 -> 0.075 | G40: 15*5*5 | I40: =K40+J40 -> 19 | J40: 15 | K40: 4 | M40: https://navanisupps.com/products/droplets | P40: https://detail.1688.com/offer/901924596865.html?spm=a26352.b28411319.offerlist.57.4ccb1e625tdpoO
A41: Sofia™ | Midi Kjole | B41: C00106S-LN | C41: =_xlfn.DISPIMG("ID_14BF4798DFA84B5785D7BC65DF159EFB",1) -> =DISPIMG("ID_14BF4798DFA84B5785D7BC65DF159EFB",1) | D41: =MAX(E41,F41) -> 0.35 | E41: 0.35 | I41: =K41+J41 -> 50 | J41: 42 | K41: 8 | M41: https://sofiakobenhavn.dk/products/sofia-midi-kjole?variant=51790068646155 | P41: https://detail.1688.com/offer/773653551668.html?spm=a26352.b28411319.offerlist.7.2e401e62WHncqZ | R41: =_xlfn.DISPIMG("ID_572AA8229B8947EEA4DC327D48824A52",1) -> =DISPIMG("ID_572AA8229B8947EEA4DC327D48824A52",1) | S41: =_xlfn.DISPIMG("ID_FD0C7A6F1AE848D5A76DC77FFDDCB939",1) -> =DISPIMG("ID_FD0C7A6F1AE848D5A76DC77FFDDCB939",1) | T41: =_xlfn.DISPIMG("ID_7356946B3CE94C59A46BC715F7EBDA5A",1) -> =DISPIMG("ID_7356946B3CE94C59A46BC715F7EBDA5A",1) | U41: 欧码
A42: Larineco - Remineralizing Gum（1+1） | B42: CQU0704005相似款 | C42: =_xlfn.DISPIMG("ID_AAD7A73DDA1D423F825C1855D92CC428",1) -> =DISPIMG("ID_AAD7A73DDA1D423F825C1855D92CC428",1) | D42: =MAX(E42,F42) -> 0.16 | E42: 0.16 | F42: 0.04 | G42: 10*10*3 | I42: =K42+J42 -> 23.1 | J42: 17.1 | K42: 6 | M42: https://buylarine.com/products/larineco%E2%84%A2%EF%B8%8F-remineralizing-gum-copy | P42: https://detail.1688.com/offer/836079571684.html?spm=a262eq.8274978.im_chat_detail.pc_zdfw_v1 | R42: =_xlfn.DISPIMG("ID_2EC640006AC249F28395191C91F577C5",1) -> =DISPIMG("ID_2EC640006AC249F28395191C91F577C5",1) | S42: =_xlfn.DISPIMG("ID_0AF784A6CAF3413B822300EF04A04A47",1) -> =DISPIMG("ID_0AF784A6CAF3413B822300EF04A04A47",1) | T42: =_xlfn.DISPIMG("ID_60F1B1166DC54D779765B4C1751E1719",1) -> =DISPIMG("ID_60F1B1166DC54D779765B4C1751E1719",1)
A43: LuminoTeeth™ Whitening Powder Bundle | B43: CQU0704006相似款 | C43: =_xlfn.DISPIMG("ID_C4A42FC3D53B4BA3AB401C08AE428EC3",1) -> =DISPIMG("ID_C4A42FC3D53B4BA3AB401C08AE428EC3",1) | D43: =MAX(E43,F43) -> 0.183168 | E43: =0.081*2 -> 0.162 | F43: =10.8*10.6*8/5000 -> 0.183168 | G43: 10.8*10.6*8 CM（2pcs） | I43: =K43+J43 -> 15.5 | J43: 12 | K43: 3.5 | M43: https://luminoteeth.com/products/bundle | P43: https://detail.1688.com/offer/937488344684.html?spm=a26352.b28411319.offerlist.1.6def1e62XODgUF | R43: =_xlfn.DISPIMG("ID_39945D1A5A6545A3ABD202123D81E155",1) -> =DISPIMG("ID_39945D1A5A6545A3ABD202123D81E155",1)
A44: AirEase | B44: GQU0701013相似款 | C44: =_xlfn.DISPIMG("ID_BE6697E8A4CB47F28626B1E77AF26C3A",1) -> =DISPIMG("ID_BE6697E8A4CB47F28626B1E77AF26C3A",1) | D44: =MAX(E44,F44) -> 0.5 | E44: 0.5 | F44: =15*12*6/8000 -> 0.135 | G44: 14.2*11.2*5.9cm | I44: =K44+J44 -> 77 | J44: 70 | K44: 7 | M44: https://shopellox.com/products/portable-nebulizer?variant=46313676800166 | P44: https://detail.1688.com/offer/735561815074.html?spm=a26352.b28411319.offerlist.11.37ab1e62MooZsH | Q44: https://detail.1688.com/offer/714870842310.html?spm=a26352.b28411319.offerlist.59.37ab1e62MooZsH | R44: =_xlfn.DISPIMG("ID_7175BCD418C2414AACA0056E28950A44",1) -> =DISPIMG("ID_7175BCD418C2414AACA0056E28950A44",1) | S44: =_xlfn.DISPIMG("ID_4DA28032E1BD46689A030CF0A57D145E",1) -> =DISPIMG("ID_4DA28032E1BD46689A030CF0A57D145E",1)
A45: PowerCleaner | B45: QUC0705003 | C45: =_xlfn.DISPIMG("ID_D902EE39A49543B9AA53DFA515BE5DB7",1) -> =DISPIMG("ID_D902EE39A49543B9AA53DFA515BE5DB7",1) | D45: =MAX(E45,F45) -> 0.15 | E45: 0.15 | F45: =10*4*13/8000 -> 0.065 | G45: 10*4*13 | I45: =K45+J45 -> 10.5 | J45: 4.5 | K45: 6 | M45: https://nl.aliexpress.com/item/1005007811722783.html?src=google&pdp_npi=4%40dis!EUR!3.55!1.81!!!!!%40!12000042286985414!ppc!!!&src=google&albch=shopping&acnt=272-267-0231&isdl=y&slnk=&plac=&mtctp=&albbt=Google_7_shopping&aff_platform=google&aff_short_key=UneMJZVf&gclsrc=aw.ds&&albagn=888888&&ds_e_adid=&ds_e_matchtype=&ds_e_device=c&ds_e_network=x&ds_e_product_group_id=&ds_e_product_id=nl1005007811722783&ds_e_product_merchant_id=108898720&ds_e_product_country=NL&ds_e_product_language=nl&ds_e_product_channel=online&ds_e_product_store_id=&ds_url_v=2&albcp=20730513328&albag=&isSmbAutoCall=false&needSmbHouyi=false&gad_source=1&gad_campaignid=20726902985&gbraid=0AAAAAoukdWMRq3jp5g1CHnUFX-5kSl5GS&gclid=Cj0KCQjw953DBhCyARIsANhIZoYPgc_jY5fQ5bhqtR1r30bBif4PNLAr4s6S-VgeXhkHsiwjTbMtKn0aAl6IEALw_wcB | P45: https://detail.1688.com/offer/889124523217.html?spm=a26352.b28411319.offerlist.6.31bb1e62PK4Os4
A46: Neck Pain Patches | B46: L0301-ME | C46: =_xlfn.DISPIMG("ID_C4077B97B263427BBA186A35B843B500",1) -> =DISPIMG("ID_C4077B97B263427BBA186A35B843B500",1) | D46: =MAX(E46,F46) -> 0.06 | E46: 0.06 | F46: =11*14*2/8000 -> 0.0385 | G46: 11*14*2 | I46: =K46+J46 -> 4.5 | J46: 0.5 | K46: 4 | M46: https://www.amazon.com/iShanCare-Neck-Pain-Relief-Patch/dp/B0BKL4NRMQ/ref=sims_dp_d_dex_ai_rank_model_feedback_d_v1_d_sccl_1_2/136-0509895-9428936?pd_rd_w=A2qmS&content-id=amzn1.sym.5daa61ea-dedc-4cc4-b84a-9865d4f36e97&pf_rd_p=5daa61ea-dedc-4cc4-b84a-9865d4f36e97&pf_rd_r=CB9PPYGYQ1H0HQRB9ZJR&pd_rd_wg=m4Buk&pd_rd_r=ceb79ee7-5477-49d7-85aa-c32ec9c0073e&pd_rd_i=B0BKL4NRMQ&th=1 | P46: https://detail.1688.com/offer/784675028700.html?spm=a26352.28064800.offerlist.2.3c751e62aifkyc&cosite=baidujj_pz&tracelog=p4p&_p_isad=1&clickid=5221096e5ce7436486ae3c7d08a7e351&sessionid=0553a9ede33dd86d6bca5c03b60c2bac
A47: Combined SKU Neck Pain Patches+E0301-ME | B47: Combined SKU E0401-ME | C47: =_xlfn.DISPIMG("ID_C4077B97B263427BBA186A35B843B500",1) -> =DISPIMG("ID_C4077B97B263427BBA186A35B843B500",1) | D47: =MAX(E47,F47) -> 0.05 | E47: 0.05 | F47: =11*14*2/8000 -> 0.0385 | G47: 11*14*2 | I47: =K47+J47 -> 0 | M47: https://www.amazon.com/iShanCare-Neck-Pain-Relief-Patch/dp/B0BKL4NRMQ/ref=sims_dp_d_dex_ai_rank_model_feedback_d_v1_d_sccl_1_2/136-0509895-9428936?pd_rd_w=A2qmS&content-id=amzn1.sym.5daa61ea-dedc-4cc4-b84a-9865d4f36e97&pf_rd_p=5daa61ea-dedc-4cc4-b84a-9865d4f36e97&pf_rd_r=CB9PPYGYQ1H0HQRB9ZJR&pd_rd_wg=m4Buk&pd_rd_r=ceb79ee7-5477-49d7-85aa-c32ec9c0073e&pd_rd_i=B0BKL4NRMQ&th=1 | P47: https://detail.1688.com/offer/784675028700.html?spm=a26352.28064800.offerlist.2.3c751e62aifkyc&cosite=baidujj_pz&tracelog=p4p&_p_isad=1&clickid=5221096e5ce7436486ae3c7d08a7e351&sessionid=0553a9ede33dd86d6bca5c03b60c2bac
C48: =_xlfn.DISPIMG("ID_C5BBE678C8854EC89E00FAE9B8048231",1) -> =DISPIMG("ID_C5BBE678C8854EC89E00FAE9B8048231",1) | D48: =MAX(E48,F48) -> 1.1088 | E48: 0.7 | F48: =22*21*12/5000 -> 1.1088 | G48: 220*209*115mm | I48: =K48+J48 -> 0
B49: E0401-ME | D49: =MAX(E49,F49) -> 1.1088 | F49: =22*21*12/5000 -> 1.1088 | I49: =K49+J49 -> 0
B50: CQU0710007 | C50: =_xlfn.DISPIMG("ID_6975375882594AF3AE9ED6E8409E1269",1) -> =DISPIMG("ID_6975375882594AF3AE9ED6E8409E1269",1) | D50: =MAX(E50,F50) -> 0.45 | E50: 0.45 | F50: 0.07 | G50: 6.5*6.5*12 | I50: =K50+J50 -> 29 | J50: 24 | K50: 5 | M50: https://www.alibaba.com/product-detail/Kangmao-OEM-Private-Label-Vegan-Supplements_1601149654630.html?spm=a2700.galleryofferlist.normal_offer.d_image.468413a0BaKGVe | P50: https://detail.1688.com/offer/913290493193.html?spm=a26352.b28411319.offerlist.5.7e6c1e62jRJITo | R50: =_xlfn.DISPIMG("ID_F380C3ECF3B84B579FE1A6465074CDD4",1) -> =DISPIMG("ID_F380C3ECF3B84B579FE1A6465074CDD4",1) | T50: 2瓶起批
B51: CQU0710008相似款 | C51: =_xlfn.DISPIMG("ID_420C09C623E64483A5D121CFC5CD72A7",1) -> =DISPIMG("ID_420C09C623E64483A5D121CFC5CD72A7",1) | D51: =MAX(E51,F51) -> 0.39 | E51: 0.3 | F51: 0.39 | G51: 195*105*135mm | I51: =K51+J51 -> 40 | J51: 35 | K51: 5 | M51: https://www.alibaba.com/product-detail/Sea-Moss-Black-Seed-Oil-Ashwagandha_1601338096781.html?spm=a2700.galleryofferlist.normal_offer.d_image.2f2513a0BNBPUc | P51: https://detail.1688.com/offer/927985422229.html?spm=a26352.b28411319.offerlist.7.423b1e627oNdbV | R51: =_xlfn.DISPIMG("ID_A8ABD764D79F4B21A2F144C31495781B",1) -> =DISPIMG("ID_A8ABD764D79F4B21A2F144C31495781B",1) | T51: 2瓶起批
B52: CQU0710009 | C52: =_xlfn.DISPIMG("ID_9337B89E9C2F4635B8340D139D8CE280",1) -> =DISPIMG("ID_9337B89E9C2F4635B8340D139D8CE280",1) | D52: =MAX(E52,F52) -> 0.25 | E52: 0.25 | F52: 0.03 | G52: 12*4*4 | I52: =K52+J52 -> 25.2 | J52: 15.2 | K52: 10 | M52: https://www.alibaba.com/product-detail/Manufacturer-OEM-apple-Cider-Vinegar-Slimming_1601242189552.html?spm=a2700.galleryofferlist.normal_offer.d_image.177f13a01ylBFX | P52: https://detail.1688.com/offer/675776595713.html?spm=a262eq.8274978.im_chat_detail.pc_zdfw_v1 | R52: =_xlfn.DISPIMG("ID_C475F6D6817C48CE9CABA2AB02ED92B7",1) -> =DISPIMG("ID_C475F6D6817C48CE9CABA2AB02ED92B7",1) | S52: =_xlfn.DISPIMG("ID_D18AA79784214D3E99E917705F48C21B",1) -> =DISPIMG("ID_D18AA79784214D3E99E917705F48C21B",1) | T52: 5瓶起批
A53: SkinGuard™ - Natuurlijke spray tegen jeuk, schimmel en infecties | B53: L002 | C53: =_xlfn.DISPIMG("ID_76C88E4864A1475AAEDF103B5BDFD722",1) -> =DISPIMG("ID_76C88E4864A1475AAEDF103B5BDFD722",1) | D53: =MAX(E53,F53) -> 0.1 | E53: 0.1 | G53: 4*4*13 | I53: =K53+J53 -> 16 | J53: 9 | K53: 7 | M53: https://lettucepets.com/products/pet-skin-treatment-spray-for-fungal-bacterial-infections?fbclid=IwY2xjawLPJKZleHRuA2FlbQIxMABicmlkETFJSU9yaTNBWEpjMkJpOXYxAR4shII-NJrs6eU9LWfVqSfPIsAB3IHewhA5WNMVKYeYQhsg0Q3816RR9wV9bw_aem_Nu3h6lEgB8GK2w8WlMLxrQ&variant=51233243562268 | P53: https://detail.1688.com/offer/940558935118.html?spm=a26352.b28411319.offerlist.1.6a001e620BDgLt | R53: =_xlfn.DISPIMG("ID_E00E39BEDCA14554BDB0F00C36D2FA85",1) -> =DISPIMG("ID_E00E39BEDCA14554BDB0F00C36D2FA85",1) | S53: =_xlfn.DISPIMG("ID_54B898D5F6A64BE89EAF26AC2C7026BF",1) -> =DISPIMG("ID_54B898D5F6A64BE89EAF26AC2C7026BF",1) | T53: =_xlfn.DISPIMG("ID_2598C4EDDE854AAEAAB7E65068067D87",1) -> =DISPIMG("ID_2598C4EDDE854AAEAAB7E65068067D87",1)
A54: Waterproof Chemical-Free Tick Repellent Tag | B54: CQU0710020 | C54: =_xlfn.DISPIMG("ID_E5259E0B57EA459997EA04E98B4C6C0F",1) -> =DISPIMG("ID_E5259E0B57EA459997EA04E98B4C6C0F",1) | D54: =MAX(E54,F54) -> 0.07 | E54: 0.07 | F54: =8*8*4/8000 -> 0.032 | G54: 8*8*4 | I54: =K54+J54 -> 27 | J54: 23 | K54: 4 | M54: https://lettucepets.com/products/waterproof-chemical-free-tick-repellent-tag?variant=52225679393052 | P54: https://detail.1688.com/offer/918240739048.html?spm=a26352.b28411319.offerlist.1.aa0e1e62scZKa7 | Q54: =_xlfn.DISPIMG("ID_5C99D4E210ED4C77BDA4CE5DA9BA36FF",1) -> =DISPIMG("ID_5C99D4E210ED4C77BDA4CE5DA9BA36FF",1) | R54: =_xlfn.DISPIMG("ID_D5975EF83C634A479E3C892C2E934141",1) -> =DISPIMG("ID_D5975EF83C634A479E3C892C2E934141",1) | S54: =_xlfn.DISPIMG("ID_5F33ADF5F8EC45C983F85F84A55EBF7A",1) -> =DISPIMG("ID_5F33ADF5F8EC45C983F85F84A55EBF7A",1)
A55: Waterproof Chemical-Free Tick Repellent Tag | B55: CQU0710021 | C55: =_xlfn.DISPIMG("ID_E5259E0B57EA459997EA04E98B4C6C0F",1) -> =DISPIMG("ID_E5259E0B57EA459997EA04E98B4C6C0F",1) | D55: =MAX(E55,F55) -> 0.11 | E55: 0.11 | F55: =8.5*8.5*3/5000 -> 0.04335 | G55: 8.5*8.5*3 | I55: =K55+J55 -> 12.5 | J55: 6.5 | K55: 6 | M55: https://lettucepets.com/products/waterproof-chemical-free-tick-repellent-tag?variant=52225679393052 | P55: https://detail.1688.com/offer/932694172151.html?spm=a26352.b28411319.offerlist.11.9e781e62pZe3it | R55: =_xlfn.DISPIMG("ID_B7BC898FA2054130A42677CEB5B42E91",1) -> =DISPIMG("ID_B7BC898FA2054130A42677CEB5B42E91",1) | S55: =_xlfn.DISPIMG("ID_B500202392044D0A97FAF18CB428C8D2",1) -> =DISPIMG("ID_B500202392044D0A97FAF18CB428C8D2",1)
A56: Waterproof Chemical-Free Tick Repellent Tag（1+1） | B56: CQU0710022 | C56: =_xlfn.DISPIMG("ID_E5259E0B57EA459997EA04E98B4C6C0F",1) -> =DISPIMG("ID_E5259E0B57EA459997EA04E98B4C6C0F",1) | D56: =MAX(E56,F56) -> 0.2 | E56: 0.08 | F56: =10*10*5/5000*2 -> 0.2 | G56: 9*9*3 | I56: =K56+J56 -> 24 | J56: 22 | K56: 2 | P56: https://detail.1688.com/offer/931244039185.html
A57: SkinGuard™ - Natuurlijke spray tegen jeuk, schimmel en infecties | B57: L002--1 | C57: =_xlfn.DISPIMG("ID_76C88E4864A1475AAEDF103B5BDFD722",1) -> =DISPIMG("ID_76C88E4864A1475AAEDF103B5BDFD722",1) | D57: =MAX(E57,F57) -> 0.15 | E57: 0.15 | F57: =13*10*9/8000 -> 0.14625 | G57: 4*4*13 | I57: =K57+J57 -> 30 | J57: 22 | K57: 8 | M57: https://lettucepets.com/products/pet-skin-treatment-spray-for-fungal-bacterial-infections?fbclid=IwY2xjawLPJKZleHRuA2FlbQIxMABicmlkETFJSU9yaTNBWEpjMkJpOXYxAR4shII-NJrs6eU9LWfVqSfPIsAB3IHewhA5WNMVKYeYQhsg0Q3816RR9wV9bw_aem_Nu3h6lEgB8GK2w8WlMLxrQ&variant=51233243562268 | P57: https://detail.1688.com/offer/940558935118.html?spm=a26352.b28411319.offerlist.1.6a001e620BDgLt | R57: =_xlfn.DISPIMG("ID_E00E39BEDCA14554BDB0F00C36D2FA85",1) -> =DISPIMG("ID_E00E39BEDCA14554BDB0F00C36D2FA85",1) | S57: =_xlfn.DISPIMG("ID_54B898D5F6A64BE89EAF26AC2C7026BF",1) -> =DISPIMG("ID_54B898D5F6A64BE89EAF26AC2C7026BF",1) | T57: =_xlfn.DISPIMG("ID_2598C4EDDE854AAEAAB7E65068067D87",1) -> =DISPIMG("ID_2598C4EDDE854AAEAAB7E65068067D87",1)
A58: SkinGuard™ - Natuurlijke spray tegen jeuk, schimmel en infecties | B58: L002--2 | C58: =_xlfn.DISPIMG("ID_76C88E4864A1475AAEDF103B5BDFD722",1) -> =DISPIMG("ID_76C88E4864A1475AAEDF103B5BDFD722",1) | D58: =MAX(E58,F58) -> 0.178 | E58: 0.178 | F58: =20*13*5/8000 -> 0.1625 | G58: 4*4*13 | I58: =K58+J58 -> 23 | J58: 16 | K58: 7 | M58: https://lettucepets.com/products/pet-skin-treatment-spray-for-fungal-bacterial-infections?fbclid=IwY2xjawLPJKZleHRuA2FlbQIxMABicmlkETFJSU9yaTNBWEpjMkJpOXYxAR4shII-NJrs6eU9LWfVqSfPIsAB3IHewhA5WNMVKYeYQhsg0Q3816RR9wV9bw_aem_Nu3h6lEgB8GK2w8WlMLxrQ&variant=51233243562268 | P58: https://detail.1688.com/offer/940558935118.html?spm=a26352.b28411319.offerlist.1.6a001e620BDgLt | R58: =_xlfn.DISPIMG("ID_E00E39BEDCA14554BDB0F00C36D2FA85",1) -> =DISPIMG("ID_E00E39BEDCA14554BDB0F00C36D2FA85",1) | S58: =_xlfn.DISPIMG("ID_54B898D5F6A64BE89EAF26AC2C7026BF",1) -> =DISPIMG("ID_54B898D5F6A64BE89EAF26AC2C7026BF",1) | T58: =_xlfn.DISPIMG("ID_2598C4EDDE854AAEAAB7E65068067D87",1) -> =DISPIMG("ID_2598C4EDDE854AAEAAB7E65068067D87",1)
B59: GQU0716013 | C59: =_xlfn.DISPIMG("ID_D06E46378C2140E7B1179D985A5F8967",1) -> =DISPIMG("ID_D06E46378C2140E7B1179D985A5F8967",1) | D59: =MAX(E59,F59) -> 0.1 | E59: 0.1 | F59: =6*6*10/5000 -> 0.072 | G59: 6*6*10cm | I59: =K59+J59 -> 17 | J59: 11 | K59: 6 | P59: https://detail.1688.com/offer/899875437113.html?spm=a26352.b28411319.offerlist.1.3c861e622Pyivy | R59: =_xlfn.DISPIMG("ID_15FB24CF06BD4BFD8CE795C58A23A234",1) -> =DISPIMG("ID_15FB24CF06BD4BFD8CE795C58A23A234",1)
A60: Leather strap | B60: GQU0716005 | C60: =_xlfn.DISPIMG("ID_E2EA151EF37844BA96C057C701B207FA",1) -> =DISPIMG("ID_E2EA151EF37844BA96C057C701B207FA",1) | D60: =MAX(E60,F60) -> 0.0936 | E60: 0.025 | F60: =18*13*2/5000 -> 0.0936 | G60: 18*13*2 | I60: =K60+J60 -> 0
A61: Stainless steel strap | B61: GQU0716006 | C61: =_xlfn.DISPIMG("ID_72FDABDE3529434D9BFF70A8F4A319E8",1) -> =DISPIMG("ID_72FDABDE3529434D9BFF70A8F4A319E8",1) | D61: =MAX(E61,F61) -> 0.0936 | E61: 0.08 | F61: =18*13*2/5000 -> 0.0936 | G61: 18*13*2 | I61: =K61+J61 -> 0
A62: a) Handwinding Steel Watch (no electronics!) b) Book | B62: CQU0623001 | C62: =_xlfn.DISPIMG("ID_772591A67D0E4438AB37EE468B7E1DC4",1) -> =DISPIMG("ID_772591A67D0E4438AB37EE468B7E1DC4",1) | D62: =MAX(E62,F62) -> 0.7776 | E62: 0.65 | F62: =27*16*9/5000 -> 0.7776 | G62: 27*16*9 | I62: =K62+J62 -> 0 | J62: 0
A63: Handwinding Steel Watch (no electronics!) | B63: CQU0623110 | C63: =_xlfn.DISPIMG("ID_B817E1AB811244D8B82BC7B728D11702",1) -> =DISPIMG("ID_B817E1AB811244D8B82BC7B728D11702",1) | D63: =MAX(E63,F63) -> 0.6468 | E63: 0.4 | F63: =21*11*14/5000 -> 0.6468 | G63: 21*11*14cm | I63: =K63+J63 -> 0 | J63: 0
A64: FindTag | B64: EQU0719003 | D64: =MAX(E64,F64) -> 0.144 | E64: 0.1 | F64: =9*8*10/5000 -> 0.144 | G64: =9*8*10/5000 -> 0.144 | I64: =K64+J64 -> 41 | J64: 36 | K64: 5 | Q64: https://detail.1688.com/offer/843271744153.html?spm=a26352.b28411319.offerlist.6.47681e623mtfjC
A65: FreshTip | B65: CQU0721003-lars | C65: =_xlfn.DISPIMG("ID_DDFB55C539E0485C9EAF7A75E2C0651F",1) -> =DISPIMG("ID_DDFB55C539E0485C9EAF7A75E2C0651F",1) | D65: =MAX(E65,F65) -> 0.1 | E65: 0.1 | F65: =7*10*5/5000 -> 0.07 | G65: 7*10 | I65: =K65+J65 -> 23 | J65: 15 | K65: 8 | M65: https://m.lifesparking.com/funnel/checkout-fungal-nail-patches | P65: https://detail.1688.com/offer/943414252843.html | R65: =_xlfn.DISPIMG("ID_0E376FB57C9049DB9A9583B996B7D37C",1) -> =DISPIMG("ID_0E376FB57C9049DB9A9583B996B7D37C",1)
A66: VeloStep - Neuropathy | B66: G030537-ME | C66: =_xlfn.DISPIMG("ID_EE91F2562288438993EA519ADA118D74",1) -> =DISPIMG("ID_EE91F2562288438993EA519ADA118D74",1) | D66: =MAX(E66,F66) -> 0.6 | E66: 0.6 | F66: =30*7*12/8000 -> 0.315 | G66: 30*7*12 | I66: =K66+J66 -> 51 | J66: 48 | K66: 3 | M66: https://try-nova.de/products/velostep?variant=52100624089421 | P66: https://detail.1688.com/offer/820489605443.html?spm=a26352.b28411319.offerlist.1.3be81e62ZNlZwd | R66: =_xlfn.DISPIMG("ID_40A367C16CEA4AFCAAF7DC948B949A8B",1) -> =DISPIMG("ID_40A367C16CEA4AFCAAF7DC948B949A8B",1) | S66: =_xlfn.DISPIMG("ID_D4612AEE91E145179DB430514C337B1A",1) -> =DISPIMG("ID_D4612AEE91E145179DB430514C337B1A",1) | T66: =_xlfn.DISPIMG("ID_6BB762CFB1944ADA8C7DA14E8BB60B18",1) -> =DISPIMG("ID_6BB762CFB1944ADA8C7DA14E8BB60B18",1) | U66: =_xlfn.DISPIMG("ID_E99860DBF94249AEAC78C28C8C5A120C",1) -> =DISPIMG("ID_E99860DBF94249AEAC78C28C8C5A120C",1)
A67: TurboFix | B67: CQU0722001 | C67: =_xlfn.DISPIMG("ID_95CF092AF6354F5B90A3B85D2900A0BB",1) -> =DISPIMG("ID_95CF092AF6354F5B90A3B85D2900A0BB",1) | D67: =MAX(E67,F67) -> 0.4 | E67: 0.4 | F67: =6*6*10/5000*2 -> 0.144 | I67: =K67+J67 -> 13 | J67: 10 | K67: 3 | P67: https://detail.1688.com/offer/899842547767.html?spm=a26352.b28411319.offerlist.12.68791e62irjsFT
A68: SOPHIE | SANDALI ELEGANTI | B68: CQU0721046 | C68: =_xlfn.DISPIMG("ID_DD794363D77F483ABDFADBBFAA669195",1) -> =DISPIMG("ID_DD794363D77F483ABDFADBBFAA669195",1) | D68: =MAX(E68,F68) -> 0.75 | E68: 0.6 | F68: 0.75 | G68: 30*20*10 | I68: =K68+J68 -> 98 | J68: 90 | K68: 8 | M68: https://lorano-firenze.com/collections/sandali-eleganti/products/sophie-sandali-eleganti | P68: https://detail.1688.com/offer/772677466543.html?spm=a26352.b28411319.offerlist.7.63db1e62fpP9aQ | Q68: =_xlfn.DISPIMG("ID_E0DB5B8A9AEC4C40AF33D88443253694",1) -> =DISPIMG("ID_E0DB5B8A9AEC4C40AF33D88443253694",1) | R68: =_xlfn.DISPIMG("ID_50660AAA265A41749499C9B382D5A617",1) -> =DISPIMG("ID_50660AAA265A41749499C9B382D5A617",1) | S68: =_xlfn.DISPIMG("ID_8BBDADBCF9B04E6FA8DAD22FB8E935BD",1) -> =DISPIMG("ID_8BBDADBCF9B04E6FA8DAD22FB8E935BD",1)
A69: SafeTag | B69: CQU07250223 | C69: =_xlfn.DISPIMG("ID_538AAC7817464E6AA436B94D24DB2E26",1) -> =DISPIMG("ID_538AAC7817464E6AA436B94D24DB2E26",1) | D69: =MAX(E69,F69) -> 0.1408 | E69: 0.1 | F69: =16*11*4/5000 -> 0.1408 | G69: 16*11*6 | I69: =K69+J69 -> 48 | J69: 45 | K69: 3 | P69: https://detail.1688.com/offer/925284637144.html?spm=a26352.b28411319.offerlist.120.753b1e62tTEt5h
A70: SealFix™ | Wasserdichte Isolierende Dichtungsmasse Für Jede Oberfläche 走华翰特惠 | B70: G00701-JA | C70: =_xlfn.DISPIMG("ID_BDFF7536221F487BB1CBE2CCDC29ABE7",1) -> =DISPIMG("ID_BDFF7536221F487BB1CBE2CCDC29ABE7",1) | D70: =MAX(E70,F70) -> 0.11 | E70: 0.06 | F70: 0.11 | G70: 17*7*7 | H70: 30g | I70: =K70+J70 -> 14 | J70: 8 | K70: 6 | M70: https://cendura.de/products/gleam1?variant=55362353299834 | P70: https://detail.1688.com/offer/891013940553.html?spm=a26352.b28411319.offerlist.6.34a71e62suWeyE

Sheet 华翰特敏
F1: 全球专线-特敏 | N1: 生效日期：2025.07.21 9:00 | O1: 返回目录
B2: 国家 | F2: 重量段KG | K2: 运费 RMB/KG | L2: 挂号费 RMB/票 | M2: 尺寸限制cm | N2: 参考时效（工作日）
B3: 加拿大 | C3: CA | F3: 0.05≤W≤0.3 | G3: 0.05 | H3: 0.3 | K3: 113 | L3: 29 | M3: 最长边≤60cm；长+宽+高≤90cm 最小尺寸≥15x10x1cm | N3: 9-15
B4: 加拿大 | C4: CA | F4: 0.3<W≤0.75 | G4: 0.3 | H4: 0.75 | K4: 113 | L4: 29
B5: 加拿大 | C5: CA | F5: 0.75<W≤1 | G5: 0.75 | H5: 1 | K5: 113 | L5: 29
B6: 加拿大 | C6: CA | F6: 1<W≤1.5 | G6: 1 | H6: 1.5 | K6: 113 | L6: 29
B7: 加拿大 | C7: CA | F7: 1.5<W≤2 | G7: 1.5 | H7: 2 | K7: 109 | L7: 29
B8: 加拿大 | C8: CA | F8: 2<W≤15 | G8: 2 | H8: 15 | K8: 109 | L8: 29
B9: 英国 | C9: UK/GB | F9: 0.01≤W≤1 | G9: 0.01 | H9: 1 | K9: 112 | L9: 17 | M9: 最大尺寸<60x40x40cm 最小尺寸≥15x10x1cm | N9: 6-10
B10: 英国 | C10: UK/GB | F10: 1<W≤2 | G10: 1 | H10: 2 | K10: 103 | L10: 17 | O10: 英国-Royal Mail偏远邮编
B11: 英国 | C11: UK/GB | F11: 2<W≤10 | G11: 2 | H11: 10 | K11: 103 | L11: 17
B12: 德国 | C12: DE | F12: 0.01≤W≤1 | G12: 0.01 | H12: 1 | K12: 102 | L12: 24 | M12: 0<W≤1：最大尺寸≤ 35x25x10cm 1<W≤10：最大尺寸≤ 60x50x40cm 最小尺寸≥15x10x1cm Packstation：尺寸限制<60x30x30cm | N12: 8-12
B13: 德国 | C13: DE | F13: 1<W≤2 | G13: 1 | H13: 2 | K13: 102 | L13: 24
B14: 德国 | C14: DE | F14: 2<W≤10 | G14: 2 | H14: 10 | K14: 102 | L14: 24
B15: 法国 | C15: FR | F15: 0.01≤W≤1 | G15: 0.01 | H15: 1 | K15: 110 | L15: 31 | M15: 最大尺寸≤60x50x40cm 最小尺寸≥15x10x1cm | N15: 8-12
B16: 法国 | C16: FR | F16: 1<W≤2 | G16: 1 | H16: 2 | K16: 110 | L16: 31
B17: 法国 | C17: FR | F17: 2<W≤10 | G17: 2 | H17: 10 | K17: 110 | L17: 31
B18: 意大利 | C18: IT | F18: 0.01≤W≤1 | G18: 0.01 | H18: 1 | K18: 123 | L18: 34 | M18: 最大尺寸≤60x50x40cm 最小尺寸≥15x10x1cm | N18: 8-12
B19: 意大利 | C19: IT | F19: 1<W≤2 | G19: 1 | H19: 2 | K19: 123 | L19: 34
B20: 意大利 | C20: IT | F20: 2<W≤10 | G20: 2 | H20: 10 | K20: 123 | L20: 34
B21: 西班牙 | C21: ES | F21: 0.01≤W≤1 | G21: 0.01 | H21: 1 | K21: 121 | L21: 27 | M21: 最大尺寸≤60x50x40cm 最小尺寸≥15x10x1cm | N21: 8-12
B22: 西班牙 | C22: ES | F22: 1<W≤2 | G22: 1 | H22: 2 | K22: 121 | L22: 27
B23: 西班牙 | C23: ES | F23: 2<W≤10 | G23: 2 | H23: 10 | K23: 121 | L23: 27
B24: 葡萄牙 | C24: PT | F24: 0.01≤W≤1 | G24: 0.01 | H24: 1 | K24: 126 | L24: 27 | M24: 最大尺寸≤60x50x40cm 最小尺寸≥15x10x1cm | N24: 8-12
B25: 葡萄牙 | C25: PT | F25: 1<W≤2 | G25: 1 | H25: 2 | K25: 126 | L25: 27
B26: 葡萄牙 | C26: PT | F26: 2<W≤10 | G26: 2 | H26: 10 | K26: 126 | L26: 27
B27: 荷兰 | C27: NL | F27: 0.01≤W≤1 | G27: 0.01 | H27: 1 | K27: 123 | L27: 44 | M27: 最大尺寸≤60x50x40cm 最小尺寸≥15x10x1cm | N27: 8-12
B28: 荷兰 | C28: NL | F28: 1<W≤2 | G28: 1 | H28: 2 | K28: 123 | L28: 44
B29: 荷兰 | C29: NL | F29: 2<W≤10 | G29: 2 | H29: 10 | K29: 123 | L29: 44
B30: 比利时 | C30: BE | F30: 0.01≤W≤1 | G30: 0.01 | H30: 1 | K30: 109 | L30: 28 | M30: 最大尺寸≤60x50x40cm 最小尺寸≥15x10x1cm | N30: 8-12
B31: 比利时 | C31: BE | F31: 1<W≤2 | G31: 1 | H31: 2 | K31: 109 | L31: 28
B32: 比利时 | C32: BE | F32: 2<W≤10 | G32: 2 | H32: 10 | K32: 109 | L32: 28
B33: 卢森堡 | C33: LU | F33: 0.01≤W≤1 | G33: 0.01 | H33: 1 | K33: 103 | L33: 30 | M33: 最大尺寸≤60x50x40cm 最小尺寸≥15x10x1cm | N33: 8-12
B34: 卢森堡 | C34: LU | F34: 1<W≤2 | G34: 1 | H34: 2 | K34: 103 | L34: 30
B35: 卢森堡 | C35: LU | F35: 2<W≤10 | G35: 2 | H35: 10 | K35: 103 | L35: 30
B36: 瑞典 | C36: SE/SW | F36: 0.01≤W≤1 | G36: 0.01 | H36: 1 | K36: 117 | L36: 48 | M36: 最大尺寸≤60x50x40cm 最小尺寸≥15x10x1cm | N36: 8-12
B37: 瑞典 | C37: SE/SW | F37: 1<W≤2 | G37: 1 | H37: 2 | K37: 117 | L37: 48
B38: 瑞典 | C38: SE/SW | F38: 2<W≤10 | G38: 2 | H38: 10 | K38: 117 | L38: 48
B39: 奥地利 | C39: AT | F39: 0.01≤W≤1 | G39: 0.01 | H39: 1 | K39: 104 | L39: 37 | M39: 最大尺寸≤60x50x40cm 最小尺寸≥15x10x1cm | N39: 8-12
B40: 奥地利 | C40: AT | F40: 1<W≤2 | G40: 1 | H40: 2 | K40: 104 | L40: 26
B41: 奥地利 | C41: AT | F41: 2<W≤10 | G41: 2 | H41: 10 | K41: 104 | L41: 26
B42: 捷克 | C42: CZ | F42: 0.01≤W≤1 | G42: 0.01 | H42: 1 | K42: 121 | L42: 46 | M42: 最大尺寸≤60x50x40cm 最小尺寸≥15x10x1cm | N42: 8-12
B43: 捷克 | C43: CZ | F43: 1<W≤2 | G43: 1 | H43: 2 | K43: 121 | L43: 46
B44: 捷克 | C44: CZ | F44: 2<W≤10 | G44: 2 | H44: 10 | K44: 121 | L44: 46
B45: 波兰 | C45: PL | F45: 0.01≤W≤1 | G45: 0.01 | H45: 1 | K45: 101 | L45: 45 | M45: 最大尺寸≤60x50x40cm 最小尺寸≥15x10x1cm | N45: 8-12
B46: 波兰 | C46: PL | F46: 1<W≤2 | G46: 1 | H46: 2 | K46: 101 | L46: 34
B47: 波兰 | C47: PL | F47: 2<W≤10 | G47: 2 | H47: 10 | K47: 101 | L47: 34
B48: 斯洛伐克 | C48: SK | F48: 0.01≤W≤1 | G48: 0.01 | H48: 1 | K48: 108 | L48: 32 | M48: 最大尺寸≤60x50x40cm 最小尺寸≥15x10x1cm | N48: 8-14
B49: 斯洛伐克 | C49: SK | F49: 1<W≤2 | G49: 1 | H49: 2 | K49: 108 | L49: 32
B50: 斯洛伐克 | C50: SK | F50: 2<W≤10 | G50: 2 | H50: 10 | K50: 108 | L50: 32
B51: 斯洛文尼亚 | C51: SI | F51: 0.01≤W≤1 | G51: 0.01 | H51: 1 | K51: 129 | L51: 75 | M51: 最大尺寸≤60x50x40cm 最小尺寸≥15x10x1cm | N51: 8-12
B52: 斯洛文尼亚 | C52: SI | F52: 1<W≤2 | G52: 1 | H52: 2 | K52: 129 | L52: 48
B53: 斯洛文尼亚 | C53: SI | F53: 2<W≤10 | G53: 2 | H53: 10 | K53: 129 | L53: 45
B54: 爱尔兰 | C54: IE | F54: 0.01≤W≤1 | G54: 0.01 | H54: 1 | K54: 112 | L54: 35 | M54: 最大尺寸≤60x50x40cm 最小尺寸≥15x10x1cm | N54: 8-14
B55: 爱尔兰 | C55: IE | F55: 1<W≤2 | G55: 1 | H55: 2 | K55: 112 | L55: 35
B56: 爱尔兰 | C56: IE | F56: 2<W≤10 | G56: 2 | H56: 10 | K56: 112 | L56: 35
B57: 匈牙利 | C57: HU | F57: 0.01≤W≤1 | G57: 0.01 | H57: 1 | K57: 108 | L57: 26 | M57: 最大尺寸≤60x50x40cm 最小尺寸≥15x10x1cm | N57: 8-12
B58: 匈牙利 | C58: HU | F58: 1<W≤2 | G58: 1 | H58: 2 | K58: 108 | L58: 26
B59: 匈牙利 | C59: HU | F59: 2<W≤10 | G59: 2 | H59: 10 | K59: 108 | L59: 26
B60: 立陶宛 | C60: LT | F60: 0.01≤W≤1 | G60: 0.01 | H60: 1 | K60: 125 | L60: 67 | M60: 最大尺寸≤60x50x40cm 最小尺寸≥15x10x1cm | N60: 8-14
B61: 立陶宛 | C61: LT | F61: 1<W≤2 | G61: 1 | H61: 2 | K61: 125 | L61: 51
B62: 立陶宛 | C62: LT | F62: 2<W≤10 | G62: 2 | H62: 10 | K62: 125 | L62: 31
B63: 丹麦 | C63: DK | F63: 0.01≤W≤1 | G63: 0.01 | H63: 1 | K63: 107 | L63: 39 | M63: 最大尺寸≤60x50x40cm 最小尺寸≥15x10x1cm | N63: 8-12
B64: 丹麦 | C64: DK | F64: 1<W≤2 | G64: 1 | H64: 2 | K64: 107 | L64: 30
B65: 丹麦 | C65: DK | F65: 2<W≤10 | G65: 2 | H65: 10 | K65: 107 | L65: 30
B66: 克罗地亚 | C66: CRO | F66: 0.01≤W≤1 | G66: 0.01 | H66: 1 | K66: 136 | L66: 118 | M66: 最大尺寸≤60x50x40cm 最小尺寸≥15x10x1cm | N66: 8-12
B67: 克罗地亚 | C67: CRO | F67: 1<W≤2 | G67: 1 | H67: 2 | K67: 136 | L67: 102
B68: 克罗地亚 | C68: CRO | F68: 2<W≤10 | G68: 2 | H68: 10 | K68: 119 | L68: 102
B69: 罗马尼亚 | C69: RO | F69: 0.01≤W≤1 | G69: 0.01 | H69: 1 | K69: 105 | L69: 28 | M69: 最大尺寸≤60x50x40cm 最小尺寸≥15x10x1cm | N69: 8-12
B70: 罗马尼亚 | C70: RO | F70: 1<W≤2 | G70: 1 | H70: 2 | K70: 105 | L70: 28
B71: 罗马尼亚 | C71: RO | F71: 2<W≤10 | G71: 2 | H71: 10 | K71: 105 | L71: 28
B72: 拉脱维亚 | C72: LV | F72: 0.01≤W≤1 | G72: 0.01 | H72: 1 | K72: 136 | L72: 87 | M72: 最大尺寸≤60x50x40cm 最小尺寸≥15x10x1cm | N72: 8-12
B73: 拉脱维亚 | C73: LV | F73: 1<W≤2 | G73: 1 | H73: 2 | K73: 141 | L73: 64
B74: 拉脱维亚 | C74: LV | F74: 2<W≤10 | G74: 2 | H74: 10 | K74: 129 | L74: 54
B75: 爱沙尼亚 | C75: EE | F75: 0.01≤W≤1 | G75: 0.01 | H75: 1 | K75: 124 | L75: 94 | M75: 最大尺寸≤60x50x40cm 最小尺寸≥15x10x1cm | N75: 8-12
B76: 爱沙尼亚 | C76: EE | F76: 1<W≤2 | G76: 1 | H76: 2 | K76: 141 | L76: 61
B77: 爱沙尼亚 | C77: EE | F77: 2<W≤10 | G77: 2 | H77: 10 | K77: 124 | L77: 61
B78: 芬兰 | C78: FI | F78: 0.01≤W≤1 | G78: 0.01 | H78: 1 | K78: 129 | L78: 63 | M78: 最大尺寸≤60x50x40cm 最小尺寸≥15x10x1cm | N78: 8-14
B79: 芬兰 | C79: FI | F79: 1<W≤2 | G79: 1 | H79: 2 | K79: 129 | L79: 50
B80: 芬兰 | C80: FI | F80: 2<W≤10 | G80: 2 | H80: 10 | K80: 124 | L80: 50
B81: 保加利亚 | C81: BG | F81: 0.01≤W≤1 | G81: 0.01 | H81: 1 | K81: 105 | L81: 30 | M81: 最大尺寸≤60x50x40cm 最小尺寸≥15x10x1cm | N81: 8-14
B82: 保加利亚 | C82: BG | F82: 1<W≤2 | G82: 1 | H82: 2 | K82: 105 | L82: 26
B83: 保加利亚 | C83: BG | F83: 2<W≤10 | G83: 2 | H83: 10 | K83: 105 | L83: 26
B84: 希腊 | C84: GR | F84: 0.01≤W≤1 | G84: 0.01 | H84: 1 | K84: 115 | L84: 27 | M84: 最大尺寸≤60x50x40cm 最小尺寸≥15x10x1cm | N84: 8-14
B85: 希腊 | C85: GR | F85: 1<W≤2 | G85: 1 | H85: 2 | K85: 115 | L85: 27
B86: 希腊 | C86: GR | F86: 2<W≤10 | G86: 2 | H86: 10 | K86: 115 | L86: 27
B87: 马耳他 | C87: MAL | F87: 0.01≤W≤1 | G87: 0.01 | H87: 1 | K87: 146 | L87: 54 | M87: 最大尺寸≤60x50x40cm 最小尺寸≥15x10x1cm | N87: 8-14
B88: 马耳他 | C88: MAL | F88: 1<W≤2 | G88: 1 | H88: 2 | K88: 146 | L88: 43
B89: 马耳他 | C89: MAL | F89: 2<W≤10 | G89: 2 | H89: 10 | K89: 146 | L89: 34
B90: 塞浦路斯 | C90: CY | F90: 0.01≤W≤1 | G90: 0.01 | H90: 1 | K90: 153 | L90: 83 | M90: 最大尺寸≤60x50x40cm 最小尺寸≥15x10x1cm | N90: 8-14
B91: 塞浦路斯 | C91: CY | F91: 1<W≤2 | G91: 1 | H91: 2 | K91: 153 | L91: 66
B92: 塞浦路斯 | C92: CY | F92: 2<W≤10 | G92: 2 | H92: 10 | K92: 164 | L92: 66

Sheet 燕文普货
G1: 返回主目录
B2: 2025-07-16 00:00:00
B3: 481
B4: 国家 | C4: CountryCode | D4: 公斤运费(元/KG) | E4: 处理费(元/件) | F4: 重量段(KG) | M4: 最小计费重量(KG)
B5: 美国 | C5: US | D5: 120 | E5: 20 | F5: 0.001 - 0.1 | G5: 0.001 | H5: 0.1 | K5: 120 | L5: 20 | M5: 0.05
B6: 美国 | C6: US | D6: 114 | E6: 18 | F6: 0.101 - 0.2 | G6: 0.101 | H6: 0.2 | K6: 114 | L6: 18 | M6: 0.05
B7: 美国 | C7: US | D7: 110 | E7: 16 | F7: 0.201 - 0.45 | G7: 0.201 | H7: 0.45 | K7: 110 | L7: 16 | M7: 0.05
B8: 美国 | C8: US | D8: 103 | E8: 16 | F8: 0.451 - 0.7 | G8: 0.451 | H8: 0.7 | K8: 103 | L8: 16 | M8: 0.05
B9: 美国 | C9: US | D9: 103 | E9: 9 | F9: 0.701 - 1.5 | G9: 0.701 | H9: 1.5 | K9: 103 | L9: 9 | M9: 0.05
B10: 美国 | C10: US | D10: 103 | E10: 9 | F10: 1.501 - 2 | G10: 1.501 | H10: 2 | K10: 103 | L10: 9 | M10: 0.05
B11: 美国 | C11: US | D11: 96 | E11: 9 | F11: 2.001 - 30 | G11: 2.001 | H11: 30 | K11: 96 | L11: 9 | M11: 0.05
B12: 加拿大 | C12: CA | D12: 78 | E12: 21 | F12: 0.001 - 0.15 | G12: 0.001 | H12: 0.15 | K12: 78 | L12: 21 | M12: 0.05
B13: 加拿大 | C13: CA | D13: 79 | E13: 22 | F13: 0.151 - 0.45 | G13: 0.151 | H13: 0.45 | K13: 79 | L13: 22 | M13: 0.05
B14: 加拿大 | C14: CA | D14: 82 | E14: 23 | F14: 0.451 - 0.75 | G14: 0.451 | H14: 0.75 | K14: 82 | L14: 23 | M14: 0.05
B15: 加拿大 | C15: CA | D15: 83 | E15: 23 | F15: 0.751 - 1 | G15: 0.751 | H15: 1 | K15: 83 | L15: 23 | M15: 0.05
B16: 加拿大 | C16: CA | D16: 83 | E16: 23 | F16: 1.001 - 30 | G16: 1.001 | H16: 30 | K16: 83 | L16: 23 | M16: 0.05
... B27: 波多黎各 | C27: PR | D27: 108 | E27: 55 | F27: 2.001 - 30 | G27: 2.001 | H27: 30 | K27: 108 | L27: 55 | M27: 0.05
B28: 美国偏远地区 | C28: #N/A | D28: 103 | E28: 30 | F28: 0.001 - 0.1 | G28: 0.001 | H28: 0.1 | K28: 103 | L28: 30 | M28: 0.05
B29: 美国偏远地区 | C29: #N/A | D29: 103 | E29: 30 | F29: 0.101 - 0.2 | G29: 0.101 | H29: 0.2 | K29: 103 | L29: 30 | M29: 0.05
B30: 美国偏远地区 | C30: #N/A | D30: 103 | E30: 35 | F30: 0.201 - 0.34 | G30: 0.201 | H30: 0.34 | K30: 103 | L30: 35 | M30: 0.05
B31: 美国偏远地区 | C31: #N/A | D31: 103 | E31: 40 | F31: 0.341 - 0.45 | G31: 0.341 | H31: 0.45 | K31: 103 | L31: 40 | M31: 0.05
B32: 美国偏远地区 | C32: #N/A | D32: 108 | E32: 55 | F32: 0.451 - 0.7 | G32: 0.451 | H32: 0.7 | K32: 108 | L32: 55 | M32: 0.05
B33: 美国偏远地区 | C33: #N/A | D33: 108 | E33: 55 | F33: 0.701 - 1.5 | G33: 0.701 | H33: 1.5 | K33: 108 | L33: 55 | M33: 0.05
B34: 美国偏远地区 | C34: #N/A | D34: 108 | E34: 55 | F34: 1.501 - 2 | G34: 1.501 | H34: 2 | K34: 108 | L34: 55 | M34: 0.05
B35: 美国偏远地区 | C35: #N/A | D35: 108 | E35: 55 | F35: 2.001 - 30 | G35: 2.001 | H35: 30 | K35: 108 | L35: 55 | M35: 0.05
B36: 英国 | C36: UK/GB | D36: 68 | E36: 16 | F36: 0.001 - 1 | G36: 0.001 | H36: 1 | K36: 68 | L36: 16 | M36: 0.001
B37: 英国 | C37: UK/GB | D37: 70 | E37: 16 | F37: 1.001 - 20 | G37: 1.001 | H37: 20 | K37: 70 | L37: 16 | M37: 0.001
B38: 法国 | C38: FR | D38: 84 | E38: 18 | F38: 0.001 - 0.2 | G38: 0.001 | H38: 0.2 | K38: 84 | L38: 18 | M38: 0.001
B39: 法国 | C39: FR | D39: 82 | E39: 19 | F39: 0.201 - 0.5 | G39: 0.201 | H39: 0.5 | K39: 82 | L39: 19 | M39: 0.001
B40: 法国 | C40: FR | D40: 78 | E40: 23 | F40: 0.501 - 30 | G40: 0.501 | H40: 30 | K40: 78 | L40: 23 | M40: 0.001
B41: 德国 | C41: DE | D41: 70 | E41: 19 | F41: 0.001 - 0.3 | G41: 0.001 | H41: 0.3 | K41: 70 | L41: 19 | M41: 0.001
B42: 德国 | C42: DE | D42: 65 | E42: 22 | F42: 0.301 - 30 | G42: 0.301 | H42: 30 | K42: 65 | L42: 22 | M42: 0.001
B43: 意大利 | C43: IT | D43: 68 | E43: 25 | F43: 0.001 - 30 | G43: 0.001 | H43: 30 | K43: 68 | L43: 25 | M43: 0.001
B44: 西班牙 | C44: ES | D44: 74 | E44: 18 | F44: 0.001 - 30 | G44: 0.001 | H44: 30 | K44: 74 | L44: 18 | M44: 0.001
B45: 荷兰 | C45: NL | D45: 93 | E45: 21 | F45: 0.001 - 0.1 | G45: 0.001 | H45: 0.1 | K45: 93 | L45: 21 | M45: 0.001
B46: 荷兰 | C46: NL | D46: 83 | E46: 23 | F46: 0.101 - 0.2 | G46: 0.101 | H46: 0.2 | K46: 83 | L46: 23 | M46: 0.001
B47: 荷兰 | C47: NL | D47: 81 | E47: 23 | F47: 0.201 - 2 | G47: 0.201 | H47: 2 | K47: 81 | L47: 23 | M47: 0.001
... B162: 南非 | C162: ZA | D162: 171 | E162: 26 | F162: 0.001 - 8 | G162: 0.001 | H162: 8 | K162: 171 | L162: 26 | M162: 0.05
B163: 国家 | C163: CountryCode | D163: 重量段(KG) | E163: 首重 | F163: 首重价格 | H163: =RIGHT(F163,5) -> 首重价格 | M163: 续重
B164: 日本 | C164: JP | D164: 0.001 - 2 | E164: 0.5 | F164: 31 | G164: 0.001 | H164: 2 | K164: 31 | L164: 5 | M164: 0.5
B165: 日本 | C165: JP | D165: 2.001 - 10 | E165: 0.5 | F165: 31 | G165: 2.001 | H165: 10 | K165: 31 | L165: 6 | M165: 0.5
B166: 国家 | C166: 分区 | D166: 公斤运费(元/KG) | E166: 处理费(元/件) | F166: 重量段(KG) | M166: 最小计费重量(KG)
B167: 澳大利亚 | C167: AU | D167: 51 | E167: 55 | F167: 0.001 - 0.5 | G167: 0.001 | H167: 0.5 | K167: 51 | L167: 55 | M167: 0.001
B168: 澳大利亚 | C168: AU | D168: 51 | E168: 95 | F168: 0.501 - 2 | G168: 0.501 | H168: 2 | K168: 51 | L168: 95 | M168: 0.001
B169: 澳大利亚 | C169: AU | D169: 51 | E169: 117 | F169: 2.001 - 5 | G169: 2.001 | H169: 5 | K169: 51 | L169: 117 | M169: 0.001
B170: 澳大利亚 | C170: AU | D170: 51 | E170: 132 | F170: 5.001 - 10 | G170: 5.001 | H170: 10 | K170: 51 | L170: 132 | M170: 0.001
B171: 澳大利亚 | C171: AU | D171: 51 | E171: 155 | F171: 10.001 - 22 | G171: 10.001 | H171: 22 | K171: 51 | L171: 155 | M171: 0.001
B173: 可提供全程追踪服务，请详见下方国家维度具体要求，参考时效为自然日
B174: 人民币计价，按克计费
B175: 无燃油附加费
B176: （1）英国、法国、德国、意大利、西班牙、荷兰、波兰、澳大利亚、新西兰、奥地利、葡萄牙、希腊、塞浦路斯、克罗地亚、斯洛文尼亚无50g起重 ；
B177: 其余国家50g起重，不足50g的部分按50g计价。
B178: （2）针对≤2kg货物，若泡重比≤1.5，免泡，按实际重量计费；若泡重比＞1.5，按包裹实际重量和体积重量相比，取较大者计费（体积重量计费方式为: 长*宽*高cm/8000=KG)
B179: （3）针对>2kg货物，按包裹实际重量和体积重量相比，取较大者计费（体积重量计费方式为: 长*宽*高cm/8000=KG)
B180: （4）税费汇率计算基准：以揽收日期所在周周一上午10点中行外汇牌价现汇卖出价汇率为基准计算。
B181: 注：
B182: 1：泡比计算方式与行业通用标准一致：（长*宽*高）/8000/实重
B183: 2：单件泡比过高或者批量单一品类泡货请提前沟通
B184: 3：服装类包括普通衣服、帽子、袜子等软包装/袋子包装货物不计泡，但不包含以下情况： （1）纸盒包装产品（包括内件和外包装）；（2）枕头，棉被，玩具娃娃等较泡的产品；
... B231: 暂无
B233: 国家 | C233: Country Code | D233: 参考时效 (自然日) | E233: 特殊要求 | F233: 申报价值 | G233: 重量要求 | H233: 包装尺寸 | J233: 派送地址要求 | K233: 退件重派 | M233: 税费征收说明
B234: 美国 | C234: US | D234: 8-15天 | E234: A.货物申报品名及相关信息，必须具体、精确，而某些常见的模糊描述将不再被接受；必须确保清关预报品名描述包括货物名称，用途，材质等信息； B.收件人名应该包括""名+姓""，而不是单名/单姓； C.请客户留意如实填写货物信息，并保证申报信息的真实性、准确性和完整性，我司对客户交寄的货物不具有审查义务，如因美国海关重新估值产生的扣关、延误、补交税款及额外罚款，我司保留追责和补收的权利。 | F234: 请如实申报，单个品名的申报价值需大于等于1美金，小于等于249美金；不接受同一个收件人名且同一个地址，当天累计包裹申报价值超过249美金。 | G234: 不超过30kg | H234: 1、不接受异形件如圆柱状，管状或者棱状包裹等 2、A. 最小尺寸 15*10*2cm B.最大尺寸：55*45*38cm（无需加收费用）； C.若发货包裹任意一边超最大尺寸但未超拒绝承运尺寸需加收100RMB。 3、美国拒绝承运包裹尺寸： 任意单边 >90cm或长+2x（宽+高）> 213cm。 若客户发运拒绝承运尺寸的包裹，我司将保留补收高额附加费权利。 | J234: 美国通达本土全境，但不接受APO/FPO地址、阿拉斯加、夏威夷等偏远地区，波多黎各、关岛等境外地址。限制邮编（前三位）：090-099、340、962-966、006-009、967-969、995-999。 | K234: 无退回中国服务，可提供本土重派服务，如需重派请在制单前联系您的燕文销售进行申请配置。自退回海外仓并通知客户包裹退回日起，30天内客户可选择重派，重派费用为50元/票，若超过30天无回复，包裹默认被销毁，销毁免费。 | M234: 关税费用根据美国海关执行的各HTS CODE对应税率收取（具体可查询CBP官网），税金我司垫付并随约定账期出具账单，因新的清关模式约束，我司无法提供各个包裹的税单凭证。
B235: 加拿大 | C235: CA | D235: 10-15天 | E235: 1. 过滤器、户外工具（管制刀具、火石、弹弓等）、手电筒（激光）、刀具、克隆粉（粉末）等，加拿大海关严查品名不建议申报。（filter，flashlight，laser，military，nunchakus，silencer等） 2. 若包裹因申报不正确、低报、瞒报、发运违禁品、侵权等不合规行为导致清关异常而产生异常费用（包括但不限于税费、罚款、销毁费等），具体判决结果以实际当地海关判定的为准，后期会统一向发件人收取 | F235: 请如实申报，申报价值不能超过300加币（约等同于210美金），其中5.001-30KG重量段申报价值限制不能低于20加币（约等同于13.9美金） | G235: 不超过30kg | H235: 不接受圆柱体和异型件，有特殊需求请咨询销售 最小为：15*10cm, 最大为: 最长边≤100cm，第二边长≤76cm, 长+2*宽+2*高≤250cm | J235: 1. 收件人名称必填且需提供收件人的全名-first name（名）and last name（姓），英文名字需要用空格隔开名和姓。 2. 商品中英文描述需详细且完整，申报超过20CAD的货物，必须在填申报品名时注明材质，如塑料玩具：plastic toys。 | K235: 无退回中国服务，可提供重派服务，个别服务无重派，具体请以客服通知为准。 重派费：首1KG为82RMB/票，续1KG为12RMB/票，不足1公斤按1公斤计费（含退回运费）。 | M235: DDP服务，加拿大免税额为20CAD，申报价值在20CAD以下，免税费； 申报价值超过20CAD（约等同13.9USD）时，我司将依据客户申报的产品价值收取20%税费
B236: 墨西哥 | C236: MX | D236: 15-30天 | E236: 因墨西哥海关针对原产中国的鞋类产品实施反倾销政策，增收高额反倾销税以及增值税，该渠道自2024.11.11起停收鞋类产品。 墨西哥海关将于2025年起正式开启查验包裏的收件人RFC/CURP信息，具体强制认证时间暂确认为2025年1月1日，建议发件人提前收集，并且下单时请开始在“税号”字段填写此信息，以下提供RFC/CURP税号规则，请参考。 RFC：由13位字符组成，格式为4位字母+6位数字+3位字母/数字。 CURP：由18位字符组成，格式为4位字母+6位数字+8位字母/数字 禁寄品主要类别： 1.个人护理、美容、按摩功能用品： 洗脸仪、吸黑头仪、电动牙刷、UV光面罩等美容仪；电动、非电动按摩仪器；减肥腰带、减肥仪；塑形、束腰类穿戴；脚趾矫正、牙齿保持器、牙齿矫正等正畸用品 2.三岁以下儿童用品、玩具： 所有适用于三岁及三岁以下儿童使用的物品，如奶嘴、婴儿水壶等。 3.医疗器械、用品：吸鼻器、听诊器、注射器、血氧仪、血压计、血压仪、血糖仪、体温计、温度计、心电仪、针灸仪，轮椅、负压器、耳镜、多普勒设备、电疗设备、牙科红外摄像仪内窥镜、助听器、理疗用品等医疗设备；止血带，创口贴等外用医疗用品； 4.空气、水等净化仪器和有消毒功能的物品：如空气净化器、水净化器，包括空气加湿器；带有消毒功能的仪器 5.涉及名牌、奢侈品、注册品牌物品： Gucci、Prada、Channel等奢侈品；带有著名品牌、奢侈品标志的物品；采用著名品牌、奢侈品牌设计的物品；涉及、带有知名动漫、电影人物形象的物品； 6.盗版、假冒、仿品：所有仿牌鞋服装、山寨电子产品等 7.特定种类的玩具：人形的、有人体形象的玩具、玩偶（如手办等），带有著名动画、影视人物图片、图标的玩具（如带有迪士尼、漫威人物的玩具） 8.成人用品、性玩具 9.涉及反倾销物品：自行车及自行车配件；木制铅笔、中性笔、圆珠笔；其他涉及反倾销的物品 10.其他：粉末、颗粒状：眼影、粉饼等； 液体状：护手霜、牙膏、护肤液、香水、指甲油等；针状物；墨粉、墨水 面膜类：面膜、鼻贴等 压缩喷剂：防晒喷剂等 下港敏感货物：头盔，面具，防护面具，雨伞等 防疫物资：任何形式的口罩，口罩滤片，酒精消毒纸巾，防护隔离面罩，测温枪，防护手套，防护服等 植物和植物材料：植物、花卉、种子 高货值：古董、文物、珠宝、黄金、白银、钻石、玉器、高价值字画等贵重货品 木制品：木盒，木勺，木桶，木铲，竹蒸笼，木质玩具（积木，孔明锁等），实木家具（如木桌，木椅，木书架…等），实木工具，非厨房用途的竹制品 燃油滤清器 | F236: 申报价值不能超过300美元，请注意，以下品名不接受50美元以下的低申报价值：Mobile Phone（手机），HD Media Player（高清媒体播放器），Multimedia Player（多媒体播放器），3D Printer（3D打印机），Tablet Notebook（平板笔记本），Laptop（笔记本电脑），CPU（中央处理器），Sports bracelet（运动手环）等； | G236: 不超过5kg | H236: 最大尺寸：长+宽+高＜150CM，最长边＜120CM | J236: 1.收件人电话：必填，格式要求为 52+8位数字或52+10位数字 2.邮编服务范围调整：新增部分邮编覆盖范围，具体通达覆盖邮编请参考报价单附录 | K236: 无退回中国服务，能否重派以实际收到重派通知为准，重派费25元/件 | M236: 墨西哥税费改为0起征，自2024年12月23日起到达我司揽收仓库的包裹，我司将代收代缴申报价值19%的综合税金。
B237: 波多黎各 | C237: PR | D237: 12-18天 | E237: A.货物申报品名及相关信息，必须具体、精确，而某些常见的模糊描述将不再被接受；必须确保清关预报品名描述包括货物名称，用途，材质等信息； B.收件人名应该包括""名+姓""，而不是单名/单姓； C.请客户留意如实填写货物信息，并保证申报信息的真实性、准确性和完整性，我司对客户交寄的货物不具有审查义务，如因美国海关重新估值产生的扣关、延误、补交税款及额外罚款，我司保留追责和补收的权利。 | F237: 请如实申报，单个品名的申报价值需大于等于1美金，小于等于249美金；不接受同一个收件人名且同一个地址，当天累计包裹申报价值超过249美金。 | G237: 不超过30kg | H237: 1、不接受异形件如圆柱状，管状或者棱状包裹等 2、A. 最小尺寸 15*10*2cm B.最大尺寸：55*45*38cm（无需加收费用）； C.若发货包裹任意一边超最大尺寸但未超拒绝承运尺寸需加收100RMB。 3、美国拒绝承运包裹尺寸： 任意单边 >90cm或长+2x（宽+高）> 213cm。 若客户发运拒绝承运尺寸的包裹，我司将保留补收高额附加费权利。 | J237: 可达006,007,009开头波多黎各地区邮编 | K237: 无退回中国服务，无重派服务，派送不成功默认销毁。 | M237: 关税费用根据美国海关执行的各HTS CODE对应税率收取（具体可查询CBP官网），税金我司垫付并随约定账期出具账单，因新的清关模式约束，我司无法提供各个包裹的税单凭证。
B238: 美国偏远地区 | C238: RA | D238: 12-18天 | E238: A.货物申报品名及相关信息，必须具体、精确，而某些常见的模糊描述将不再被接受；必须确保清关预报品名描述包括货物名称，用途，材质等信息； B.收件人名应该包括""名+姓""，而不是单名/单姓； C.请客户留意如实填写货物信息，并保证申报信息的真实性、准确性和完整性，我司对客户交寄的货物不具有审查义务，如因美国海关重新估值产生的扣关、延误、补交税款及额外罚款，我司保留追责和补收的权利。 | F238: 请如实申报，单个品名的申报价值需大于等于1美金，小于等于249美金；不接受同一个收件人名且同一个地址，当天累计包裹申报价值超过249美金。 | G238: 不超过30kg | H238: 1、不接受异形件如圆柱状，管状或者棱状包裹等 2、A. 最小尺寸 15*10*2cm B.最大尺寸：55*45*38cm（无需加收费用）； C.若发货包裹任意一边超最大尺寸但未超拒绝承运尺寸需加收100RMB。 3、美国拒绝承运包裹尺寸： 任意单边 >90cm或长+2x（宽+高）> 213cm。 若客户发运拒绝承运尺寸的包裹，我司将保留补收高额附加费权利。 | J238: 可达967（除96799）,968,995,996,997998,999开头的美国偏远地区（夏威夷&阿拉斯加）邮编。 | K238: 无退回中国服务，无重派服务，派送不成功默认销毁。 | M238: 关税费用根据美国海关执行的各HTS CODE对应税率收取（具体可查询CBP官网），税金我司垫付并随约定账期出具账单，因新的清关模式约束，我司无法提供各个包裹的税单凭证。
B239: 英国 | C239: GB | D239: 5-12天 | E239: - | F239: 英国（包括北爱尔兰地区）每日发给同一收件人包裹的合计申报价值＜135 英镑 为了预防万一，防止在海外查验时被要求提供相关信息，我们强烈建议！您在发货时，同时提供以下信息给我们，店铺的VAT税号，HS CODE 和销售订单号 order number。以上信息非必填。 | G239: 不超过20kg | H239: 0-20kg，单边不能超60CM，最大尺寸60*46*46 不接受圆柱体和异型件，有特殊需求请咨询销售 | J239: 1. 0-20kg 全境可达，军事地址除外 2. Jersey/Guernsey /Isle of Man 为偏远岛屿，派送至邮局无妥投节点 | K239: 1. 无退回中国服务； 2. 提供二次重派服务，可重派至英国境内(不含外岛)，重派期限为5天，即自通知客户包裹退回起，5天内，客户可选择重派，若不回复，超过5天后，包裹默认被销毁。重派费：45元/件； 3. 当包裹重量大于20kg或尺寸大于60*46*46cm，无二次重派服务。 | M239: 增值税0起征点，0-135英镑的货物都需要缴纳VAT，税率20%，无论是平台卖家/自建站客户/个人商户/都在销售环节缴纳，燕文不再收取VAT。
B240: 法国 | C240: FR | D240: 8-12天 | E240: 法国对于玩具、电子产品、眼镜、太阳眼镜这些类别的产品，商品本身需要带有CE标识，且被海关查验时需要及时提供证明，若查验未能及时提供证明会导致货物被扣押。 自2021年7月16日，全新的商品安全条例正式在欧盟国家生效，具体条例要求如下： 1 所有向法国境内出售的带有CE标志的商品，除了要持有CE认证标志外，还需要带有CE标志的产品具有法国境内负责人作为商品合规性的联系人； 2 在 7 月 16 日之后，向法国销售带有 CE 标志的商品，但没有位于法国境内的负责人属于违法行为； 3 您需要确保自己带有 CE 标志的商品贴有联系人的信息，此类标签可以贴在商品本身、商品包装、快递包裹或者随附文件上均可。 若不符合以上安全条例，将有可能出现被海关查验、扣关、销毁的情况，由此带来的费用及损失由客户自行承担，海关查验的费用以账单为准。 严禁发仿牌，如有违反，引致的损失、罚款、清关费用等及法律责任由客户承担。 | F240: 自2021年6月24日起，本产品发往欧盟27国的货物，每日发给同一收件人包裹的合计申报价值小于150欧元，均为DDP服务。暂不接受150欧元以上货物。 | G240: 不超过30kg | H240: 0-2KG 最长边≤60cm，长+宽+高≤90cm；2-30KG 最长边≤100cm，长+宽+高≤150cm 不接受圆柱体和异型件，有特殊需求请咨询销售 | J240: 1.不接受PO.BOX地址的包裹 2.邮编限制：必须为5位纯数字（海外省以及军事基地不可），邮编开头为00、97、98的法属岛屿区域不通达 3.含ARMEE/CEDEX不可以发 | K240: 无退回中国服务，能否重派以实际收到重派通知为准，重派费50元/件 | M240: 根据欧盟海关新政要求，从2021年7月1日起，欧盟27国取消22欧以下免税政策，0欧起征。新政实施的时间节点是以货物抵达清关口岸为准。 对于2021年6月24日上午8时后到仓货物，客户已经填写IOSS号的，按正常运费结算。对于没有填写或填写错误IOSS号的订单，默认由燕文预收增值税，收费税率标准为按各国应缴VAT标准税率统一增加2%收取，例如，荷兰VAT为21%，实收则为23%，且该部分税金无法用作未来的VAT进项抵扣。 凡是预缴税金的货物，收件人无需再支付税款。请如实申报，切勿低报，否则相关查验延误，扣留和罚款等风险均由发件人自行承担，同时，对低报货物，我司有权拒收。 货物因低报被法国海关查扣，要求按照实际价值缴纳税金和罚金，产生的费用由客户承担，费用以实际账单为准。
B241: 德国 | C241: DE | D241: 5-12天 | E241: 1. 海关查验货物包裹的销售链接请务必在48小时内提供，超时和未提供的将会产生150欧罚金且无法豁免； 2. 海关近期严查仿牌和假货，查出即罚没 | F241: 自2021年6月24日起，本产品发往欧盟27国的货物，每日发给同一收件人包裹的合计申报价值小于150欧元，均为DDP服务。暂不接受150欧元以上货物。 | G241: 不超过30kg | H241: 最大尺寸：60*50*40；最小尺寸：15*11*1。不接受圆柱体和异型件，有特殊需求请咨询销售 异形件说明： 1.库内判定是否为异形件，若确认为异形件，客服会联系客户确认处理方式：退回、换产品、继续发送。若确认继续通过原产品发送，需预付150元异形件费用； 2.异形件说明文档，请咨询相关客服。 | J241: 收件人姓名需跟地址对应门铃/邮箱上显示的姓名完全一致，否则可能影响包裹正常投递 | K241: 无退回中国服务，全重量段可提供重派和销毁服务，重派48元/票 | M241: 根据欧盟海关新政要求，从2021年7月1日起，欧盟27国取消22欧以下免税政策，0欧起征。新政实施的时间节点是以货物抵达清关口岸为准。对于2021年6月24日上午8时后到仓货物，客户已经填写IOSS号的，按正常运费结算。对于没有填写或填写错误IOSS号的订单，默认由燕文预收增值税，收费税率标准为按各国应缴VAT标准税率统一增加2%收取，例如，荷兰VAT为21%，实收则为23%，且该部分税金无法用作未来的VAT进项抵扣。凡是预缴税金的货物，收件人无需再支付税款。请如实申报，切勿低报，否则相关查验延误，扣留和罚款等风险均由发件人自行承担，同时，对低报货物，我司有权拒收。
B242: 意大利 | C242: IT | D242: 10-12天 | E242: 严禁发仿牌，如有违反，引致的损失、罚款、清关费用等及法律责任由客户承担。(155欧元/件） | F242: 自6月24日起，本产品发往欧盟27国的货物，每日发给同一收件人包裹的合计申报价值小于150欧元，均为DDP服务。暂不接受150欧元以上货物。 | G242: 不超过30kg | H242: 最大尺寸（实重）： 0-5kg：L≤60cm，W≤50cm，L+W+H≤130cm 5kg以上：120cm*50cm*40cm 不接受圆柱体和异型件 | J242: 系统会验证邮编有效性，通达邮编请见附件。具体请咨询客服。 | K242: 无退回中国服务，可提供重派服务，重派费50元/件 | M242: 根据欧盟海关新政要求，从2021年7月1日起，欧盟27国取消22欧以下免税政策，0欧起征。新政实施的时间节点是以货物抵达清关口岸为准。 对于2021年6月24日上午8时后到仓货物，客户已经填写IOSS号的，按正常运费结算。对于没有填写IOSS号的订单，默认由燕文预收增值税，收费税率标准为按各国应缴VAT标准税率统一增加2%收取，例如，荷兰VAT为21%，实收则为23%，且该部分税金无法用作未来的VAT进项抵扣。 凡是预缴税金的货物，收件人无需再支付税款。请如实申报，切勿低报，否则相关查验延误，扣留和罚款等风险均由发件人自行承担，同时，对低报货物，我司有权拒收。
B243: 西班牙 | C243: ES | D243: 7-12天 | E243: 一、禁寄品： 1.母婴用品：如奶嘴、奶瓶等婴儿用品； 2.药品及医疗器械：麻醉药、药膏、足贴、水银温度计等产品以及注射器、纹身针等对人体皮肤有强烈侵入性产品；听诊器、血氧仪、血压计、血压仪、血糖仪、体温计、温度计、心电仪、针灸仪、口罩、绷带，止血带，创口贴等医疗用品； 3. 手机、平板电脑、相机等高货值产品； 4. 山寨、仿牌、盗版及其他侵犯知识产权的产品； 5. 无人机 6. 其他含电含磁货物（普货渠道无法承运） 7.成人用品 二、其他品类： 1. 电子产品、电器、灯具、玩具类、机械类、带电产品、眼镜（太阳镜、光学眼镜、镜片等）等需要欧盟CE认证或产品上有CE标志，其中玩具类因涉及儿童健康，还需要EN71标准测试报告，主要涉及无毒无害证明，玩具上还要有具体吊牌、商标、适合年龄段等详细说明； 2. 塑料制品（塑料袋，塑料餐具，搅拌棒和吸管，气球棒，气球等），因涉及欧盟禁塑令，该类产品进口清关时海关查验扣货风险较高。 三、申报品名：申报品名应详细准确，和实物保持一致，不要填写笼统的泛指品名，如sample、gift、accessories、others等。 （清关敏感品名：clothes, gift, paint, tool,phone accessaries,phone case,medical, electronic,请谨慎申报） | F243: 自6月24日起，本产品发往欧盟27国的货物，每日发给同一收件人包裹的合计申报价值小于150欧元，均为DDP服务。暂不接受150欧元以上货物。 国外海关查验新要求： 货值小于150欧元的，需提供交易水单截图，交易截图、商业发票 注： 1、请在截止日期前提供所需文件资料或收件人联系方式（电话+email），逾期未提供文件资料的海关会直接联系收件人要交易证明 2、逾期提供或者默认销毁的可能会有150欧的罚款，销毁会产生20欧左右额外销毁费用，具体金额后续以海关账单为准 以下是对这几种文件的具体要求： 1、交易水单截图（Proof of Payment）,交易证明必需显示卖家或者买家的交易流水金额（例如信用卡和Paypal等证明） 2、交易截图，也就是订单截图（proof of order） 3、商业发票（货值大于等于150欧元，发票内必须注明收件人税号、 联系电话、有效的电子邮箱） | G243: 不超过30kg | H243: 长*宽*高≤60*50*40cm 不接受圆柱体和异型件，有特殊需求请咨询销售 | J243: 请见附件：部分国家通达邮编汇总 | K243: 无退回中国服务，无重派服务，派送不成功默认销毁。 | M243: 根据欧盟海关新政要求，从2021年7月1日起，欧盟27国取消22欧以下免税政策，0欧起征。新政实施的时间节点是以货物抵达清关口岸为准。 对于2021年6月24日上午8时后到仓货物，客户已经填写IOSS号的，按正常运费结算。对于没有填写IOSS号的订单，默认由燕文预收增值税，收费税率标准为按各国应缴VAT标准税率统一增加2%收取，例如，荷兰VAT为21%，实收则为23%，且该部分税金无法用作未来的VAT进项抵扣。 凡是预缴税金的货物，收件人无需再支付税款。请如实申报，切勿低报，否则相关查验延误，扣留和罚款等风险均由发件人自行承担，同时，对低报货物，我司有权拒收。
B244: 荷兰 | C244: NL | D244: 10-12天 | E244: ①收件人手机/电话必填其一 ②300g以上收件人邮箱必填 | F244: 自2021年6月24日起，本产品发往欧盟27国的货物，每日发给同一收件人包裹的合计申报价值小于150欧元，均为DDP服务。暂不接受150欧元以上货物。 | G244: 不超过30kg | H244: 0-300g：单边长＜60cm，长+宽+高＜90cm 300g以上：单边长＜60cm，长+宽+高＜120cm（如未填写收件人邮箱，限制长+宽+高＜90cm） 不接受圆柱体和异型件，有特殊需求请咨询销售 | J244: 不接受PO.BOX地址的包裹 门牌号必填 荷兰瓦登群岛不通达 不通达邮编： 1791AA to 1797ZZ 8880AA to 8899ZZ 9160AA to 9166ZZ | K244: 无退回中国服务，无重派服务，派送不成功默认销毁。 | M244: 根据欧盟海关新政要求，从2021年7月1日起，欧盟27国取消22欧以下免税政策，0欧起征。新政实施的时间节点是以货物抵达清关口岸为准。 对于2021年6月24日上午8时后到仓货物，客户已经填写IOSS号的，按正常运费结算。对于没有填写IOSS号的订单，默认由燕文预收增值税，收费税率标准为按各国应缴VAT标准税率统一增加2%收取，例如，荷兰VAT为21%，实收则为23%，且该部分税金无法用作未来的VAT进项抵扣。 凡是预缴税金的货物，收件人无需再支付税款。请如实申报，切勿低报，否则相关查验延误，扣留和罚款等风险均由发件人自行承担，同时，对低报货物，我司有权拒收。
... B255: 克罗地亚 | C255: HR | D255: 7-15天 | E255: - | F255: 自2021年6月24日起，本产品发往欧盟27国的货物，每日发给同一收件人包裹的合计申报价值小于150欧元，均为DDP服务。暂不接受150欧元以上货物。 | G255: 不超过30kg | H255: 最长边≤60cm，长+宽+高≤90cm 不接受圆柱体和异型件，有特殊需求请咨询销售 | J255: 地址需填门牌号，门牌号最多5位，格式如下： a）数字短横杠数字2-5 b）数字杠数字11/20 c）数字+字母123a | K255: 部分支持重派，以实际通知为准，重派费40元/件；没有退回国内服务，销毁免费 | M255: "根据欧盟海关新政要求，从2021年7月1日起，欧盟27国取消22欧以下免税政策，0欧起征。新政实施的时间节点是以货物抵达清关口岸为准。 对于2021年6月24日上午8时后到仓货物，客户已经填写IOSS号的，按正常运费结算。对于没有填写IOSS号的订单，默认由燕文预收增值税，收费税率标准为按各国应缴VAT标准税率统一增加2%收取，例如，荷兰VAT为21%，实收则为23%，且该部分税金无法用作未来的VAT进项抵扣。 凡是预缴税金的货物，收件人无需再支付税款。请如实申报，切勿低报，否则相关查验延误，扣留和罚款等风险均由发件人自行承担，同时，对低报货物，我司有权拒收。"
B256: 匈牙利 | C256: HU | D256: 7-15天 | F256: 自2021年6月24日起，本产品发往欧盟27国的货物，每日发给同一收件人包裹的合计申报价值小于150欧元，均为DDP服务。暂不接受150欧元以上货物。 | G256: 不超过30kg | H256: 最长边≤60cm，长+宽+高≤90cm 不接受圆柱体和异型件，有特殊需求请咨询销售 | J256: - | K256: 无退回中国服务，无重派服务，派送不成功默认销毁。 | M256: 根据欧盟海关新政要求，从2021年7月1日起，欧盟27国取消22欧以下免税政策，0欧起征。新政实施的时间节点是以货物抵达清关口岸为准。 对于2021年6月24日上午8时后到仓货物，客户已经填写IOSS号的，按正常运费结算。对于没有填写IOSS号的订单，默认由燕文预收增值税，收费税率标准为按各国应缴VAT标准税率统一增加2%收取，例如，荷兰VAT为21%，实收则为23%，且该部分税金无法用作未来的VAT进项抵扣。 凡是预缴税金的货物，收件人无需再支付税款。请如实申报，切勿低报，否则相关查验延误，扣留和罚款等风险均由发件人自行承担，同时，对低报货物，我司有权拒收。
B257: 爱尔兰 | C257: IE | D257: 7-15天 | E257: - | F257: 自6月24日起，本产品发往欧盟27国的货物，每日发给同一收件人包裹的合计申报价值小于150欧元，均为DDP服务。暂不接受150欧元以上货物。且申报价值不能低于1欧元。 | G257: 不超过20kg | H257: 最长边≤60cm，长+宽+高≤120cm，最大尺寸60*50*40 不接受圆柱体和异型件，有特殊需求请咨询销售 | J257: 只通达爱尔兰全境，若客户发到其他国家，将按以下标准收费：280元/件 | K257: 无退回中国服务，无重派服务，派送不成功默认销毁。 | M257: 根据欧盟海关新政要求，从2021年7月1日起，欧盟27国取消22欧以下免税政策，0欧起征。新政实施的时间节点是以货物抵达清关口岸为准。 对于2021年6月24日上午8时后到仓货物，客户已经填写IOSS号的，按正常运费结算。对于没有填写IOSS号的订单，默认由燕文预收增值税，收费税率标准为按各国应缴VAT标准税率统一增加2%收取，例如，荷兰VAT为21%，实收则为23%，且该部分税金无法用作未来的VAT进项抵扣。 凡是预缴税金的货物，收件人无需再支付税款。请如实申报，切勿低报，否则相关查验延误，扣留和罚款等风险均由发件人自行承担，同时，对低报货物，我司有权拒收。
B258: 立陶宛 | C258: LT | D258: 7-15天 | E258: - | F258: 自2021年6月24日起，本产品发往欧盟27国的货物，每日发给同一收件人包裹的合计申报价值小于150欧元，均为DDP服务。暂不接受150欧元以上货物。 | G258: 不超过30kg | H258: 最长边≤60cm，长+宽+高≤120cm 不接受圆柱体和异型件，有特殊需求请咨询销售 | J258: 1）州必填 2）电话号码格式：+3706xxxxxxx 3）末端当地派送到自提点，不送货上门。包裹到达自提点以后会短信/邮件通知收件人自提，所以收件人的联系方式非常重要，需要提供格式正确且能接收短信通知的收件人电话，同时建议提供收件人邮箱。 | K258: 1. 无退回中国服务； 2. 0-5kg可提供重派服务，重派期限为12天，即自通知客户包裹退回起，12天内，客户可选择重派，若超过12天后未回复，包裹默认销毁。重派费：40元/件。5-30kg无重派服务。具体重派服务以国外通知反馈为准。 | M258: "根据欧盟海关新政要求，从2021年7月1日起，欧盟27国取消22欧以下免税政策，0欧起征。新政实施的时间节点是以货物抵达清关口岸为准。 对于2021年6月24日上午8时后到仓货物，客户已经填写IOSS号的，按正常运费结算。对于没有填写IOSS号的订单，默认由燕文预收增值税，收费税率标准为按各国应缴VAT标准税率统一增加2%收取，例如，荷兰VAT为21%，实收则为23%，且该部分税金无法用作未来的VAT进项抵扣。 凡是预缴税金的货物，收件人无需再支付税款。请如实申报，切勿低报，否则相关查验延误，扣留和罚款等风险均由发件人自行承担，同时，对低报货物，我司有权拒收。"
B259: 卢森堡 | C259: LU | D259: 10-12天 | E259: - | F259: 自6月24日起，本产品发往欧盟27国的货物，每日发给同一收件人包裹的合计申报价值小于150欧元，均为DDP服务。暂不接受150欧元以上货物。 | G259: 不超过30kg | H259: 0-2kg：最长边≤60cm，长+宽+高≤90cm；2-30kg：最长边≤60cm，长+宽+高≤120cm 不接受圆柱体和异型件，有特殊需求请咨询销售 | J259: 系统会验证邮编有效性，通达邮编请见附件。具体请咨询客服。 | K259: 无退回中国服务，无重派服务，派送不成功默认销毁。 | M259: 根据欧盟海关新政要求，从2021年7月1日起，欧盟27国取消22欧以下免税政策，0欧起征。新政实施的时间节点是以货物抵达清关口岸为准。 对于2021年6月24日上午8时后到仓货物，客户已经填写IOSS号的，按正常运费结算。对于没有填写IOSS号的订单，默认由燕文预收增值税，收费税率标准为按各国应缴VAT标准税率统一增加2%收取，例如，荷兰VAT为21%，实收则为23%，且该部分税金无法用作未来的VAT进项抵扣。 凡是预缴税金的货物，收件人无需再支付税款。请如实申报，切勿低报，否则相关查验延误，扣留和罚款等风险均由发件人自行承担，同时，对低报货物，我司有权拒收。
B260: 拉脱维亚 | C260: LV | D260: 7-15天 | E260: - | F260: 自2021年6月24日起，本产品发往欧盟27国的货物，每日发给同一收件人包裹的合计申报价值小于150欧元，均为DDP服务。暂不接受150欧元以上货物。 | G260: 不超过30kg | H260: 最长边≤60cm，长+宽+高≤120cm 不接受圆柱体和异型件，有特殊需求请咨询销售 | J260: 电话号码格式： +3712xxxxxxx | K260: 1. 无退回中国服务； 2. 0-5kg可提供重派服务，重派期限为12天，即自通知客户包裹退回起，12天内，客户可选择重派，若超过12天后未回复，包裹默认销毁。重派费：40元/件。5-30kg无重派服务。具体重派服务以国外通知反馈为准。 | M260: "根据欧盟海关新政要求，从2021年7月1日起，欧盟27国取消22欧以下免税政策，0欧起征。新政实施的时间节点是以货物抵达清关口岸为准。 对于2021年6月24日上午8时后到仓货物，客户已经填写IOSS号的，按正常运费结算。对于没有填写IOSS号的订单，默认由燕文预收增值税，收费税率标准为按各国应缴VAT标准税率统一增加2%收取，例如，荷兰VAT为21%，实收则为23%，且该部分税金无法用作未来的VAT进项抵扣。 凡是预缴税金的货物，收件人无需再支付税款。请如实申报，切勿低报，否则相关查验延误，扣留和罚款等风险均由发件人自行承担，同时，对低报货物，我司有权拒收。"
B261: 马耳他 | C261: MT | D261: 7-15天 | E261: 需填写邮箱，邮箱规则如下：（0-9/A-Z）@（0-9/A-Z）.（0-9/A-Z） 例：sjahdvks@gmai.com | F261: 自6月24日起，本产品发往欧盟27国的货物，每日发给同一收件人包裹的合计申报价值小于150欧元，均为DDP服务。暂不接受150欧元以上货物。 | G261: 不超过20kg | H261: 最长边≤60cm，长+宽+高≤90cm， 不接受圆柱体和异型件，有特殊需求请咨询销售 | J261: - | K261: 无退回中国服务，0-30kg：可提供重派服务，重派费：50元/件 | M261: 根据欧盟海关新政要求，从2021年7月1日起，欧盟27国取消22欧以下免税政策，0欧起征。新政实施的时间节点是以货物抵达清关口岸为准。 对于2021年6月24日上午8时后到仓货物，客户已经填写IOSS号的，按正常运费结算。对于没有填写IOSS号的订单，默认由燕文预收增值税，收费税率标准为按各国应缴VAT标准税率统一增加2%收取，例如，荷兰VAT为21%，实收则为23%，且该部分税金无法用作未来的VAT进项抵扣。 凡是预缴税金的货物，收件人无需再支付税款。请如实申报，切勿低报，否则相关查验延误，扣留和罚款等风险均由发件人自行承担，同时，对低报货物，我司有权拒收。
B262: 挪威 | C262: NO | D262: 7-15天 | E262: 1）挪威路向VOEC税号必填，且需填写在“寄件人税号”框中；税号的填写格式为7位纯数字。VOEC税号备案需客户自主在燕文门户网站上进行申报备案，备案完成后方可发货。请您确保VOEC号码的正确性，若因税号信息不准确带来的一切后果由您自行承担。 2）邮编必须4位数字 3）手机号/电话号码必填其一，格式要求如下 a）如首位00、47、0047、4700、+47开头，后面手机位数长度要求大于等于6，小于等于50 b）不可以出现6个以及以上的相同数字或者连号 4）城市不能含数字 | F262: 最高不超过3000挪威克朗（约300欧元） | G262: 不超过5kg | H262: 1.标准尺寸：最长边≤45cm，三边和≤90cm，无附加费； 2.最大尺寸：45cm＜最长边≤60cm，90cm＜三边和≤120cm，此部分超尺订单将逐票发至客户处确认，并加收40元超尺附加费 3.不接受最长边>60cm或三边和＞120cm的包裹 4.不接受圆柱体和异型件，有特殊需求请咨询销售 5.超出标准尺寸包裹需要自提，请留意提供正确电话、邮箱信息 | J262: 不接受PO.BOX等邮箱地址 | K262: 无退回中国服务，不提供重派服务
B263: 波兰 | C263: PL | D263: 7-12天 | E263: - | F263: 自2021年6月24日起，本产品发往欧盟27国的货物，每日发给同一收件人包裹的合计申报价值小于150欧元，均为DDP服务。暂不接受150欧元以上货物。 | G263: 不超过20kg | H263: 1）最大尺寸60*50*40cm 2）不接受圆柱体和异型件，有特殊需求请咨询销售 异形件说明： 若确认为异形件，需收取32元/件的费用 | J263: 1）波兰的地址，若有门牌号的，需要填写门牌号。若未填写，可能会导致退件。 2）电话格式要求：9位纯数字 3）邮编格式：2位数字+横杠+3位数字 | K263: 无退回中国服务，无重派服务，派送不成功默认销毁。 | M263: 根据欧盟海关新政要求，从2021年7月1日起，欧盟27国取消22欧以下免税政策，0欧起征。新政实施的时间节点是以货物抵达清关口岸为准。 对于2021年6月24日上午8时后到仓货物，客户已经填写IOSS号的，按正常运费结算。对于没有填写IOSS号的订单，默认由燕文预收增值税，收费税率标准为按各国应缴VAT标准税率统一增加2%收取，例如，荷兰VAT为21%，实收则为23%，且该部分税金无法用作未来的VAT进项抵扣。 凡是预缴税金的货物，收件人无需再支付税款。请如实申报，切勿低报，否则相关查验延误，扣留和罚款等风险均由发件人自行承担，同时，对低报货物，我司有权拒收。
B264: 葡萄牙 | C264: PT | D264: 7-12天 | E264: 一、禁寄品： 1.母婴用品：如奶嘴、奶瓶等婴儿用品； 2.药品及医疗器械：麻醉药、药膏、足贴、水银温度计等产品以及注射器、纹身针等对人体皮肤有强烈侵入性产品；听诊器、血氧仪、血压计、血压仪、血糖仪、体温计、温度计、心电仪、针灸仪、口罩、绷带，止血带，创口贴等医疗用品； 3. 手机、平板电脑、相机等高货值产品； 4. 山寨、仿牌、盗版及其他侵犯知识产权的产品； 5. 无人机 6. 其他含电含磁货物（普货渠道无法承运） 7.成人用品 二、其他品类： 1. 电子产品、电器、灯具、玩具类、机械类、带电产品、眼镜（太阳镜、光学眼镜、镜片等）等需要欧盟CE认证或产品上有CE标志，其中玩具类因涉及儿童健康，还需要EN71标准测试报告，主要涉及无毒无害证明，玩具上还要有具体吊牌、商标、适合年龄段等详细说明； 2. 塑料制品（塑料袋，塑料餐具，搅拌棒和吸管，气球棒，气球等），因涉及欧盟禁塑令，该类产品进口清关时海关查验扣货风险较高。 三、申报品名：申报品名应详细准确，和实物保持一致，不要填写笼统的泛指品名，如sample、gift、accessories、others等。 （清关敏感品名：clothes, gift, paint, tool,phone accessaries,phone case,medical, electronic,请谨慎申报） | F264: 自6月24日起，本产品发往欧盟27国的货物，每日发给同一收件人包裹的合计申报价值小于150欧元，均为DDP服务。暂不接受150欧元以上货物。 | G264: 不超过30kg | H264: 长*宽*高≤60*50*40cm 不接受圆柱体和异型件，有特殊需求请咨询销售 | J264: 不接受9开头的偏远邮编 | K264: 无退回中国服务，无重派服务，派送不成功默认销毁。 | M264: 根据欧盟海关新政要求，从2021年7月1日起，欧盟27国取消22欧以下免税政策，0欧起征。新政实施的时间节点是以货物抵达清关口岸为准。 对于2021年6月24日上午8时后到仓货物，客户已经填写IOSS号的，按正常运费结算。对于没有填写IOSS号的订单，默认由燕文预收增值税，收费税率标准为按各国应缴VAT标准税率统一增加2%收取，例如，荷兰VAT为21%，实收则为23%，且该部分税金无法用作未来的VAT进项抵扣。 凡是预缴税金的货物，收件人无需再支付税款。请如实申报，切勿低报，否则相关查验延误，扣留和罚款等风险均由发件人自行承担，同时，对低报货物，我司有权拒收。
B265: 罗马尼亚 | C265: RO | D265: 7-15天 | E265: - | F265: 自2021年6月24日起，本产品发往欧盟27国的货物，每日发给同一收件人包裹的合计申报价值小于150欧元，均为DDP服务。暂不接受150欧元以上货物。 | G265: 不超过30kg | H265: 最长边≤60cm，长+宽+高≤90cm 不接受圆柱体和异型件，有特殊需求请咨询销售 | J265: 电话号码的格式：7XXXXXXXX，07XXXXXXXX，407XXXXXXXX，+407XXXXXXXX | K265: 无退回中国服务，不提供重派 | M265: "根据欧盟海关新政要求，从2021年7月1日起，欧盟27国取消22欧以下免税政策，0欧起征。新政实施的时间节点是以货物抵达清关口岸为准。 对于2021年6月24日上午8时后到仓货物，客户已经填写IOSS号的，按正常运费结算。对于没有填写IOSS号的订单，默认由燕文预收增值税，收费税率标准为按各国应缴VAT标准税率统一增加2%收取，例如，荷兰VAT为21%，实收则为23%，且该部分税金无法用作未来的VAT进项抵扣。 凡是预缴税金的货物，收件人无需再支付税款。请如实申报，切勿低报，否则相关查验延误，扣留和罚款等风险均由发件人自行承担，同时，对低报货物，我司有权拒收。"
B266: 瑞典 | C266: SE | D266: 7-15天 | E266: 1. 2024年3月11日更新：海关目前严查太阳眼镜相关产品，请避免发送相关产品。海关查验货物包裹的销售链接请务必在48小时内提供，超时和未提供的部分会产生150欧罚金且无法豁免，需客户自行承担； 2. 海关近期严查仿牌和假货，查出即罚没，并会产生罚金由客户自行承担； 3. 2KG以上为自提服务，请提供准确电话号码接收提货通知。 | F266: 自6月24日起，本产品发往欧盟27国的货物，每日发给同一收件人包裹的合计申报价值小于150欧元，均为DDP服务。暂不接受150欧元以上货物。 | G266: 不超过20kg | H266: 0-5KG:最长边≤60cm，长+宽+高≤90cm， 5.001-20KG：单边≤60cm，长+宽+高≤120cm 不接受圆柱体和异型件，有特殊需求请咨询销售 | K266: 无退回中国服务，部分提供重派，能否重派以实际收到重派通知为准，重派费：50元/件 | M266: 根据欧盟海关新政要求，从2021年7月1日起，欧盟27国取消22欧以下免税政策，0欧起征。新政实施的时间节点是以货物抵达清关口岸为准。 对于2021年6月24日上午8时后到仓货物，客户已经填写IOSS号的，按正常运费结算。对于没有填写IOSS号的订单，默认由燕文预收增值税，收费税率标准为按各国应缴VAT标准税率统一增加2%收取，例如，荷兰VAT为21%，实收则为23%，且该部分税金无法用作未来的VAT进项抵扣。 凡是预缴税金的货物，收件人无需再支付税款。请如实申报，切勿低报，否则相关查验延误，扣留和罚款等风险均由发件人自行承担，同时，对低报货物，我司有权拒收。
B267: 斯洛文尼亚 | C267: SI | D267: 7-15天 | E267: - | F267: 自2021年6月24日起，本产品发往欧盟27国的货物，每日发给同一收件人包裹的合计申报价值小于150欧元，均为DDP服务。暂不接受150欧元以上货物。 | G267: 不超过30kg | H267: 长+宽+高,(0,90],最长边,(0,60] 不接受圆柱体和异型件，有特殊需求请咨询销售 | J267: 1.收件人电话必填 2.地址需填门牌号，门牌号最多5位，格式如下： a）数字短横杠数字2-5 b）数字杠数字11/20 c）数字+字母123a | K267: 无重派；没有退回国内服务，销毁免费 | M267: "根据欧盟海关新政要求，从2021年7月1日起，欧盟27国取消22欧以下免税政策，0欧起征。新政实施的时间节点是以货物抵达清关口岸为准。 对于2021年6月24日上午8时后到仓货物，客户已经填写IOSS号的，按正常运费结算。对于没有填写IOSS号的订单，默认由燕文预收增值税，收费税率标准为按各国应缴VAT标准税率统一增加2%收取，例如，荷兰VAT为21%，实收则为23%，且该部分税金无法用作未来的VAT进项抵扣。 凡是预缴税金的货物，收件人无需再支付税款。请如实申报，切勿低报，否则相关查验延误，扣留和罚款等风险均由发件人自行承担，同时，对低报货物，我司有权拒收。"
B268: 斯洛伐克 | C268: SK | D268: 7-15天 | E268: - | F268: 自2021年6月24日起，本产品发往欧盟27国的货物，每日发给同一收件人包裹的合计申报价值小于150欧元，均为DDP服务。暂不接受150欧元以上货物。 | G268: 不超过30kg | H268: 最长边≤60cm，长+宽+高≤90cm 不接受圆柱体和异型件，有特殊需求请咨询销售 | J268: 1）邮编格式：5位纯数字 2）地址需填门牌号，门牌号最多5位，格式如下： a）数字短横杠数字2-5 b）数字杠数字11/20 c）数字+字母123a 电话限制： 电话必填：9位数，前可加区号：+00421、00421、00421-、+421、421-、421、 | K268: 无退回中国服务，无重派服务，派送不成功默认销毁。 | M268: 根据欧盟海关新政要求，从2021年7月1日起，欧盟27国取消22欧以下免税政策，0欧起征。新政实施的时间节点是以货物抵达清关口岸为准。 对于2021年6月24日上午8时后到仓货物，客户已经填写IOSS号的，按正常运费结算。对于没有填写IOSS号的订单，默认由燕文预收增值税，收费税率标准为按各国应缴VAT标准税率统一增加2%收取，例如，荷兰VAT为21%，实收则为23%，且该部分税金无法用作未来的VAT进项抵扣。 凡是预缴税金的货物，收件人无需再支付税款。请如实申报，切勿低报，否则相关查验延误，扣留和罚款等风险均由发件人自行承担，同时，对低报货物，我司有权拒收。
B269: 乌克兰 | C269: UA | D269: 7-15天 | E269: 禁运品主要类别：路由设备 | F269: 对于同一个收货人，同一天的申报总价值不能超过100欧元（2019年7月1日开始） | G269: 不超过30kg | H269: 1. 不接受圆柱形和异型包裹 2. 长宽高＜100×50×40cm，最长边＜100cm | J269: 只接受表格内邮编（详见附录），具体请咨询客服。 | K269: 无退回中国服务，不提供重派服务，退件默认销毁 | M269: 对于同一个收货人，同一天的申报总价值150欧元以内免税。
B270: 巴西 | C270: BR | D270: 15-25天 | E270: 1. 税号必填 ：格式为去除符号后仅11位数字。示例：自然人税号称为CPF码，如000.000.000-00。 2. 英文品名字符长度不超过200个字符（字符过多会影响面单信息展示）。 3. 需要规范申报，具体包含：品名/材质/类型/规格/用途等信息，若申报品名较为笼统可能会因申报信息不全而被扣件。 （1）避免申报大类模糊品名，过于宽泛的品名较易引起海关扣件。反面申报案例：“玩具”，“装饰品”，“摆件”，“电子产品”等，均易引起海关质疑。 （2）避免简单申报单一品名（如只申报“奖牌”，“手表”，“手机壳”等），影响海关辨别实际商品。请尽量详细申报，包括但不限于商品详细名称+规格+型号+数量+颜色等，便于海关根据申报品名判断包裹内实际商品。 （3）避免出现“加密”“保密”等敏感词汇，此类申报会引起海关担忧包裹有信息入侵风险。反面案例：“加密硬件钱包”。 （4）避免发运疑似商用产品如“白色黏土”、“机箱盖子”、“手机液晶屏”等，另同批次同一收件人收货数量过多，也容易让海关怀疑包裹有商用嫌疑。 4. 确保收件人税号与本人信息一致。 5. 从8月下旬开始，海关严格审查申报海关编码（海关H.S编码）与实物的对应关系； 申报时要求填写商品真实的前8位海关编码，海关编码的查询网址：https://portalunico.siscomex.gov.br/classif/#/sumario?perfil=publico ，填报虚假海关编码的行为会被视为虚假申报而停止下一步的操作与清关。 | F270: 1.申报品名规范标准：产品描述尽可能详尽，可在申报品名中添加商品品名，品牌，型号，材质，颜色，大小，功能等。现巴西海关加强清关查验， 建议补充完整申报品名信息，避免申报模糊导致海关查扣，清关失败。 2. 请如实申报，5USD ≤ 申报价值＜50USD 3. 建议同个批次同个收件人包裹最多不要超过2个，申报价值总计不能超过50USD；单个包裹建议1-2个内件，超过可能有被海关定义模式改变产生罚款的风险。 | G270: 不超过5kg | H270: 尺寸要求：尺寸要求：1CM≤最短边≤100CM，10CM≤第二长边≤100CM，15CM≤最长边≤100CM 长+宽+高≤200CM,不接受异形件。 包装要求：1、不要使用黄色胶带包装/缠绕；2、不要使用透明气泡膜包装/缠绕；3、不要使用透明胶粘多个小包在一起。 | J270: 1.州，城市，邮编必填（邮编需要具体到收件人地址中的街道） 2.地址1或地址2字段必须包含数字（数字代表巴西境内的门牌号） 3.收件人手机/电话必填其一，格式为不含国家代码（+55）的10或者11位数字 4. 收件人邮箱必填 | K270: 无退回中国服务，支持当地重派服务：0-2kg 50元/票,2-3kg 60元/票；自通知客户包裹退回日起，15天内客户可选择重派，超期默认销毁 | M270: 巴西海关严查低申报，要求如实申报。实际税费情况需以海关判定为准，清关过程中若产生增值税或关税，海关会向收件人收取。
B271: 智利 | C271: CL | D271: 12-20天 | E271: 1. 收件人税号必填，税号参考格式：xxxxxxx-y或 xxxxxxxx-y，‘’x‘’代表数字，‘’y‘’代表数字或大写字母”K”，如 18121446-5，22272244-K 2. 普货产品禁发任何带电、液体、粉末物品 | F271: 1.请如实申报，2023年5月10日起申报价值不能超过41美元 2.同个批次同个收件人包裹申报价值总计不能超过41美元 | G271: 不超过5kg | H271: 尺寸要求：10CM≤最长边≤100CM，长+宽+高≤200CM,不接受异形件。 | J271: 城市名称需填写准确，如圣地亚哥大都会区-塞里洛斯（Metropolitana de Santiago-Cerrillos），【城市】请填写“Cerrillos”，如填写“Santiago”可能会导致派送失败。 | K271: 1）无退回中国服务 2）无重派服务，派送不成功默认销毁。 | M271: 一般情况下，申报价值41美元内免征关税，具体需要以海关判定为准；若经海关核实，实际货物价值超过41美金，产生的相关费用由发件人承担。
B272: 哥伦比亚 | C272: CO | D272: 15-30天 | E272: 申报品名不要包含“无线”、“蓝牙”等字眼，否则容易被海关查验扣关。 | F272: 请如实申报，申报价值≤200美元，最低申报价值不能低于5USD，最高不能超过200USD。 | G272: 不超过3kg | H272: 尺寸要求：10CM≤最长边≤90CM，长+宽+高≤150CM | J272: - | K272: 无退回中国服务，无重派服务。 收件人地址/电话有误联系不上收件人的，或是郊外偏远地区派件时效较久的情况，收件人可通过以下联系方式自行联系当地邮政： 1）哥伦比亚邮政官网：https://www.4-72.com.co/ 2）哥伦比亚邮政联系方式： Diagonal 25 G # 95 A 55, Bogotá - Colombia - ZIP Code: 11091 Administrative Headquarters: (+57) (601) 472 2005 Physical and electronic channels for customer service You can report on the Anti-Corruption Line:?(+57) (601) 4722005 Options 6 and then * Free line: 01 8000 111 210 Contact Center: (+57) (601) 472 2000 Customer service:??servicioalcliente@4-72.com.co Judicial notifications:??notificaciones.judiciales@4-72.com.co | M272: 货物申报价值≤200USD免征关税，最低申报价值不能低于5USD，最高不能超过200USD。 针对以下两种情况 从2023年3月6日起需要额外收取费用： 1. 如果包裹被海关重新调整价值，客户提交文件申诉，则需要交15美金的申诉费用，无论申诉成功与否。但是如果客户决定弃件或者直接缴税，则不收取此费用。 2. 如果包裹被哥伦比亚海关定义为“模式改变”，则须向发件人收取40美金，无论客户决定弃件、还是找清关代理清关（清关费用500美元，需收件人支付）都需缴纳此费用。 A. 据服务商解释，收取该费用的原因是尾程服务商为了履行海关的新流程，须将货物运送到海关履行相关规范而产生的额外费用，这个费用需要发货人承担，因为发货人未按要求发运产品。 B. 被海关定义为“模式改变” 的产品类型主要有： a）包裹数量超限，涉嫌商业用途（普通用品同一类别不超过6个项目）； b）违禁产品和危险用品； c）虚假申报，产品名和实际申报不符； d）受限制品，缺乏相关证书。
B273: 秘鲁 | C273: PE | D273: 20-40天 | E273: - | F273: 请如实申报，申报价值不能超过200美元 | G273: 不超过2kg | H273: 单边长度≤60cm，长+宽+高≤90cm | J273: 地址信息需填写准确，错误的地址可能会导致妥投失败，具体请参考附录VII-部分国家州城市对应关系 | K273: 无退回中国服务，无重派服务，派送不成功默认销毁。 | M273: 申报价值200美元以免征关税
B274: 澳大利亚 | C274: AU | D274: 8-15天 | E274: 禁寄品主要类别：请避免植物、花卉、藤编、竹编制品、木制品、危险品、不明液体、禁止进口等物品的派发，以避免销毁；如发送禁寄品会造成海关查验费及销毁处理等费用由客户承担。 文件：资料（发票、图片）的提供，请确保图片清晰，资料相互统一。文件资料模糊或者不匹配将会影响AQIS部门海关审核，增大销毁几率。 | F274: 请如实申报，申报价值不能超过1000澳元 | G274: 不超过22kg | H274: 最长边＜100CM，体积≤0.25m3 | J274: 1.收件人电话需必填，只允许数字与“+-（）”及空格除此之外不能包含其他特殊符号。 2.收件人地址需准确且完整有街道号门牌号，邮编和城市洲省一致。 3.通达澳大利亚全境，支持P.O.Box、自提柜地址。 4.商业快递+邮政快递派送。 5.澳大利亚邮编请查看附录VIII“国家分组-澳洲邮编”或咨询销售和客服索取。 6.若地址信息潦草或不详、不适宜派送（个别街区，邮政车辆开不进去）、发件人要求返回签收记录, 不适用safe drop 的包裹或者收件人被邮政黑名单，包裹都不会派送需自提。 | K274: 无退回中国服务，可提供重派服务，重派费：50元/件，销毁免费 | M274: 申报价值1000澳元内免征关税
B275: 新西兰 | C275: NZ | D275: 8-15天 | E275: -禁止发送任何动植物、植物/木材相关物品。例：干花或活花、种子或松果、蜂蜡或蜂蜜、动物产品或器官藤条、藤条或任何与木材相关的物品。武器、枪支弹药、轮胎、烟草、石棉、农产品、食品、生鲜食品、易燃易爆物品、儿童蜡笔、指画和水彩画、仿牌/侵权产品、无线电干扰设备、有毒有害物质；肥料、药物/片剂/化学溶液等；违反要求发货产生的后果及相关费用由发件人承担! -无偏远附加费；请按正确地址进行填写，避免派送失败情况； 新西兰海关要求收件人必须完整的姓名，必须有“名字”和“姓”，写于收件人姓名一栏！！！ | F275: 请如实申报，申报价值不能超过1000NZD（新西兰币） | G275: 不超过25kg | H275: 最长边≤150cm，体积≤0.125m3 | J275: 2025年2月19日起，针对WAIHEKE ISLAND、GREAT BARRIER ISLAND、STEWART ISLAND、CHATHAM ISLAND四个岛屿地址共计15个邮编收取180元/票的超偏远附加费，具体邮编如下 1081 1840 1841 1842 1843 1971 0961 0991 0960 0962 0963 8013 8016 8942 8944 | K275: 无退回中国服务，可提供重派服务，重派费：35元/件，销毁免费 | M275: 申报价值1000NZD（新西兰币）内免征关税
B276: 日本 | C276: JP | D276: 3-9天 | E276: 1、禁寄品主要类别：仿牌及侵权商品、二手物品、带度数的眼镜及镜片、化妆品、美容工具、纹身工具、6岁以下儿童玩具、成人用品、针织类商品、皮革材质类商品、添加石棉的商品、含有活性炭的商品、银行卡、学生证、在留卡、纹身针、货值超过1万日元或商品数量超过属于合理自用范围的包裹（非医用口罩每个收件人少于100枚、按摩工具、温度计、接触食物和口腔的物品等每个收件人仅限1件）。 2、如发送禁寄品会造成海关查验费、销毁处理费、清关手续费及关税等费用由发件人自行承担。 3、本渠道为目的国个人清关渠道，不接受任何B类（公司）性质的收件人和亚马逊仓收件地址的包裹，内件商品数量符合个人自用范围（每批次同一个收件人只能一个包裹）否则会产生清关关税、内点费、仓储费等费用由发件人自行承担。 4、发货前请与你的专属销售确认，如发送禁寄品会造成海关查验费、销毁处理费、清关手续费及关税等费用由发件人自行承担。 5、08099761533 此电话号码已进入海关黑名单，建议不要使用此号码发货，请填写收件人真实的电话号码 大阪府 門真市 深田町 20-2 株式トライワーク内 （株）つなぐ 此地址为仓库地址，已进入海关黑名单，建议不要使用此地址发货，请填写收件人真实的个人地址 6、清关时因仿牌、侵权及资料不完整，申报收件人及品名信息不实等原因，无法清关滞留在海关仓库的包裹，产生的所有费用由发件人承担。 | F276: 请如实申报，申报价值不能超过10000日元，同一天同一收件人多票的申报价值也不能超过限制，请注意低申报会影响清关时效。 | G276: 不超过10kg | H276: 最长边≤100CM，长+宽+高＜160cm | J276: 1.收件人名称必须是真实的个人姓名，也支持用英文字母填写的姓名，填写时确保姓氏和名字完整，不可出现只有姓氏或只有名字或者姓氏加尊称的情况，英文名字需要用空格隔开姓和名。日本人的姓名常见的是3-5位的日文汉字，例如正常填写的日本人姓名：“ 藤田泰彦、清川 覚、戸田 慶三郎 ”。基本不会出现名字中含有片/平假名这类非正式的姓名，例如：“ くどう しんいち、工藤 しんいち ”。 2.收件人电话需必填，格式为0开头的10位数座机号（0xxxxxxxxx）或者11位数手机号（0x0xxxxxxxx），不需要填写国际区号如“+81-”不能包含特殊字符。 3.收件人地址需准确且完整有街道号门牌号，邮编和城市洲省一致。 4.2025年1月22日开始，仅对 沖縄県 收取偏远费每票100元，偏远邮编请咨询客服（详见附录）。 如果因为收件人信息填写不准确或者申报信息有误等原因导致清关扣件产生的额外税费等，需要发件人承担。 | K276: 无退回中国服务，派送不成功会退回日本当地中转仓，免费保存14天，超期自动销毁。可提供重派服务，重派费：55元/件，在清关当中发现的问题件产生相关费用需要客户承担，若因客户原因产生相应的仓储费需要客户承担，清关阶段问题件超14天未确认的默认销毁，因客户原因产生的费用以账单为准；退件逾期未处理默认销毁，销毁免费； | M276: 申报价值10000日元内免征关税
B277: 中国香港 | C277: HK | D277: 3-7天 | E277: 收件人电话必填，香港电话号码格式为 : 852区号（区号可不填）+2，5 , 6 , 8 , 9开头8位数 | F277: - | G277: 不超过20kg | H277: 最长边不超过100cm，长+宽+高不超过150cm。 | J277: 以下离岛地区不提供派送服务：大屿山，即）：大澳、梅窝、愉景湾、马湾 (Tai O / Mui Wo / Ma Wan / Discovery Bay)，长洲 Cheung Chau，坪洲 Peng Chau，南丫岛 Lamma Island，蒲台岛，索科群岛，塔门，东平洲，不能派送PO BOX地址 | K277: 无退回中国服务，可提供重派服务，重派费：30元/件，退件会在库内保存1个月，逾期默认销毁，销毁免费。
B278: 印度 | C278: IN | D278: 全段时效：10-13天 | E278: 二、品类限制及描述 1、不接收成人用品、毒品、危险品、化学品、液态物品、粉末、生化制品、生鲜物品、食品、药品、仿冒及侵权物品等以及各种侵权、仿牌物品，纯电、手机、通讯用品，平板电脑、笔记本电脑、无人机、无人机配件、摄像机、平衡车、充电宝、手机/笔记本电脑电池、对讲机、U盘、电子钱包等。冲货发违禁品造成一切罚款与损失由发件人承担，我司有权追究发件人责任。 2、必须提供电话号码，且电话号码格式为：区号91+10位数字 3、制氧机免税，但需要额外支付12%GST费用+20RMB/票处理费 4、商业清关DDP服务，申报价值不超过50美元，免征税费；请如实申报，严禁低报，在目的国清关因低报造成的费用以及处理后果均由发件人承担。 5. 印度的电话号码格式除国际区号外以9,8,7,6开头的10位数字，必须要是手机因为要接收KYC认证消息。 三、限制物品： 由于印巴边境局势敏感, 现海关通知以下物品严格禁止运往印度： 1. 无人机（所有类型，包括商用、休闲和军用级） 2. 无人机零件及配件（电机、螺旋桨、控制器、GPS 模块等） 3. 监控设备 o 具有录制/流媒体功能的摄像头 o 夜视设备 o 远程或高分辨率光学设备 4. 数据存储和电子设备 o 硬盘、固态硬盘 (SSD)、USB 闪存盘 o 加密设备 o 具有存储/内存的计算机组件（例如 RAM、微芯片） o 5. 通信和 GPS 设备 o 卫星电话 o 无线电收发器（非标准频率） o GPS 追踪器/地图工具 6. 军民两用技术（具有潜在军事用途的物品） | F278: 请如实申报，申报价值<=50美元 | G278: 不超过30kg | H278: 2W+2H＜150cm | J278: - | K278: 重派费用说明： 0-0.5kg 70元/件； 0.501-1kg 120元/件； 1-1.5kg 170元/件； 1.501-2kg 220元/件； 2-5kg 350元/件； 5-10kg 550元/件； 10-30kg 1500元/件 此国家无退回国内服务 海外仓退件会保留14天，超期则默认销毁； | M278: 商业清关DDP服务
B279: 韩国 | C279: KR | D279: 7-13天 | E279: （1）收件人电话需必填，格式为010+8位数字，支持符号- + 空格， 共11位纯数字； （2）收件人税号需必填，格式为P开头+12位数字； （3）请一定正确填写收件人姓名、电话、个人通关码和详细地址信息。品名、规格、数量、价格、收件人信息等不正确的情况，清关会加收清关手续费1000韩币。收件人地址信息不详细不正确会产生高额罚款，罚款由发件人/收件人承担。 3C类产品清关会找加收清关手续费1000韩币，收件人不给的情况下会找发件人收取； （4）禁发侵权商品、成人用品、未加工的水果蔬菜肉类、瞄准器、纹身相关产品、针头等； （5）请如实申报包裹内的品名，在单个包裹内有多种品名的情况下，请务必在“中文品名”、“英文品名”栏或“具体品名”栏内如实写清楚所有品名，且商品总件量需与实际情况相符，如出现瞒报、漏报等情况会产生清关费用及5万至10万韩币罚款（费用由发件人承担）； （6）每个收件人每个包裹内的用电类产品限发一件，超过限制件数韩国海关会要求提供韩国KC认证，即使提供了KC认证且商品价值在免税额以下也需要缴纳相关税费； (7)禁止出口尿素类化肥产品，禁止以简化申报形式报关出口。 (8)以下不适用目录清关的商品种类，会产生关税、手续费、罚款等由发件人承担； 1. 药品、医疗用品及器材（如体温计） 2. 中药材 3. 野生动物相关产品 4. 农产品和畜产品等检验检疫对象商品 5. 保健品 6. 侵权商品 7. 食品类、酒类、烟类 8. 化妆品（限功能性化妆品、含胎盘化妆品、含类固醇化妆品、无法确认成分的有害化妆品）、洗涤用品 9. 修改申报内容，报关产品有新增的情况 10. 单上的品名、规格、数量、价格、收件人地址、收件人联系方式等不准确的商品 11. 此外，《关税法》第226条规定的需要海关总署确认对象商品及海关总署不认可目录清关的商品 (9)无线耳机、无线音响、手机、笔记本电脑、蓝牙。wifi等无线设备及电子仪器(含零部件)（HS CODE85类产品）需申报简易清关，费用1000韩币，此费用默认为发件人支付。 （10）个人通关码可先在此网址进行校验：http://inspection.e-kc.vip/ （11）同一入港日期，抵达的包裹物品超过2件的多到件认为不属于个人使用范围，需要额外的清关操作及收取相关费用。同一包裹申报数量建议不超过20个。 （12）近期韩国海关提高了吸尘器、烘干机、扬声器等产品的检查率，申报时请注意填写准确的申报金额；还有知名品牌的仿牌，有可能被海关认定为侵权产品。 （13）戴森产品的吹风机、吸尘器等仿牌货物，以及其他侵犯知识产权的物品，寄过去后，假货会全部销毁；所以请不要寄不是正品的货物，即使寄过去，也需要两周时间拿到鉴定结果。 （14）清关时因仿牌、侵权及资料不完整，申报收件人及品名信息不实等原因，无法清关滞留在海关仓库的包裹，产生的所有费用由发件人承担。 （15）不收异形件和超尺寸件，异形件和超尺寸件会转交其他服务进行派送，因此产生的附加费实报实销 | F279: 申报价值＜150美金，且符合个人自用的原则。本渠道为目的国个人清关渠道，收件人必须为个人不接受任何B类（公司）性质的收件人和亚马逊仓收件地址的包裹 | G279: 不超过20kg | H279: 长+宽+高≤160cm；最长边≤100cm，宽和高不能同时＞90cm 拒收圆柱体及异形包装 | J279: 济州偏远地区（63000-63644）另收取偏远费每票17元，偏远邮编请咨询客服（详见附录） | K279: 无退回中国服务，暂不提供重派服务，退回默认销毁，销毁免费。 | M279: 每目的港清关批次中每个收件人只允许一个包裹且申报价值不超过150美元
B280: 马来西亚 | C280: MY | D280: 全段时效：11-15天 | E280: 法律禁止的货物、银行票据、票据或货币、普通烟花，危险废物或危险废物服务人类遗骸、胎儿遗骸、人体部位、人类胚胎或其组成部分，1972 年《野生动物保护法》涵盖的野生动物服装和服装配饰物品.1972 年《野生动物保护法》涵盖的其他野生动物毛皮物品。，不带 IMEl 的移动电话导入 （国际移动设备标识），象牙，大麻，包括用于药用的大麻任何/所有麻醉药品或精神药物邮票，鱼翅，酒精饮料非驯养动物产品（例如珍珠母镶嵌、蛇皮表带），弹药 生物物质，B 类和豁免人类或动物标本危险品，枪支和武器（包括惰性和复制品、爆炸性武器），毛皮，假冒商品，二手和重新调整用途的小工具，飞机、热气球、直升机和无人驾驶飞行器 （UAV）。丢弃的花纹/铅废料/类型废料，色情和淫秽材料，性玩具，彩票和赌博设备，精神药物种子，黄金或其他贵金属，大麻和 CBD，活体动物，易腐货物，个人使用的物品，植物和种子需要植物和检疫局的 lmport 许可证，烟草 禁止发手机 所有关于涉及两用物项的货物稀土、稀有金属（包括但不限于各类型金属锭、金属制模具、金属原材料，五金件等高密度货物）、石墨、锂亚硫酰氯电池、等禁止出口的物资将从严查验 | F280: 申报价值低于500马来西亚林吉特（大约为112USD） | G280: 不超过30kg | H280: L+W+H < 125cm | J280: - | K280: 1. 重派费：80元/件 2. 海外仓退件会保留14天，超期则默认销毁； | M280: 申报价值低于500马来西亚林吉特（大约为112USD）免税
B281: 菲律宾 | C281: PH | D281: 全段时效：11-15天 | E281: 1. 菲律宾电话格式：+63 917 xxx xxxx或者9+9位数开头 2. 法律禁止的货物、银行票据、票据或货币、普通烟花，危险废物或危险废物服务人类遗骸、胎儿遗骸、人体部位、人类胚胎或其组成部分，1972 年《野生动物保护法》涵盖的野生动物服装和服装配饰物品.1972 年《野生动物保护法》涵盖的其他野生动物毛皮物品。，不带 IMEl 的移动电话导入 （国际移动设备标识），象牙，大麻，包括用于药用的大麻任何/所有麻醉药品或精神药物邮票，鱼翅，酒精饮料非驯养动物产品（例如珍珠母镶嵌、蛇皮表带），弹药 生物物质，B 类和豁免人类或动物标本危险品，枪支和武器（包括惰性和复制品、爆炸性武器），毛皮，假冒商品，二手和重新调整用途的小工具，飞机、热气球、直升机和无人驾驶飞行器 （UAV）。丢弃的花纹/铅废料/类型废料，色情和淫秽材料，性玩具，彩票和赌博设备，精神药物种子，黄金或其他贵金属，大麻和 CBD，活体动物，易腐货物，个人使用的物品，植物和种子需要植物和检疫局的 lmport 许可证，烟草 3. 禁止发手机 4. 货物品名、申报价值及申报数量需如实申报； 5. 不接受超尺寸发货 | F281: 申报价值低于10000菲律宾比索（大约为175USD） | G281: 不超过30kg | H281: 2W+2H＜150cm | J281: - | K281: 无退回中国服务，可提供重派服务，重派费：60元/件，退件会在库内保存14天，逾期默认销毁，销毁免费。 | M281: 申报价值低于10000菲律宾比索（大约为175USD）免税
B282: 新加坡 | C282: SG | D282: 7-14天 | E282: 电话号码内仅接受纯数字 | F282: 申报价值＜400新加坡元 | G282: 不超过30kg | H282: 尺寸限制： （高+宽）*2≤150cm | J282: - | K282: 无退回中国服务，提供重派服务，重派金额：30元/件，妥投失败会退回国外中转仓，免费保存7天，逾期默认销毁，销毁免费。 | M282: 税号非必填，不收取税费及代缴税处理费，如果客户填写税号（请填写在“寄件人税号”栏）
...

Sheet 顺邮宝挂号
O1: 返 回 目 录
C2: 顺邮宝挂号价目表
C4: (2025/07/07生效)
B6: 国家(地区) | K6: 单价(元/KG) | L6: 处理费(元/件) | M6: 限重(KG)
B7: 英文 | D7: 代码 | E7: 中文
B9: Afghanistan | C9: AF | D9: AF | E9: 阿富汗 | G9: 0 | H9: 2 | K9: 205 | L9: 20 | M9: 2
B10: Albania | C10: AL | D10: AL | E10: 阿尔巴尼亚 | G10: 0 | H10: 2 | K10: 175 | L10: 15 | M10: 2
B11: Algeria | C11: DZ | D11: DZ | E11: 阿尔及利亚 | G11: 0 | H11: 2 | K11: 195 | L11: 14 | M11: 2
B12: American Samoa | C12: AS | D12: AS | E12: 美属萨摩亚 | G12: 0 | H12: 2 | K12: 185 | L12: 20 | M12: 2
B13: Andorra | C13: AD | D13: AD | E13: 安道尔 | G13: 0 | H13: 2 | K13: 305 | L13: 20 | M13: 2
B14: Angola | C14: AO | D14: AO | E14: 安哥拉 | G14: 0 | H14: 2 | K14: 135 | L14: 20 | M14: 2
B15: Anguilla | C15: AI | D15: AI | E15: 安圭拉岛 | G15: 0 | H15: 2 | K15: 485 | L15: 20 | M15: 2
B16: Antigua and Barbuda | C16: AG | D16: AG | E16: 安提瓜和巴布达 | G16: 0 | H16: 2 | K16: 205 | L16: 30 | M16: 2
B17: Argentina | C17: AR | D17: AR | E17: 阿根廷 | G17: 0 | H17: 2 | K17: 255 | L17: 14 | M17: 2
B18: Armenia | C18: AM | D18: AM | E18: 亚美尼亚 | G18: 0 | H18: 2 | K18: 195 | L18: 15 | M18: 2
B19: Aruba | C19: AW | D19: AW | E19: 阿鲁巴 | G19: 0 | H19: 2 | K19: 215 | L19: 37 | M19: 2
B20: Ascension Island | C20: AC | D20: AC | E20: 阿森松岛 | G20: 0 | H20: 2 | K20: 485 | L20: 20 | M20: 2
... B232: Zimbabwe | C232: ZW | D232: ZW | E232: 津巴布韦 | G232: 0 | H232: 2 | K232: 105 | L232: 10 | M232: 2
A235: 地址：深圳市龙华区民治街道光浩国际中心A座19楼 电话：4006075388 网址：www.sypost.com 邮箱：b@sypost.com

Sheet CneForClothes
B1: 路向国 | D1: 包裹处理费 （RMB/票） | E1: 包裹运费 （RMB/KG） | F1: 重量段 （KG） | G1: 重量 min | H1: 重量 max | I1: 参考时效 （工作日） | J1: 旺季参考时效 （工作日） | K1: 包裹运费 （RMB/KG） | L1: 包裹处理费 （RMB/票） | M1: 尺寸限制 （CM） | N1: 备注说明
B2: 美国 | C2: US | D2: 22 | E2: 76 | F2: 0-0.15 | G2: 0 | H2: 0.15 | I2: 7-12 | J2: 10-15 | K2: 105 | L2: 24 | M2: 15＜L≤55，10≤W≤40, H≤25 | N2: 1）起步50g, 2）圆柱体、不规则件，需加收34元/票附加费 3）L≤66且L+2（W+H）≤213cm的超尺寸包裹，需加收34元/票附加费 4）L＞66cm或L+2（W+H）>213cm不可发
B3: 美国 | C3: US | D3: 20 | E3: 76 | F3: 0.151-0.3 | G3: 0 | H3: 0.3 | K3: 98 | L3: 22
B4: 美国 | C4: US | D4: 20 | E4: 76 | F4: 0.301-0.453 | G4: 0.301 | H4: 0.453 | K4: 98 | L4: 18
B5: 美国 | C5: US | D5: 20 | E5: 76 | F5: 0.454-0.7 | G5: 0.454 | H5: 0.7 | K5: 90 | L5: 16
B6: 美国 | C6: US | D6: 16 | E6: 76 | F6: 0.701-1.814 | G6: 0.701 | H6: 1.814 | K6: 86 | L6: 9
B7: 美国 | C7: US | D7: 16 | E7: 79 | F7: 1.815-2 | G7: 1.815 | H7: 2 | K7: 77 | L7: 9
B8: 美国 | C8: US | D8: 12 | E8: 76 | F8: 2.001-10 | G8: 2.001 | H8: 10 | K8: 77 | L8: 9
B9: 英国 | C9: UK/GB | D9: 16 | E9: 50 | F9: 0-0.3 | G9: 0 | H9: 0.3 | I9: 6-9 | J9: 7-10 | K9: 44 | L9: 16 | M9: 15≤L≤60,10≤W≤40，H≤40 | N9: (1)2区禁用,若单独申请开通发货需加收17元/票;​ 2区邮编:苏格兰高地和群岛-邮政编码IV、HS、KA27-28、KW、PA20-49、PA60-78、PH17-26、PH30-44、 PH49-50、马恩岛、根西岛辖区和泽西岛、ZE、GY、JE、IM (2)3区禁用,若单独申请开通发货需加收9元/票​ 3区邮编:北爱尔兰和锡利群岛-邮政编码BT，TR21-25​ 若有需求开通偏远邮编发货,请联系销售经理
B10: 英国 | C10: UK/GB | D10: 16 | E10: 53 | F10: 0.301-1 | G10: 0.301 | H10: 1 | K10: 44 | L10: 16
B11: 英国 | C11: UK/GB | D11: 16 | E11: 53 | F11: 1.001-20 | G11: 1.001 | H11: 20 | K11: 44 | L11: 16
B12: 德国 | C12: DE | D12: 19 | E12: 59 | F12: 0-0.1 | G12: 0 | H12: 0.1 | I12: 6-9 | J12: 7-15 | K12: 52 | L12: 19 | M12: 15≤L≤100,10≤W≤60 | N12: 异形包裹需加收25元/票附加费
B13: 德国 | C13: DE | D13: 19 | E13: 59 | F13: 0.1-0.3 | G13: 0.1 | H13: 0.3 | K13: 52 | L13: 19
B14: 德国 | C14: DE | D14: 22 | E14: 59 | F14: 0.301-30 | G14: 0.301 | H14: 30 | K14: 52 | L14: 21
B15: 意大利 | C15: IT | D15: 24 | E15: 64 | F15: 0-0.3 | G15: 0 | H15: 0.3 | I15: 6-9 | J15: 7-15 | K15: 59 | L15: 24 | M15: 15≤L≤60,10≤W≤50 L+H+W≤130
B16: 意大利 | C16: IT | D16: 23 | E16: 62 | F16: 0.3-5 | G16: 0.3 | H16: 5 | K16: 55 | L16: 23
B17: 西班牙 | C17: ES | D17: 18 | E17: 56 | F17: 0-1 | G17: 0 | H17: 1 | I17: 7-10 | J17: 7-15 | K17: 55 | L17: 18 | M17: 15≤L≤60,10≤W≤50，L+H+W≤150
B18: 西班牙 | C18: ES | D18: 18 | E18: 56 | F18: 1.001-30 | G18: 1.001 | H18: 30 | K18: 50 | L18: 18
B19: 法国 | C19: FR | F19: 0-0.2KG | G19: 0 | H19: 0.2 | I19: 6-9 | J19: 7-12 | K19: 61 | L19: 19 | M19: 15<L≤60,L+W+H≤90 | N19: 禁发圆柱体，异形件加收48元/票
B20: 法国 | C20: FR | F20: 0.201-0.4KG | G20: 0.201 | H20: 0.4 | K20: 61 | L20: 19
B21: 法国 | C21: FR | F21: 0.401-2KG | G21: 0.401 | H21: 2 | K21: 62 | L21: 21
B22: 重要提示： 随着步入旺季，为了尽量保证货物正常转运，请您避免出现以下几种因货物无法上分拣设备需人工操作导致转运延迟的情况： 1.超大规格或小于10x15CM尺寸的货物； 2.不规则货物（例如：球形、三角形、圆柱形等）； 3.面单不合规或模糊褶皱； 4.账户欠费。 5.所有国家不接受亚马逊仓库地址及其他海外仓库地址。
B23: 注意事项：
B24: 一、计泡说明
B25: 1、计泡标准：符合渠道货物类型的按实重计费
B26: 二、在线追踪
B27: 1、专线类挂号小包类可追踪；平邮小包类不可追踪；
B28: 2、查询网址如下：http://www.cne.com；http://www.17track.net
B29: 三、关税相关
B30: 1、清关模式：DDP模式，CNE预收VAT，不提供税单。
B31: 2、美国：不接受申报价值超过USD800的产品，且不接受同一个收件人名且同一地址，当天累计包裹申报价值超过USD800
B32: 3、英国：自2021年1月1日起，所有发往英国的货物取消15GBP以下免征VAT的豁免政策，至此之后申报价值≤135 英镑的 B2C 进口货物需交纳VAT，申报价值＞135 英镑的进口货物需交纳VAT和关税（Duty）。
B33: 4、欧盟国家：下单时若未提供IOSS：（1）与CNE签署代缴协议，由CNE进行VAT的预收和代缴，VAT计费规则是每日发给同一收件人包裹的合计申报价值≤150EUR 时，按照订单申报价值的20%收取；（2）下单时已提供IOSS，申报价值≤150EUR 时，CNE将不再征收VAT；（3）包裹申报价值＞EUR150 时，有无IOSS都要征收VAT，另还会产生关税，产生关税以及产生的关税额度视所寄物品与当地海关的政策法规而定，CNE将会在海关账单下来的当月补扣该费用。
... B56: 特别提示：如贵司同意接受我司服务，即视为贵司已详细阅读过以上内容，并接受各条款的约束。

Sheet CneForGeneral
B1: 路向国 | D1: 包裹处理费 （RMB/票） | E1: 包裹运费 （RMB/KG） | F1: 重量段 （KG） | G1: 重量 min | H1: 重量 max | I1: 参考时效 （工作日） | J1: 旺季参考时效 （工作日） | K1: 包裹运费 （RMB/KG） | L1: 包裹处理费 （RMB/票） | M1: 尺寸限制 （CM） | N1: 备注说明
B2: 美国 | C2: US | D2: 25 | E2: 113 | F2: 0-0.15 | G2: 0 | H2: 0.15 | I2: 7-12 | J2: 10-15 | K2: 113 | L2: 25 | M2: 15＜L≤55，10≤W≤40, H≤25 | N2: 1）起步50g 2）圆柱体、不规则件，需加收34元/票附加费 3）L≤66且L+2（W+H）≤213cm的超尺寸包裹，需加收34元/票附加费 4）L＞66cm或L+2（W+H）>213cm不可发
B3: 美国 | C3: US | D3: 22 | E3: 107 | F3: 0.151-0.3 | G3: 0.151 | H3: 0.3 | K3: 107 | L3: 22
B4: 美国 | C4: US | D4: 20 | E4: 102 | F4: 0.301-0.453 | G4: 0.301 | H4: 0.453 | K4: 102 | L4: 20
B5: 美国 | C5: US | D5: 18 | E5: 96 | F5: 0.454-0.7 | G5: 0.454 | H5: 0.7 | K5: 96 | L5: 18
B6: 美国 | C6: US | D6: 12 | E6: 91 | F6: 0.701-1.814 | G6: 0.701 | H6: 1.814 | K6: 91 | L6: 12
B7: 美国 | C7: US | D7: 12 | E7: 81 | F7: 1.815-2 | G7: 1.815 | H7: 2 | K7: 81 | L7: 12
B8: 美国 | C8: US | D8: 12 | E8: 81 | F8: 2.001-10 | G8: 2.001 | H8: 10 | K8: 81 | L8: 12
B9: 英国 | C9: UK/GB | D9: 16 | E9: 54 | F9: 0-0.3 | G9: 0 | H9: 0.3 | I9: 6-9 | J9: 7-10 | K9: 47 | L9: 16 | M9: 15≤L≤60,10≤W≤40，H≤40 | N9: (1)2区禁用,若单独申请开通发货需加收17元/票;​ 2区邮编:苏格兰高地和群岛-邮政编码IV、HS、KA27-28、KW、PA20-49、PA60-78、PH17-26、PH30-44、 PH49-50、马恩岛、根西岛辖区和泽西岛、ZE、GY、JE、IM (2)3区禁用,若单独申请开通发货需加收9元/票​ 3区邮编:北爱尔兰和锡利群岛-邮政编码BT，TR21-25​ 若有需求开通偏远邮编发货,请联系销售经理
B10: 英国 | C10: UK/GB | D10: 16 | E10: 54 | F10: 0.301-1 | G10: 0.301 | H10: 1 | K10: 47 | L10: 16
B11: 英国 | C11: UK/GB | D11: 16 | E11: 54 | F11: 1.001-30 | G11: 1.001 | H11: 30 | K11: 47 | L11: 16
B12: 法国 | C12: FR | D12: 19 | E12: 73 | F12: 0-0.2 | G12: 0 | H12: 0.2 | I12: 6-9 | J12: 7-12 | K12: 63 | L12: 19 | M12: 15≤L≤80,10≤W≤60 L+W+H≤150 | N12: 禁发圆柱体，异形件加收48元/票
B13: 法国 | C13: FR | D13: 19 | E13: 73 | F13: 0.201-0.4 | G13: 0.201 | H13: 0.4 | K13: 63 | L13: 19
B14: 法国 | C14: FR | D14: 23 | E14: 65 | F14: 0.401-5 | G14: 0.401 | H14: 5 | K14: 64 | L14: 21
B15: 德国 | C15: DE | D15: 19 | E15: 62 | F15: 0-0.3 | G15: 0 | H15: 0.3 | I15: 6-9 | J15: 7-15 | K15: 55 | L15: 19 | M15: 15≤L≤100,10≤W≤60 | N15: 异形包裹需加收25元/票附加费
B16: 德国 | C16: DE | D16: 22 | E16: 62 | F16: 0.3-30 | G16: 0.3 | H16: 30 | K16: 55 | L16: 21
B17: 意大利 | C17: IT | D17: 24 | E17: 72 | F17: 0-0.3 | G17: 0 | H17: 0.3 | I17: 6-9 | J17: 7-15 | K17: 63 | L17: 24 | M17: 15≤L≤60,10≤W≤50 L+H+W≤130
B18: 意大利 | C18: IT | D18: 23 | E18: 70 | F18: 0.301-10 | G18: 0.301 | H18: 10 | K18: 61 | L18: 23
B19: 西班牙 | C19: ES | D19: 18 | E19: 62 | F19: 0-1 | G19: 0 | H19: 1 | I19: 7-10 | J19: 7-15 | K19: 57 | L19: 18 | M19: 15≤L≤60,10≤W≤50，L+H+W≤150
B20: 西班牙 | C20: ES | D20: 18 | E20: 62 | F20: 1.001-30 | G20: 1.001 | H20: 30 | K20: 53 | L20: 18
B21: 爱尔兰 | C21: IE | D21: 23 | E21: 80 | F21: 0-0.2 | G21: 0 | H21: 0.2 | I21: 7-10 | J21: 7-15 | K21: 68 | L21: 23 | M21: 15≤L≤100,10≤W≤50,L+2W+2H≤300
B22: 爱尔兰 | C22: IE | D22: 23 | E22: 70 | F22: 0.201-3 | G22: 0.201 | H22: 3 | K22: 58 | L22: 23
B23: 比利时 | C23: BE | D23: 23 | E23: 75 | F23: 0-0.2 | G23: 0 | H23: 0.2 | I23: 6-9 | J23: 7-15 | K23: 70 | L23: 23 | M23: 15≤L≤100,10≤W≤60 L+H+W<150 | N23: 异形包裹需加收50元/票附加费，直径≥40cm或(直径x2+长)≥2m的异形包裹不可发
B24: 比利时 | C24: BE | D24: 21 | E24: 75 | F24: 0.201-1 | G24: 0.201 | H24: 1 | K24: 66 | L24: 21
B25: 比利时 | C25: BE | D25: 21 | E25: 68 | F25: 1.001-20 | G25: 1.001 | H25: 20 | K25: 59 | L25: 21
B26: 波兰 | C26: PL | D26: 15 | E26: 71 | F26: 0-0.5 | G26: 0 | H26: 0.5 | I26: 6-9 | J26: 7-15 | K26: 72 | L26: 15 | M26: 15≤L≤60,10≤W≤50 | N26: 异形包裹需加收52元/票附加费
B27: 波兰 | C27: PL | D27: 15 | E27: 67 | F27: 0.5-10 | G27: 0.5 | H27: 10 | K27: 57 | L27: 15
B28: 立陶宛 | C28: LT | D28: 21 | E28: 44 | F28: 0-0.3 | G28: 0 | H28: 0.3 | I28: 6-9 | J28: 7-16 | K28: 45 | L28: 21 | M28: 15≤L≤80,10≤W≤60，L+2*W+2*H≤300 | N28: 异形包裹需加收180元/票附加费
B29: 立陶宛 | C29: LT | D29: 21 | E29: 46 | F29: 0.301-0.6 | G29: 0.301 | H29: 0.6 | K29: 51 | L29: 21
B30: 立陶宛 | C30: LT | D30: 21 | E30: 55 | F30: 0.601-20 | G30: 0.601 | H30: 20 | K30: 56 | L30: 21
B31: 匈牙利 | C31: HU | D31: 21 | E31: 59 | F31: 0-1 | G31: 0 | H31: 1 | I31: 6-9 | J31: 7-16 | K31: 64 | L31: 21 | M31: 15≤L≤60,10≤W≤50,H≤30 | N31: 1) 圆柱体、不规则件，且尺寸小于50cm*20cm(直径*高)，需加收55元/票附加费 2) L≤105cm且H≤55cm的超尺寸包裹，附加费55元/票 3) L>105cm或H>55cm不可发
B32: 匈牙利 | C32: HU | D32: 21 | E32: 59 | F32: 45301 | G32: 45301 | H32: 45301 | K32: 64 | L32: 21
B33: 捷克 | C33: CZ | D33: 23 | E33: 70 | F33: 0-1 | G33: 0 | H33: 1 | I33: 6-9 | J33: 7-16 | K33: 70 | L33: 23 | M33: 15≤L≤60,10≤W≤50,H≤30 | N33: 1) 圆柱体、不规则件，且尺寸小于50cm*20cm(直径*高)，需加收55元/票附加费 2) L≤105cm且H≤55cm的超尺寸包裹，附加费55元/票 3) L>105cm或H>55cm不可发
B34: 捷克 | C34: CZ | D34: 23 | E34: 60 | F34: 1.001-10 | G34: 1.001 | H34: 10 | K34: 60 | L34: 23
B35: 荷兰 | C35: NL | D35: 24 | E35: 81 | F35: 0-0.2 | G35: 0 | H35: 0.2 | I35: 6-9 | J35: 7-15 | K35: 82 | L35: 23 | M35: 15≤L≤80,10≤W≤60 | N35: 禁发异形件
B36: 荷兰 | C36: NL | D36: 22 | E36: 71 | F36: 0.201-2 | G36: 0.201 | H36: 2 | K36: 66 | L36: 21
B37: 荷兰 | C37: NL | D37: 22 | E37: 61 | F37: 2-30 | G37: 2 | H37: 30 | K37: 53 | L37: 21
B38: 斯洛伐克 | C38: SK | D38: 21 | E38: 70 | F38: 0-0.2 | G38: 0 | H38: 0.2 | I38: 6-9 | J38: 7-16 | K38: 80 | L38: 22 | M38: 15≤L≤60,10≤W≤50,H≤30 | N38: 1) 圆柱体、不规则件，且尺寸小于50cm*20cm(直径*高)，需加收55元/票附加费 2) L≤105cm且H≤55cm的超尺寸包裹，附加费55元/票 3) L>105cm或H>55cm不可发
B39: 斯洛伐克 | C39: SK | D39: 21 | E39: 70 | F39: 0.2-1 | G39: 0.2 | H39: 1 | K39: 72 | L39: 21
B40: 斯洛伐克 | C40: SK | D40: 21 | E40: 62 | F40: 45321 | G40: 45321 | H40: 45321 | K40: 65 | L40: 21
B41: 丹麦 | C41: DK | D41: 26 | E41: 75 | F41: 0-0.3 | G41: 0 | H41: 0.3 | I41: 6-9 | J41: 7-15 | K41: 79 | L41: 26 | M41: L＜60,L+2W+2H＜120
B42: 丹麦 | C42: DK | D42: 23 | E42: 72 | F42: 0.301-20 | G42: 0.301 | H42: 20 | K42: 69 | L42: 23
B43: 瑞士 | C43: CH | D43: 22 | E43: 108 | F43: 0-0.1 | G43: 0 | H43: 0.1 | I43: 6-10 | J43: 8-12 | K43: 100 | L43: 22 | M43: 15≤L＜60,L+W+H＜90 | N43: 50G起步；禁发异形件
B44: 瑞士 | C44: CH | D44: 21 | E44: 102 | F44: 0.101-0.6 | G44: 0.101 | H44: 0.6 | K44: 97 | L44: 21
B45: 瑞士 | C45: CH | D45: 18 | E45: 95 | F45: 0.6-10 | G45: 0.6 | H45: 10 | K45: 87 | L45: 18
B46: 瑞典 | C46: SE/SW | D46: 16 | E46: 75 | F46: 0-5 | G46: 0 | H46: 5 | I46: 7-9 | J46: 9-15 | K46: 68 | L46: 16 | M46: L＜60,L+W+H＜120 | N46: 异形包裹需加收180元/票附加费
B47: 路向国 | D47: 包裹首重 （RMB/500G） | E47: 包裹续重 （RMB/500G） | F47: 重量段 （KG） | I47: 参考时效 （工作日） | J47: 旺季参考时效 （工作日） | K47: 包裹续重 （RMB/500G） | L47: 包裹首重 （RMB/500G） | M47: 尺寸限制 （CM） | N47: 备注说明
B48: 日本 | C48: JP | D48: 32 | E48: 7 | F48: 0-10KG | G48: 0 | H48: 10 | I48: 2-4 | J48: 2-7 | K48: 7 | L48: 38 | M48: L+W+H≤160 | N48: ①不接受亚马逊地址 ②日本禁发医疗用品 ③冲绳偏远禁运，如需开通下单请联系业务或客服 ④禁发植物类、土壤类及果实、种子类等产品
B49: 重要提示： 随着步入旺季，为了尽量保证货物正常转运，请您避免出现以下几种因货物无法上分拣设备需人工操作导致转运延迟的情况： 1.超大规格或小于10x15CM尺寸的货物； 2.不规则货物（例如：球形、三角形、圆柱形等）； 3.面单不合规或模糊褶皱； 4.账户欠费。 5.所有国家不接受亚马逊仓库地址及其他海外仓库地址。
B50: 注意事项：
B51: 一、计泡说明
B52: 1、计泡标准：货物单边>5CM且L+W+H＞50CM需计泡（除日本），日本是L+W+H＞60CM需计泡。
B53: 2、计泡系数（除日本）
B54: ①.单边>5CM且50CM<L+W+H≤70CM,记泡系数10000
B55: ②.单边>5CM且70CM<L+W+H≤90CM,记泡系数8000
B56: ③.L+W+H>90CM,记泡系数6000
B57: 3、日本计泡系数
B58: L+W+H>60CM,记泡系数6000
B59: 注：三边之和小于50CM单件泡比过高或者批量单一品类泡货请提前沟通，否则我司有计泡的权利。
B60: 二、在线追踪
... B87: 3、退件重派有费用，重派原国家收取原运费，详情请咨询客服人员。

Sheet 4PXForCosmetic
O1: 报价币种：人民币 价格生效日期：2024年10月14日 | P1: 返回目录
A2: 大洲/地区 | B2: 国家/地区 | D2: 产品代码 | E2: 报价区域 | F2: 重量段 （KG） | K2: 收费标准 | M2: 标准尺寸 | N2: 可服务超尺寸及附加费 | O2: 时效 （工作日） | P2: 备注
G3: 重量 min | H3: 重量 max | K3: 运费 RMB/KG | L3: 挂号费 RMB/票
A4: 北美洲 | B4: 美国 | C4: US | D4: S5060 | E4: 华南/华东 | F4: 0-0.1 | G4: 0 | H4: 0.1 | K4: 149 | L4: 49 | M4: 最小尺寸：10*15CM 最大尺寸：三边之和≤90cm，单边≤60cm | N4: / | O4: 15-17 | P4: 可服务邮编，见“分区&无服务邮编表”
B5: 美国 | C5: US | F5: 0.101-0.2 | G5: 0.101 | H5: 0.2 | K5: 161 | L5: 49
B6: 美国 | C6: US | F6: 0.201-0.45 | G6: 0.201 | H6: 0.45 | K6: 165 | L6: 48
B7: 美国 | C7: US | F7: 0.451-0.7 | G7: 0.451 | H7: 0.7 | K7: 165 | L7: 48
B8: 美国 | C8: US | F8: 0.701-1 | G8: 0.701 | H8: 1 | K8: 165 | L8: 39
B9: 美国 | C9: US | F9: 1.001-2 | G9: 1.001 | H9: 2 | K9: 160 | L9: 39
B10: 加拿大 | C10: CA | D10: S5060 | E10: 华南/华东 | F10: 0-0.3 | G10: 0 | H10: 0.3 | K10: 162 | L10: 24 | M10: 最小尺寸：10*15cm 最大尺寸：60cm*40cm*35cm | N10: / | O10: 10-15 | P10: /
B11: 加拿大 | C11: CA | F11: 0.301-0.5 | G11: 0.301 | H11: 0.5 | K11: 162 | L11: 24
B12: 加拿大 | C12: CA | F12: 0.501-2 | G12: 0.501 | H12: 2 | K12: 162 | L12: 24
B13: 加拿大 | C13: CA | F13: 2.001-5 | G13: 2.001 | H13: 5 | K13: 162 | L13: 24
B14: 墨西哥 | C14: MX | D14: S5060 | E14: 华南/华东 | F14: 0-0.5 | G14: 0 | H14: 0.5 | K14: 115 | L14: 21 | M14: 最小尺寸：10*15cm 最大尺寸：40cm*50cm*60cm | N14: / | O14: 10-20 | P14: 可服务邮编，见“分区&无服务邮编表”
B15: 墨西哥 | C15: MX | F15: 0.501-1 | G15: 0.501 | H15: 1 | K15: 115 | L15: 21
B16: 墨西哥 | C16: MX | F16: 1.001-5 | G16: 1.001 | H16: 5 | K16: 115 | L16: 23
A17: 南美洲 | B17: 巴西 | C17: BR | D17: S5060 | E17: 华南/华东 | F17: 0-0.2 | G17: 0 | H17: 0.2 | K17: 90 | L17: 37 | M17: 最小尺寸：10*15cm 最大尺寸：单边长度≤100cm 长+宽+高≤200cm | N17: / | O17: 15-25 受PRC政策影响 预计延误7-10天 | P17: /
B18: 巴西 | C18: BR | F18: 0.201-0.5 | G18: 0.201 | H18: 0.5 | K18: 90 | L18: 37
B19: 巴西 | C19: BR | F19: 0.501-1 | G19: 0.501 | H19: 1 | K19: 90 | L19: 41
B20: 巴西 | C20: BR | F20: 1.01-1.5 | G20: 1.01 | H20: 1.5 | K20: 90 | L20: 49
B21: 巴西 | C21: BR | F21: 1.501-2 | G21: 1.501 | H21: 2 | K21: 90 | L21: 53
B22: 巴西 | C22: BR | F22: 2.01-30 | G22: 2.01 | H22: 30 | K22: 90 | L22: 64
A23: 欧洲 | B23: 法国 | C23: FR | D23: S5060 | E23: 华南/华东 | F23: 0-2 | G23: 0 | H23: 2 | K23: 119 | L23: 23 | M23: 最小尺寸：10CM*15CM 单边尺寸：≤60CM 三边尺寸：长+宽+高≤90CM | N23: / | O23: 10-15 | P23: 无服务邮编：邮编前两位97、98
B24: 德国 | C24: DE | F24: 0-2 | G24: 0 | H24: 2 | K24: 120 | L24: 22 | P24: 无服务邮编：27498、78266
B25: 意大利 | C25: IT | F25: 0-2 | G25: 0 | H25: 2 | K25: 116 | L25: 25 | P25: 无服务邮编：120、47890 – 47899、22061、23030
B26: 西班牙 | C26: ES | F26: 0-2 | G26: 0 | H26: 2 | K26: 135 | L26: 18 | P26: 无服务邮编：51、52、35、38开头、44500、GX11_1AA
B27: 荷兰 | C27: NL | F27: 0-2 | G27: 0 | H27: 2 | K27: 111 | L27: 24
B28: 比利时 | C28: BE | F28: 0-2 | G28: 0 | H28: 2 | K28: 149 | L28: 22
B29: 卢森堡 | C29: LU | F29: 0-2 | G29: 0 | H29: 2 | K29: 133 | L29: 26
B30: 葡萄牙 | C30: PT | F30: 0-2 | G30: 0 | H30: 2 | K30: 139 | L30: 20
B31: 丹麦 | C31: DK | F31: 0-2 | G31: 0 | H31: 2 | K31: 117 | L31: 24 | P31: 无服务邮编：FO 100:999、3900:3999
B32: 克罗地亚 | C32: CRO | F32: 0-2 | G32: 0 | H32: 2 | K32: 115 | L32: 26
B33: 匈牙利 | C33: HU | F33: 0-2 | G33: 0 | H33: 2 | K33: 108 | L33: 21
B34: 塞浦路斯 | C34: CY | F34: 0-2 | G34: 0 | H34: 2 | K34: 115 | L34: 24
B35: 奥地利 | C35: AT | F35: 0-2 | G35: 0 | H35: 2 | K35: 115 | L35: 23
B36: 希腊 | C36: GR | F36: 0-2 | G36: 0 | H36: 2 | K36: 127 | L36: 23 | P36: 无服务邮编：630_86
B37: 拉脱维亚 | C37: LV | F37: 0-2 | G37: 0 | H37: 2 | K37: 108 | L37: 25
B38: 捷克 | C38: CZ | F38: 0-2 | G38: 0 | H38: 2 | K38: 111 | L38: 21
B39: 斯洛伐克 | C39: SK | F39: 0-2 | G39: 0 | H39: 2 | K39: 109 | L39: 21
B40: 斯洛文尼亚 | C40: SI | F40: 0-2 | G40: 0 | H40: 2 | K40: 122 | L40: 26
B41: 波兰 | C41: PL | F41: 0-2 | G41: 0 | H41: 2 | K41: 133 | L41: 15
B42: 爱尔兰 | C42: IE | F42: 0-2 | G42: 0 | H42: 2 | K42: 117 | L42: 23
B43: 瑞典 | C43: SE/SW | F43: 0-2 | G43: 0 | H43: 2 | K43: 102 | L43: 23
B44: 立陶宛 | C44: LT | F44: 0-2 | G44: 0 | H44: 2 | K44: 106 | L44: 22
B45: 罗马尼亚 | C45: RO | F45: 0-2 | G45: 0 | H45: 2 | K45: 126 | L45: 20
B46: 芬兰 | C46: FI | F46: 0-2 | G46: 0 | H46: 2 | K46: 99 | L46: 36 | P46: 无服务邮编：22000:22999
B47: 马耳他 | C47: MAL | F47: 0-2 | G47: 0 | H47: 2 | K47: 170 | L47: 30
B48: 保加利亚 | C48: BG | F48: 0-2 | G48: 0 | H48: 2 | K48: 100 | L48: 18
B49: 爱沙尼亚 | C49: EE | F49: 0-2 | G49: 0 | H49: 2 | K49: 106 | L49: 25

Sheet 4PXForElectric
O1: 报价币种：人民币 价格生效日期：2024年10月19日 | P1: 返回目录
A2: 大洲 | B2: 国家/地区 | D2: 产品代码 | E2: 报价区域 | F2: 重量段 （KG） | K2: 收费标准 | M2: 标准尺寸 | N2: 可服务超尺寸及附加费 | O2: 时效 （工作日） | P2: 备注
G3: 重量 min | H3: 重量 max | K3: 运费 RMB/KG | L3: 挂号费 RMB/票
A4: 北美洲 | B4: 美国 | C4: =VLOOKUP(B4,'[13]Detailed Calculation table'!$A$4:$B$79,2,0) -> US | D4: JW | E4: 华南/华东 | F4: 0-0.1 | G4: 0 | H4: 0.1 | K4: 138 | L4: 20 | M4: 最小尺寸：10*15CM 最大尺寸：60*40*35CM | N4: / | O4: 9-14 | P4: 无服务邮编： ①邮编前3位006-009,967-969,995-999（006-009：波多黎各、维尔京群岛；967-969：夏威夷、关岛；995-999：阿拉斯加）；②不接受APO/FPO军事地址和亚马逊仓库地址；
B5: 美国 | C5: =VLOOKUP(B5,'[13]Detailed Calculation table'!$A$4:$B$79,2,0) -> US | F5: 0.101-0.2 | G5: 0.101 | H5: 0.2 | K5: 133 | L5: 18
B6: 美国 | C6: =VLOOKUP(B6,'[13]Detailed Calculation table'!$A$4:$B$79,2,0) -> US | F6: 0.201-0.45 | G6: 0.201 | H6: 0.45 | K6: 127 | L6: 16
B7: 美国 | C7: =VLOOKUP(B7,'[13]Detailed Calculation table'!$A$4:$B$79,2,0) -> US | F7: 0.451-0.7 | G7: 0.451 | H7: 0.7 | K7: 125 | L7: 16
B8: 美国 | C8: =VLOOKUP(B8,'[13]Detailed Calculation table'!$A$4:$B$79,2,0) -> US | F8: 0.701-1 | G8: 0.701 | H8: 1 | K8: 125 | L8: 9
B9: 美国 | C9: =VLOOKUP(B9,'[13]Detailed Calculation table'!$A$4:$B$79,2,0) -> US | F9: 1.001-3 | G9: 1.001 | H9: 3 | K9: 125 | L9: 9
B10: 美国 | C10: =VLOOKUP(B10,'[13]Detailed Calculation table'!$A$4:$B$79,2,0) -> US | F10: 3.001-6 | G10: 3.001 | H10: 6 | K10: 125 | L10: 9
B11: 美国 | C11: =VLOOKUP(B11,'[13]Detailed Calculation table'!$A$4:$B$79,2,0) -> US | F11: 6.001-30 | G11: 6.001 | H11: 30 | K11: 125 | L11: 9
B12: 加拿大 | C12: =VLOOKUP(B12,'[13]Detailed Calculation table'!$A$4:$B$79,2,0) -> CA | D12: JW | E12: 华南/华东 | F12: 0-0.3 | G12: 0 | H12: 0.3 | K12: 90 | L12: 19 | M12: 单边长度≤100CM 长+宽+高≤200CM | N12: / | O12: 12-17 | P12: /
B13: 加拿大 | C13: =VLOOKUP(B13,'[13]Detailed Calculation table'!$A$4:$B$79,2,0) -> CA | F13: 0.301-0.5 | G13: 0.301 | H13: 0.5 | K13: 90 | L13: 19
B14: 加拿大 | C14: =VLOOKUP(B14,'[13]Detailed Calculation table'!$A$4:$B$79,2,0) -> CA | F14: 0.501-1.5 | G14: 0.501 | H14: 1.5 | K14: 99 | L14: 20
B15: 加拿大 | C15: =VLOOKUP(B15,'[13]Detailed Calculation table'!$A$4:$B$79,2,0) -> CA | F15: 1.501-2 | G15: 1.501 | H15: 2 | K15: 106 | L15: 22
B16: 加拿大 | C16: =VLOOKUP(B16,'[13]Detailed Calculation table'!$A$4:$B$79,2,0) -> CA | F16: 2.001-30 | G16: 2.001 | H16: 30 | K16: 107 | L16: 23
B17: 墨西哥 | C17: =VLOOKUP(B17,'[13]Detailed Calculation table'!$A$4:$B$79,2,0) -> MX | D17: JW | E17: 华南/华东 | F17: 0-0.25 | G17: 0 | H17: 0.25 | K17: 87 | L17: 18 | M17: 最大尺寸：40cm*50m*60cm | N17: / | O17: 12-22 | P17: 【禁运物品清单】
B18: 墨西哥 | C18: =VLOOKUP(B18,'[13]Detailed Calculation table'!$A$4:$B$79,2,0) -> MX | F18: 0.251-0.5 | G18: 0.251 | H18: 0.5 | K18: 87 | L18: 18
B19: 墨西哥 | C19: =VLOOKUP(B19,'[13]Detailed Calculation table'!$A$4:$B$79,2,0) -> MX | F19: 0.501-1 | G19: 0.501 | H19: 1 | K19: 87 | L19: 18
B20: 墨西哥 | C20: =VLOOKUP(B20,'[13]Detailed Calculation table'!$A$4:$B$79,2,0) -> MX | F20: 1.001-1.5 | G20: 1.001 | H20: 1.5 | K20: 94 | L20: 20
B21: 墨西哥 | C21: =VLOOKUP(B21,'[13]Detailed Calculation table'!$A$4:$B$79,2,0) -> MX | F21: 1.501-2 | G21: 1.501 | H21: 2 | K21: 94 | L21: 20
B22: 墨西哥 | C22: =VLOOKUP(B22,'[13]Detailed Calculation table'!$A$4:$B$79,2,0) -> MX | F22: 2.001-10 | G22: 2.001 | H22: 10 | K22: 94 | L22: 20
A23: 欧洲 | B23: 英国 | C23: =VLOOKUP(B23,'[13]Detailed Calculation table'!$A$4:$B$79,2,0) -> UK/GB | D23: JW | E23: 华南/华东 | F23: 0-2 | G23: 0 | H23: 2 | K23: 69 | L23: 16 | M23: 0-2KG： 最小尺寸：10CM*21CM 单边尺寸：≤60CM 三边尺寸：60CM*40CM*35CM 最大体积＜0.04m³ 2-15KG 最小尺寸：10CM*21CM 单边尺寸：≤120CM 三边尺寸：长+宽+高≤150CM 最大体积＜0.04m³ | N23: 主要地区收费标准：130RMB/票； 0-2KG：60CM＜单边≤120CM 或 140CM＜长+宽+高≤150CM或 0-15KG 体积长*宽*高≥0.04m³ 偏远地区：不接受超尺服务 2-15KG不接受超尺服务； | O23: 7-9 | P23: 无服务邮编 详见 【分区&无服务邮编表】
B24: 英国 | C24: =VLOOKUP(B24,'[13]Detailed Calculation table'!$A$4:$B$79,2,0) -> UK/GB | F24: 2.001-15 | G24: 2.001 | H24: 15 | K24: 66 | L24: 16
B25: 德国 | C25: =VLOOKUP(B25,'[13]Detailed Calculation table'!$A$4:$B$79,2,0) -> DE | D25: JW | E25: 华南/华东 | F25: 0-0.3 | G25: 0 | H25: 0.3 | K25: 84 | L25: 19 | M25: 最大尺寸限制：120CM*60CM*60CM；最小尺寸限制：10*21CM | N25: / | O25: 10-12 | P25: 不提供P.O.BOX及军事地址派送服务；
B26: 德国 | C26: =VLOOKUP(B26,'[13]Detailed Calculation table'!$A$4:$B$79,2,0) -> DE | F26: 0.301-2 | G26: 0.301 | H26: 2 | K26: 84 | L26: 22
B27: 德国 | C27: =VLOOKUP(B27,'[13]Detailed Calculation table'!$A$4:$B$79,2,0) -> DE | F27: 2.001-3 | G27: 2.001 | H27: 3 | K27: 84 | L27: 22
B28: 德国 | C28: =VLOOKUP(B28,'[13]Detailed Calculation table'!$A$4:$B$79,2,0) -> DE | F28: 3.001-30 | G28: 3.001 | H28: 30 | K28: 89 | L28: 22
B29: 法国 | C29: =VLOOKUP(B29,'[13]Detailed Calculation table'!$A$4:$B$79,2,0) -> FR | D29: JW | E29: 华南/华东 | F29: 0-0.4 | G29: 0 | H29: 0.4 | K29: 98 | L29: 19 | M29: 0-2KG： 最小尺寸：10CM*15CM 单边尺寸：最长边不超60CM 三边尺寸：长+宽+高≤90CM 2-30KG： 最小尺寸：10CM*15CM 单边尺寸：最长边不超80CM 三边尺寸：长+宽+高≤120CM | N29: 收费标准：130RMB/票； 0-2KG：60CM＜单边≤100CM 或 90CM＜长+宽+高≤150CM 2-30KG：80CM<单边≤100CM或120CM<长+宽+高≤150CM | O29: 10-12 | P29: 无服务邮编编码 前两位： 97、98、00，POBOX，军事地址：字符里有armee或者armée 及 字符里有或邮编为00100和00200
B30: 法国 | C30: =VLOOKUP(B30,'[13]Detailed Calculation table'!$A$4:$B$79,2,0) -> FR | F30: 0.401-30 | G30: 0.401 | H30: 30 | K30: 98 | L30: 23
B31: 爱尔兰 | C31: =VLOOKUP(B31,'[13]Detailed Calculation table'!$A$4:$B$79,2,0) -> IE | D31: JW | E31: 华南/华东 | F31: 0-20 | G31: 0 | H31: =RIGHT(F31,2) -> 20 | K31: 91 | L31: 23 | M31: 最大尺寸限制：40CM*50CM*60CM 最小尺寸：10*15CM | N31: / | O31: 10-12
A32: 亚洲 | B32: 日本 | C32: =VLOOKUP(B32,'[13]Detailed Calculation table'!$A$4:$B$79,2,0) -> JP | D32: JW | E32: 华南/华东 | F32: 0-0.3 | G32: 0 | H32: =RIGHT(F32,3) -> 0.3 | K32: 25 | L32: 23 | M32: 最小尺寸：10CM*20CM 单边尺寸：≤100CM 三边尺寸：长+宽+高≤160CM | N32: / | O32: 6-8 | P32: /
B33: 日本 | C33: =VLOOKUP(B33,'[13]Detailed Calculation table'!$A$4:$B$79,2,0) -> JP | F33: 0.301-0.5 | G33: 0.301 | H33: =RIGHT(F33,3) -> 0.5 | K33: 25 | L33: 24
B34: 日本 | C34: =VLOOKUP(B34,'[13]Detailed Calculation table'!$A$4:$B$79,2,0) -> JP | F34: 0.501-1 | G34: 0.501 | H34: =RIGHT(F34,1) -> 1 | K34: 25 | L34: 24
B35: 日本 | C35: =VLOOKUP(B35,'[13]Detailed Calculation table'!$A$4:$B$79,2,0) -> JP | F35: 1.001-2 | G35: 1.001 | H35: =RIGHT(F35,1) -> 2 | K35: 25 | L35: 28
B36: 日本 | C36: =VLOOKUP(B36,'[13]Detailed Calculation table'!$A$4:$B$79,2,0) -> JP | F36: 2.001-20 | G36: 2.001 | H36: =RIGHT(F36,2) -> 20 | K36: 26 | L36: 28
B37: 澳大利亚-3区 | D37: JW | E37: 华南/华东 | F37: 0-0.3 | K37: 97 | L37: 19
B38: 澳大利亚-3区 | F38: 0.3-0.5 | K38: 97 | L38: 19
B39: 澳大利亚-3区 | F39: 0.5-1 | K39: 97 | L39: 19
B40: 澳大利亚-3区 | F40: 1-2 | K40: 97 | L40: 19
A41: 价格使用说明
A42: 一、计费重量
A43: 以G为单位进位；
A44: 取实重和体积重较大值计费（体积重量计算方式为：长*宽*高/8000），测量以我司数据为准；
A45: 美国、加拿大、西班牙：最低50G计费；
A46: 二、尺寸限制补充说明
A47: 英国、法国：不接受圆筒状等不规则产品，若有发货，需额外收取130RMB/票的处理费;
A48: 墨西哥：不接受圆筒状等不规则产品。
A49: 德国：不接受不规则产品（圆形货物；三角形、三棱状包装；货物主体上附带凸出的货物；货物底部不平稳，异性货物；多个包裹捆绑在一起致超尺寸的货物；使用特殊麻袋、桶状、金属、木质、布料包装的货物、薄膜或快递袋的包装 有提手环或收口；用橡皮筋捆扎或只用胶带缠绕的外包装）。若有发货，需额外收取130RMB/票的处理费；
A50: 其他国家不接受圆筒状等不规则产品，若有发货，需额外收取130RMB/票的处理费；
A51: 关于异形件示例，见附表【异形件说明】。
A52: 三、申报及税费
... A117: 2、最好提供销售链接和海关编码（方便快速清关）。

Sheet 4PXForGeneral
O1: 报价币种：人民币 价格生效日期：2024年10月19日 | P1: 返回目录
A2: 大洲 | B2: 国家/地区 | D2: 产品代码 | E2: 报价区域 | F2: 重量段 （KG） | K2: 收费标准 | M2: 标准尺寸 | N2: 可服务超尺寸及附加费 | O2: 时效 （工作日） | P2: 备注
G3: 重量 min | H3: 重量 max | K3: 运费 RMB/KG | L3: 挂号费 RMB/票
A4: 北美洲 | B4: 美国 | C4: US | D4: O5 | E4: 华南/华东 | F4: 0-0.1 | G4: 0 | H4: 0.1 | K4: 132 | L4: 20 | M4: 最小尺寸：10*15CM 最大尺寸：60*40*35CM | N4: / | O4: 9-14 | P4: 无服务邮编： ①邮编前3位006-009,967-969,995-999（006-009：波多黎各、维尔京群岛；967-969：夏威夷、关岛；995-999：阿拉斯加）；②不接受APO/FPO军事地址和亚马逊仓库地址；
B5: 美国 | C5: US | F5: 0.101-0.2 | G5: 0.101 | H5: 0.2 | K5: 127 | L5: 18
B6: 美国 | C6: US | F6: 0.201-0.45 | G6: 0.201 | H6: 0.45 | K6: 121 | L6: 16
B7: 美国 | C7: US | F7: 0.451-0.7 | G7: 0.451 | H7: 0.7 | K7: 119 | L7: 16
B8: 美国 | C8: US | F8: 0.701-1 | G8: 0.701 | H8: 1 | K8: 119 | L8: 9
B9: 美国 | C9: US | F9: 1.001-3 | G9: 1.001 | H9: 3 | K9: 119 | L9: 9
B10: 美国 | C10: US | F10: 3.001-6 | G10: 3.001 | H10: 6 | K10: 119 | L10: 9
B11: 美国 | C11: US | F11: 6.001-30 | G11: 6.001 | H11: 30 | K11: 119 | L11: 9
B12: 加拿大 | C12: CA | D12: O5 | E12: 华南/华东 | F12: 0-0.3 | G12: 0 | H12: 0.3 | K12: 89 | L12: 19 | M12: 单边长度≤100CM 长+宽+高≤200CM | N12: / | O12: 12-17 | P12: /
B13: 加拿大 | C13: CA | F13: 0.301-0.5 | G13: 0.301 | H13: 0.5 | K13: 88 | L13: 19
B14: 加拿大 | C14: CA | F14: 0.501-1.5 | G14: 0.501 | H14: 1.5 | K14: 95 | L14: 20
B15: 加拿大 | C15: CA | F15: 1.501-2 | G15: 1.501 | H15: 2 | K15: 88 | L15: 22
B16: 加拿大 | C16: CA | F16: 2.001-30 | G16: 2.001 | H16: 30 | K16: 89 | L16: 23
B17: 墨西哥 | C17: MX | D17: O5 | E17: 华南/华东 | F17: 0-0.25 | G17: 0 | H17: 0.25 | K17: 75 | L17: 18 | M17: 最大尺寸：40cm*50m*60cm | N17: / | O17: 12-22 | P17: 【禁运物品清单】
B18: 墨西哥 | C18: MX | F18: 0.251-0.5 | G18: 0.251 | H18: 0.5 | K18: 75 | L18: 18
B19: 墨西哥 | C19: MX | F19: 0.501-1 | G19: 0.501 | H19: 1 | K19: 75 | L19: 18
B20: 墨西哥 | C20: MX | F20: 1.001-1.5 | G20: 1.001 | H20: 1.5 | K20: 82 | L20: 20
B21: 墨西哥 | C21: MX | F21: 1.501-2 | G21: 1.501 | H21: 2 | K21: 82 | L21: 20
B22: 墨西哥 | C22: MX | F22: 2.001-10 | G22: 2.001 | H22: 10 | K22: 82 | L22: 20
A23: 欧洲 | B23: 英国 | C23: UK/GB | D23: O5 | E23: 华南/华东 | F23: 0-2 | G23: 0 | H23: 2 | K23: 63 | L23: 16 | M23: 0-2KG： 最小尺寸：10CM*21CM 单边尺寸：≤60CM 三边尺寸：60CM*40CM*35CM 最大体积＜0.04m³ 2-15KG 最小尺寸：10CM*21CM 单边尺寸：≤120CM 三边尺寸：长+宽+高≤150CM 最大体积＜0.04m³ | N23: 主要地区收费标准：130RMB/票； 0-2KG：60CM＜单边≤120CM 或 140CM＜长+宽+高≤150CM或 0-15KG 体积长*宽*高≥0.04m³ 偏远地区：不接受超尺服务 2-15KG不接受超尺服务； | O23: 8-10 | P23: 无服务邮编 详见 【分区&无服务邮编表】
B24: 英国 | C24: UK/GB | F24: 2.001-15 | G24: 2.001 | H24: 15 | K24: 63 | L24: 16
B25: 德国 | C25: DE | D25: O5 | E25: 华南/华东 | F25: 0-0.3 | G25: 0 | H25: 0.3 | K25: 63 | L25: 19 | M25: 最大尺寸限制：60CM*40CM*40CM；最小尺寸限制：10*21CM | N25: / | O25: 10-12 | P25: 不提供P.O.BOX及军事地址派送服务；
B26: 德国 | C26: DE | F26: 0.301-2 | G26: 0.301 | H26: 2 | K26: 58 | L26: 22
B27: 德国 | C27: DE | F27: 2.001-3 | G27: 2.001 | H27: 3 | K27: 58 | L27: 22
B28: 德国 | C28: DE | F28: 3.001-30 | G28: 3.001 | H28: 30 | K28: 63 | L28: 22
B29: 法国 | C29: FR | D29: O5 | E29: 华南/华东 | F29: 0-0.2 | G29: 0 | H29: 0.2 | K29: 76 | L29: 18 | M29: 0-2KG： 最小尺寸：10CM*15CM 单边尺寸：最长边不超60CM 三边尺寸：长+宽+高≤90CM 2-30KG： 最小尺寸：10CM*15CM 单边尺寸：最长边不超80CM 三边尺寸：长+宽+高≤120CM | N29: 收费标准：130RMB/票； 0-2KG：60CM＜单边≤100CM 或 90CM＜长+宽+高≤150CM 2-30KG：80CM<单边≤100CM或120CM<长+宽+高≤150CM | O29: 10-12 | P29: 无服务邮编编码 前两位： 97、98、00，POBOX，军事地址：字符里有armee或者armée 及 字符里有或邮编为00100和00200
B30: 法国 | C30: FR | F30: 0.201-0.5 | G30: 0.201 | H30: 0.5 | K30: 74 | L30: 19
C31: FR | F31: 0.501-30 | G31: 0.501 | H31: 30 | K31: 72 | L31: 23
B32: 爱尔兰 | C32: IE | D32: O5 | E32: 华南/华东 | F32: 0-20 | G32: 0 | H32: 20 | K32: 82 | L32: 23 | M32: 最大尺寸限制：40CM*50CM*60CM 最小尺寸：10*15CM | N32: / | O32: 10-12
A33: 亚洲 | B33: 日本 | C33: JP | D33: O5 | E33: 华南/华东 | F33: 0-0.3 | G33: 0 | H33: 0.3 | K33: 20 | L33: 23 | M33: 最小尺寸：10CM*20CM 单边尺寸：≤100CM 三边尺寸：长+宽+高≤160CM | N33: / | O33: 6-8 | P33: /
B34: 日本 | C34: JP | F34: 0.301-0.5 | G34: 0.301 | H34: 0.5 | K34: 20 | L34: 24
B35: 日本 | C35: JP | F35: 0.501-1 | G35: 0.501 | H35: 1 | K35: 20 | L35: 24
B36: 日本 | C36: JP | F36: 1.001-2 | G36: 1.001 | H36: 2 | K36: 20 | L36: 28
B37: 日本 | C37: JP | F37: 2.001-20 | G37: 2.001 | H37: 20 | K37: 23 | L37: 28
B38: 澳大利亚 | C38: AU | D38: O5 | E38: 华南/华东 | F38: 0-0.3 | G38: 0 | H38: 0.3 | K38: 89 | L38: 19
B39: 澳大利亚 | C39: AU | F39: 0.3-0.5 | G39: 0.3 | H39: 0.5 | K39: 89 | L39: 19
B40: 澳大利亚 | C40: AU | F40: 0.5-1 | G40: 0.5 | H40: 1 | K40: 89 | L40: 19
B41: 澳大利亚 | C41: AU | F41: 1-2 | G41: 1 | H41: 2 | K41: 89 | L41: 19

Sheet 4PXForClothes
O1: 报价币种：人民币 价格生效日期：2024年10月19日 | P1: 返回目录
A2: 大洲 | B2: 国家/地区 | D2: 产品代码 | E2: 报价区域 | F2: 重量段 （KG） | K2: 收费标准 | M2: 标准尺寸 | N2: 可服务超尺寸及附加费 | O2: 时效 （工作日） | P2: 备注
G3: 重量 min | H3: 重量 max | K3: 运费 RMB/KG | L3: 挂号费 RMB/票
A4: 北美洲 | B4: 美国 | C4: US | D4: S1427 | E4: 华南/华东 | F4: 0-0.1 | G4: 0 | H4: 0.1 | K4: 128 | L4: 20 | M4: 最小尺寸：10*15CM 最大尺寸：60*40*35CM | N4: 无超尺服务 | O4: 7-12 | P4: 无服务邮编： ①邮编前3位006-009,967-969,995-999（006-009：波多黎各、维尔京群岛；967-969：夏威夷、关岛；995-999：阿拉斯加）；②不接受APO/FPO军事地址和亚马逊仓库地址
B5: 美国 | C5: US | F5: 0.101-0.2 | G5: 0.101 | H5: 0.2 | K5: 123 | L5: 18
B6: 美国 | C6: US | F6: 0.201-0.45 | G6: 0.201 | H6: 0.45 | K6: 117 | L6: 16
B7: 美国 | C7: US | F7: 0.451-0.7 | G7: 0.451 | H7: 0.7 | K7: 115 | L7: 16
B8: 美国 | C8: US | F8: 0.701-1 | G8: 0.701 | H8: 1 | K8: 115 | L8: 9
B9: 美国 | C9: US | F9: 1.001-3 | G9: 1.001 | H9: 3 | K9: 115 | L9: 9
B10: 美国 | C10: US | F10: 3.001-6 | G10: 3.001 | H10: 6 | K10: 115 | L10: 9
B11: 美国 | C11: US | F11: 6.001-30 | G11: 6.001 | H11: 30 | K11: 115 | L11: 9
B12: 加拿大 | C12: CA | D12: S1427 | E12: 华南/华东 | F12: 0-0.3 | G12: 0 | H12: 0.3 | K12: 85 | L12: 19 | M12: 单边长度≤100CM 长+宽+高≤200CM | N12: / | O12: 10-15 | P12: /
B13: 加拿大 | C13: CA | F13: 0.301-0.5 | G13: 0.301 | H13: 0.5 | K13: 85 | L13: 19
B14: 加拿大 | C14: CA | F14: 0.501-1.5 | G14: 0.501 | H14: 1.5 | K14: 91 | L14: 20
B15: 加拿大 | C15: CA | F15: 1.501-2 | G15: 1.501 | H15: 2 | K15: 91 | L15: 22
B16: 加拿大 | C16: CA | F16: 2.001-30 | G16: 2.001 | H16: 30 | K16: 95 | L16: 23
B17: 墨西哥 | C17: MX | D17: S1427 | E17: 华南/华东 | F17: 0-0.25 | G17: 0 | H17: 0.25 | K17: 78 | L17: 18 | M17: 最大尺寸限制：40cm*50m*60cm | N17: / | O17: 10-20 | P17: 【禁运物品清单】
B18: 墨西哥 | C18: MX | F18: 0.251-0.5 | G18: 0.251 | H18: 0.5 | K18: 78 | L18: 18
B19: 墨西哥 | C19: MX | F19: 0.501-1 | G19: 0.501 | H19: 1 | K19: 78 | L19: 18
B20: 墨西哥 | C20: MX | F20: 1.001-1.5 | G20: 1.001 | H20: 1.5 | K20: 85 | L20: 20
B21: 墨西哥 | C21: MX | F21: 1.501-2 | G21: 1.501 | H21: 2 | K21: 85 | L21: 20
B22: 墨西哥 | C22: MX | F22: 2.001-10 | G22: 2.001 | H22: 10 | K22: 85 | L22: 20
A23: 欧洲 | B23: 英国 | C23: UK/GB | D23: S1427 | E23: 华南/华东 | F23: 0-2 | G23: 0 | H23: 2 | K23: 51 | L23: 16 | M23: 0-2KG： 最小尺寸：10CM*21CM 单边尺寸：≤60CM 三边尺寸：60CM*40CM*35CM 最大体积＜0.04m³ 2-15KG 最小尺寸：10CM*21CM 单边尺寸：≤120CM 三边尺寸：长+宽+高≤150CM 最大体积＜0.04m³ | N23: 主要地区收费标准：130RMB/票； 0-2KG：60CM＜单边≤120CM 或 140CM＜长+宽+高≤150CM或 0-15KG 体积长*宽*高≥0.04m³ 偏远地区：不接受超尺服务 2-15KG不接受超尺服务； | O23: 8-10 | P23: 无服务邮编 详见 【分区&无服务邮编表】
B24: 英国 | C24: UK/GB | F24: 2.001-15 | G24: 2.001 | H24: 15 | K24: 54 | L24: 16
B25: 德国 | C25: DE | D25: S1427 | E25: 华南/华东 | F25: 0-0.4 | G25: 0 | H25: 0.4 | K25: 61 | L25: 19 | M25: 最大尺寸限制：60CM*40CM*35CM； 最小尺寸限制：10*15CM | N25: / | O25: 10-12 | P25: 不提供P.O.BOX及军事地址派送服务；
B26: 德国 | C26: DE | F26: 0.401-2 | G26: 0.401 | H26: 2 | K26: 56 | L26: 22
B27: 德国 | C27: DE | F27: 2.001-3 | G27: 2.001 | H27: 3 | K27: 56 | L27: 22
B28: 德国 | C28: DE | F28: 3.001-30 | G28: 3.001 | H28: 30 | K28: 61 | L28: 22
B29: 法国 | C29: FR | D29: S1427 | E29: 华南/华东 | F29: 0-0.4 | G29: 0 | H29: 0.4 | K29: 71 | L29: 19 | M29: 最小尺寸：10CM*15CM 单边尺寸：最长边不超60CM 三边尺寸：长+宽+高≤90CM | N29: 收费标准：130RMB/票； 60CM＜单边≤100CM 或 90CM＜长+宽+高≤150CM | O29: 10-12 | P29: 无服务邮编编码 前两位： 97、98、00，POBOX，军事地址：字符里有armee或者armée 及 字符里有或邮编为00100和00200
B30: 法国 | C30: FR | F30: 0.401-30 | G30: 0.401 | H30: 30 | K30: 71 | L30: 23
B31: 意大利 | C31: IT | D31: S1427 | E31: 华南/华东 | F31: 0-2 | G31: 0 | H31: 2 | K31: 68 | L31: 25 | M31: 最小尺寸：10CM*15CM 单边尺寸：≤60CM 三边尺寸：长+宽+高≤120CM | N31: 收费标准：130RMB/票； 60CM＜单边≤120CM 或 120CM＜长+宽+高≤240CM | O31: 10-12 | P31: /
B32: 意大利 | C32: IT | F32: 2.001-20 | G32: 2.001 | H32: 20 | K32: 68 | L32: 25
B33: 西班牙 | C33: ES | D33: S1427 | E33: 华南/华东 | F33: 0-2 | G33: 0 | H33: 2 | K33: 65 | L33: 18 | M33: 最小尺寸：14cm*9cm 单边尺寸：≤60CM 三边尺寸：长+宽+高≤90CM | N33: / | O33: 8-10 | P33: 无服务邮编编码前两位: 07， 35， 38， 51-99
B34: 西班牙 | C34: ES | F34: 2.001-30 | G34: 2.001 | H34: 30 | K34: 65 | L34: 18
B35: 瑞典 | C35: SE/SW | D35: S1427 | E35: 华南/华东 | F35: 0-0.3 | G35: 0 | H35: 0.3 | K35: 69 | L35: 16 | M35: 最大尺寸限制：40CM*50CM*60CM 最小尺寸：10*15CM | N35: / | O35: 8-10 | P35: /
B36: 瑞典 | C36: SE/SW | F36: 0.301-20 | G36: 0.301 | H36: 20 | K36: 59 | L36: 21
B37: 丹麦 | C37: DK | D37: S1427 | E37: 华南/华东 | F37: 0-2 | G37: 0 | H37: 2 | K37: 70 | L37: 24 | N37: / | O37: 8-10 | P37: /
B38: 丹麦 | C38: DK | F38: 2.001-20 | G38: 2.001 | H38: 20 | K38: 68 | L38: 24
B39: 荷兰 | C39: NL | D39: S1427 | E39: 华南/华东 | F39: 0-0.1 | G39: 0 | H39: 0.1 | K39: 81 | L39: 21 | M39: 最长边≤60CM, 长+宽+高≤90CM 最小尺寸：10*15CM | N39: 收费标准：50RMB/票； 60CM＜单边≤120CM 或 90CM＜长+宽+高≤240CM | O39: 8-10 | P39: /
B40: 荷兰 | C40: NL | F40: 0.101-2 | G40: 0.101 | H40: 2 | K40: 81 | L40: 21
C41: NL | F41: 2.001-20 | G41: 2.001 | H41: 20 | K41: 79 | L41: 23
B42: 比利时 | C42: BE | D42: S1427 | E42: 华南/华东 | F42: 0-0.2 | G42: 0 | H42: 0.1 | K42: 83 | L42: 21 | O42: 8-10 | P42: /
B43: 比利时 | C43: BE | F43: 0.201-2 | G43: 0.101 | H43: 2 | K43: 83 | L43: 21
C44: BE | F44: 2.001-20 | G44: 2.001 | H44: 20 | K44: 81 | L44: 23
B45: 葡萄牙 | C45: PT | D45: S1427 | E45: 华南/华东 | F45: 0-2 | G45: 0 | H45: 2 | K45: 84 | L45: 19 | M45: 最长边不大于60CM，三边之和小于90CM，最小尺寸不小于：10CM*15CM | N45: / | O45: 10-14 | P45: 无服务邮编编码 开头：9
B46: 罗马尼亚 | C46: RO | D46: S1427 | E46: 华南/华东 | F46: 0-30 | G46: 0 | H46: 30 | K46: 63 | L46: 20 | M46: 最小尺寸：16x10x1cm 单边尺寸不超过60cm 三边之和不超过90cm | N46: / | O46: 8-10 | P46: /
B47: 克罗地亚 | C47: CRO | D47: S1427 | E47: 华南/华东 | F47: 0-30 | G47: 0 | H47: 30 | K47: 82 | L47: 22 | M47: 最小尺寸：16x10x1 cm 最大尺寸： 60x50x30 cm
B48: 匈牙利 | C48: HU | D48: S1427 | E48: 华南/华东 | F48: 0-30 | G48: 0 | H48: 30 | K48: 66 | L48: 21
B49: 奥地利 | C49: AT | D49: S1427 | E49: 华南/华东 | F49: 0-3 | G49: 0 | H49: 3 | K49: 61 | L49: 23
B50: 奥地利 | C50: AT | F50: 3-30 | G50: 3 | H50: 30 | K50: 61 | L50: 23
B51: 波兰 | C51: PL | D51: S1427 | E51: 华南/华东 | F51: 0-2 | G51: 0 | H51: 2 | K51: 51 | L51: 12 | M51: 最大尺寸：20*40*65 cm 最小尺寸不小于：16x10x1cm | N51: / | O51: 8-10 | P51: /
B52: 波兰 | C52: PL | F52: 2-20 | G52: 2 | H52: 20 | K52: 51 | L52: 14
B53: 捷克 | C53: CZ | D53: S1427 | E53: 华南/华东 | F53: 0-2 | G53: 0 | H53: 2 | K53: 52 | L53: 20 | M53: 单边不超过60cm 三边之和不超过90cm 最小尺寸不小于：16x10x1cm | N53: / | O53: 8-10 | P53: /
B54: 捷克 | C54: CZ | F54: 2-20 | G54: 2 | H54: 20 | K54: 52 | L54: 20
B55: 斯洛文尼亚 | C55: SI | D55: S1427 | E55: 华南/华东 | F55: 0-30 | G55: 0 | H55: 30 | K55: 80 | L55: 24 | M55: 最小尺寸：16x10x1 cm 最大尺寸： 60x50x30 cm | N55: / | O55: 8-10 | P55: /
B56: 斯洛伐克 | C56: SK | D56: S1427 | E56: 华南/华东 | F56: 0-30 | G56: 0 | H56: 30 | K56: 74 | L56: 20
B57: 保加利亚 | C57: BG | D57: S1427 | E57: 华南/华东 | F57: 0-30 | G57: 0 | H57: 30 | K57: 60 | L57: 17
A58: 价格使用说明
A59: 如需发货，请咨询业务人员进行备案。
A60: 一、计费重量
A61: 以G为单位进位；不足50G按50G计费；
A62: 取实重，测量以我司数据为准；泡比>1.2倍计泡，材积/6000；
A63: 二、尺寸限制补充说明
A64: 德国：不接受不规则产品（圆形货物；三角形、三棱状包装；货物主体上附带凸出的货物；货物底部不平稳，异性货物；多个包裹捆绑在一起致超尺寸的货物；使用特殊麻袋、桶状、金属、木质、布料包装的货物、薄膜或快递袋的包装有提手环 或收口；用橡皮筋捆扎或只用胶带缠绕的外包装）。若有发货，需额外收取130RMB/票的处理费；
A65: 美国、西班牙、葡萄牙、墨西哥：不接受圆筒状等不规则产品;
A66: 其他国家：不接受圆筒状等不规则产品，若有发货，需额外收取130RMB/票的处理费;
A67: 关于异形件示例，见附表【异形件说明】。
A68: 三、申报及税费
A69: 1、通用条款：
... A139: 2、最好提供销售链接和海关编码（方便快速清关）。

Sheet YwenForElectric
A1: 燕文专线追踪-特货 | J1: 返回主目录
A2: 生效日期 | B2: 2024-09-25 00:00:00
A3: 产品号 | B3: 484
A4: 大洲 | B4: 国家 | C4: CountryCode | D4: 公斤运费(元/KG) | E4: 处理费(元/件) | F4: 重量段(KG) | G4: 重量 min | H4: 重量 max | I4: 最小计费重量(KG) | K4: 公斤运费(元/KG) | L4: 处理费(元/件)
A5: 北美洲 | B5: 美国 | C5: US | D5: 133 | E5: 20 | F5: 0.001 - 0.1 | G5: 0.001 | H5: 0.1 | I5: 0.03 | K5: 126 | L5: 18
A6: 北美洲 | B6: 美国 | C6: US | D6: 127 | E6: 18 | F6: 0.101 - 0.2 | G6: 0.101 | H6: 0.2 | I6: 0.03 | K6: 126 | L6: 18
A7: 北美洲 | B7: 美国 | C7: US | D7: 123 | E7: 16 | F7: 0.201 - 0.45 | G7: 0.201 | H7: 0.45 | I7: 0.03 | K7: 126 | L7: 16
A8: 北美洲 | B8: 美国 | C8: US | D8: 116 | E8: 16 | F8: 0.451 - 0.7 | G8: 0.451 | H8: 0.7 | I8: 0.03 | K8: 120 | L8: 16
A9: 北美洲 | B9: 美国 | C9: US | D9: 116 | E9: 9 | F9: 0.701 - 1.5 | G9: 0.701 | H9: 1.5 | I9: 0.03 | K9: 120 | L9: 9
A10: 北美洲 | B10: 美国 | C10: US | D10: 116 | E10: 9 | F10: 1.501 - 2 | G10: 1.501 | H10: 2 | I10: 0.03 | K10: 120 | L10: 9
C11: US | D11: 109 | E11: 9 | F11: 2.001 - 30 | G11: 2.001 | H11: 30
A12: 北美洲 | B12: 加拿大 | C12: CA | D12: 83 | E12: 21 | F12: 0.001 - 0.15 | G12: 0.001 | H12: 0.15 | I12: 0.05 | K12: 83 | L12: 23
A13: 北美洲 | B13: 加拿大 | C13: CA | D13: 84 | E13: 22 | F13: 0.151 - 0.45 | G13: 0.151 | H13: 0.45 | I13: 0.05 | K13: 84 | L13: 23
A14: 北美洲 | B14: 加拿大 | C14: CA | D14: 86 | E14: 23 | F14: 0.451 - 0.75 | G14: 0.451 | H14: 0.75 | I14: 0.05 | K14: 86 | L14: 23
A15: 北美洲 | B15: 加拿大 | C15: CA | D15: 88 | E15: 23 | F15: 0.751 - 1 | G15: 0.751 | H15: 1 | I15: 0.05 | K15: 88 | L15: 23
A16: 北美洲 | B16: 加拿大 | C16: CA | D16: 88 | E16: 23 | F16: 1.001 - 30 | G16: 1.001 | H16: 30 | I16: 0.05 | K16: 88 | L16: 23
A17: 北美洲 | B17: 墨西哥 | C17: MX | D17: 100 | E17: 18 | F17: 0.001 - 0.5 | G17: 0.001 | H17: 0.5 | I17: 0.05 | K17: 103 | L17: 18
A18: 北美洲 | B18: 墨西哥 | C18: MX | D18: 100 | E18: 19 | F18: 0.501 - 1 | G18: 0.501 | H18: 1 | I18: 0.05 | K18: 103 | L18: 19
A19: 北美洲 | B19: 墨西哥 | C19: MX | D19: 103 | E19: 20 | F19: 1.001 - 5 | G19: 1.001 | H19: 5 | I19: 0.05 | K19: 103 | L19: 20
A20: 北美洲 | B20: 波多黎各 | C20: PR | D20: 118 | E20: 32 | F20: 0.001 - 0.1 | G20: 0.001 | H20: 0.1 | I20: 0.05 | K20: 117 | L20: 32
A21: 北美洲 | B21: 波多黎各 | C21: PR | D21: 118 | E21: 32 | F21: 0.101 - 0.2 | G21: 0.101 | H21: 0.2 | I21: 0.05 | K21: 125 | L21: 35
A22: 北美洲 | B22: 波多黎各 | C22: PR | D22: 126 | E22: 35 | F22: 0.201 - 0.34 | G22: 0.201 | H22: 0.34 | I22: 0.05 | K22: 127 | L22: 40
A23: 北美洲 | B23: 波多黎各 | C23: PR | D23: 128 | E23: 40 | F23: 0.341 - 0.45 | G23: 0.341 | H23: 0.45 | I23: 0.05 | K23: 132 | L23: 55
C24: PR | D24: 133 | E24: 55 | F24: 0.451 - 0.7 | G24: 0.451 | H24: 0.7
C25: PR | D25: 133 | E25: 55 | F25: 0.701 - 1.5 | G25: 0.701 | H25: 1.5
C26: PR | D26: 133 | E26: 55 | F26: 1.501 - 2 | G26: 1.501 | H26: 2
C27: PR | D27: 133 | E27: 55 | F27: 2.001 - 30 | G27: 2.001 | H27: 30
A28: 北美洲 | B28: 美国偏远地区 | C28: RA | D28: 118 | E28: 32 | F28: 0.001 - 0.1 | G28: 0.001 | H28: 0.1 | I28: 0.05 | K28: 117 | L28: 32
A29: 北美洲 | B29: 美国偏远地区 | C29: RA | D29: 118 | E29: 32 | F29: 0.101 - 0.2 | G29: 0.101 | H29: 0.2 | I29: 0.05 | K29: 125 | L29: 35
A30: 北美洲 | B30: 美国偏远地区 | C30: RA | D30: 126 | E30: 35 | F30: 0.201 - 0.34 | G30: 0.201 | H30: 0.34 | I30: 0.05 | K30: 127 | L30: 40
A31: 北美洲 | B31: 美国偏远地区 | C31: RA | D31: 128 | E31: 40 | F31: 0.341 - 0.45 | G31: 0.341 | H31: 0.45 | I31: 0.05 | K31: 132 | L31: 55
C32: RA | D32: 133 | E32: 55 | F32: 0.451 - 0.7 | G32: 0.451 | H32: 0.7
C33: RA | D33: 133 | E33: 55 | F33: 0.701 - 1.5 | G33: 0.701 | H33: 1.5
C34: RA | D34: 133 | E34: 55 | F34: 1.501 - 2 | G34: 1.501 | H34: 2
C35: RA | D35: 133 | E35: 55 | F35: 2.001 - 30 | G35: 2.001 | H35: 30
A36: 欧洲 | B36: 英国 | C36: UK/GB | D36: 71 | E36: 16 | F36: 0.001 - 1 | G36: 0.001 | H36: 1 | I36: 0.001 | K36: 70 | L36: 16
A37: 欧洲 | B37: 英国 | C37: UK/GB | D37: 73 | E37: 16 | F37: 1.001 - 20 | G37: 1.001 | H37: 20 | I37: 0.001 | K37: 71 | L37: 16
A38: 欧洲 | B38: 法国 | C38: FR | D38: 93 | E38: 19 | F38: 0.001 - 0.5 | G38: 0.001 | H38: 0.5 | I38: 0.001 | K38: 98 | L38: 19
A39: 欧洲 | B39: 法国 | C39: FR | D39: 91 | E39: 23 | F39: 0.501 - 30 | G39: 0.501 | H39: 30 | I39: 0.001 | K39: 96 | L39: 23
A40: 欧洲 | B40: 德国 | C40: DE | D40: 89 | E40: 19 | F40: 0.001 - 0.3 | G40: 0.001 | H40: 0.3 | I40: 0.001 | K40: 88 | L40: 19
A41: 欧洲 | B41: 德国 | C41: DE | D41: 89 | E41: 22 | F41: 0.301 - 30 | G41: 0.301 | H41: 30 | I41: 0.001 | K41: 88 | L41: 22
A42: 欧洲 | B42: 意大利 | C42: IT | D42: 72 | E42: 25 | F42: 0.001 - 30 | G42: 0.001 | H42: 30 | I42: 0.001 | K42: 67 | L42: 25
A43: 欧洲 | B43: 西班牙 | C43: ES | D43: 89 | E43: 18 | F43: 0.001 - 30 | G43: 0.001 | H43: 30 | I43: 0.001 | K43: 75 | L43: 18
A44: 欧洲 | B44: 荷兰 | C44: NL | D44: 104 | E44: 21 | F44: 0.001 - 0.3 | G44: 0.001 | H44: 0.3 | I44: 0.001 | K44: 102 | L44: 21
A45: 欧洲 | B45: 荷兰 | C45: NL | D45: 101 | E45: 21 | F45: 0.301 - 0.5 | G45: 0.301 | H45: 0.5 | I45: 0.001 | K45: 93 | L45: 21
D46: 101 | E46: 21 | F46: 0.501 - 2 | G46: 0.501 | H46: 2
D47: 105 | E47: 21 | F47: 2.001 - 30 | G47: 2.001 | H47: 30
C48: AT | D48: 98 | E48: 23 | F48: 0.001 - 30 | G48: 0.001 | H48: 30
A49: 欧洲 | B49: 比利时 | C49: BE | D49: 96 | E49: 21 | F49: 0.001 - 0.3 | G49: 0.001 | H49: 0.3 | I49: 0.05 | K49: 104 | L49: 21
A50: 欧洲 | B50: 比利时 | C50: BE | D50: 96 | E50: 21 | F50: 0.301 - 0.5 | G50: 0.301 | H50: 0.5 | I50: 0.05 | K50: 97 | L50: 21
C51: BE | D51: 96 | E51: 21 | F51: 0.501 - 2 | G51: 0.501 | H51: 2
C52: BE | D52: 92 | E52: 21 | F52: 2.001 - 30 | G52: 2.001 | H52: 30
A53: 欧洲 | B53: 保加利亚 | C53: BG | D53: 75 | E53: 18 | F53: 0.001 - 30 | G53: 0.001 | H53: 30 | I53: 0.05 | K53: 85 | L53: 18
A54: 欧洲 | B54: 瑞士 | C54: CH | D54: 94 | E54: 22 | F54: 0.001 - 0.2 | G54: 0.001 | H54: 0.2 | I54: 0.05 | K54: 95 | L54: 24
A55: 欧洲 | B55: 瑞士 | C55: CH | D55: 103 | E55: 24 | F55: 0.201 - 0.5 | G55: 0.201 | H55: 0.5 | I55: 0.05 | K55: 95 | L55: 24
A56: 欧洲 | B56: 瑞士 | C56: CH | D56: 112 | E56: 24 | F56: 0.501 - 1 | G56: 0.501 | H56: 1 | I56: 0.05 | K56: 95 | L56: 24
A57: 欧洲 | B57: 瑞士 | C57: CH | D57: 112 | E57: 24 | F57: 1.001 - 2 | G57: 1.001 | H57: 2 | I57: 0.05 | K57: 109 | L57: 34
B58: 瑞士 | C58: CH | D58: 118 | E58: 34 | F58: 2.001 - 30 | G58: 2.001 | H58: 30
B59: 塞浦路斯 | C59: CY | D59: 200 | E59: 20 | F59: 0.001 - 2 | G59: 0.001 | H59: 2
A60: 欧洲 | B60: 捷克 | C60: CZ | D60: 75 | E60: 20 | F60: 0.001 - 2 | G60: 0.001 | H60: 2 | I60: 0.05 | K60: 89 | L60: 21
A61: 欧洲 | B61: 丹麦 | C61: DK | D61: 97 | E61: 24 | F61: 0.001 - 2 | G61: 0.001 | H61: 2 | I61: 0.05 | K61: 97 | L61: 24
A62: 欧洲 | B62: 丹麦 | C62: DK | D62: 93 | E62: 24 | F62: 2.001 - 30 | G62: 2.001 | H62: 30 | I62: 0.05 | K62: 93 | L62: 24
A63: 欧洲 | B63: 爱沙尼亚 | C63: EE | D63: 90 | E63: 20 | F63: 0.001 - 2 | G63: 0.001 | H63: 2 | I63: 0.05 | K63: 80 | L63: 20
A64: 欧洲 | B64: 爱沙尼亚 | C64: EE | D64: 90 | E64: 20 | F64: 2.001 - 30 | G64: 2.001 | H64: 30 | I64: 0.05 | K64: 80 | L64: 20
A65: 欧洲 | B65: 芬兰 | C65: FI | D65: 90 | E65: 26 | F65: 0.001 - 20 | G65: 0.001 | H65: 20 | I65: 0.05 | K65: 88 | L65: 26
A66: 欧洲 | B66: 希腊 | C66: GR | D66: 100 | E66: 18 | F66: 0.001 - 30 | G66: 0.001 | H66: 30 | I66: 0.05 | K66: 93 | L66: 18
A67: 欧洲 | B67: 克罗地亚 | C67: CRO | D67: 100 | E67: 23 | F67: 0.001 - 30 | G67: 0.001 | H67: 30 | I67: 0.05 | K67: 85 | L67: 26
A68: 欧洲 | B68: 匈牙利 | C68: HU | D68: 88 | E68: 21 | F68: 0.001 - 2 | G68: 0.001 | H68: 2 | I68: 0.05 | K68: 75 | L68: 21
A69: 欧洲 | B69: 匈牙利 | C69: HU | D69: 90 | E69: 21 | F69: 2.001 - 30 | G69: 2.001 | H69: 30 | I69: 0.05 | K69: 75 | L69: 21
A70: 欧洲 | B70: 爱尔兰 | C70: IE | D70: 100 | E70: 23 | F70: 0.001 - 30 | G70: 0.001 | H70: 30 | I70: 0.05 | K70: 100 | L70: 23
A71: 欧洲 | B71: 立陶宛 | C71: LT | D71: 90 | E71: 20 | F71: 0.001 - 2 | G71: 0.001 | H71: 2 | I71: 0.05 | K71: 80 | L71: 20
... A78: 欧洲 | B78: 挪威 | C78: NO | D78: 97 | E78: 20 | F78: 0.001 - 0.1 | G78: 0.001 | H78: 0.1 | I78: 0.05 | K78: 117 | L78: 20
C79: NO | D79: 82 | E79: 20 | F79: 0.101 - 0.3 | G79: 0.101 | H79: 0.3
C80: NO | D80: 77 | E80: 20 | F80: 0.301 - 5 | G80: 0.301 | H80: 5
A81: 欧洲 | B81: 波兰 | C81: PL | D81: 83 | E81: 13 | F81: 0.001 - 0.2 | G81: 0.001 | H81: 0.2 | I81: 0.001 | K81: 78 | L81: 13
A82: 欧洲 | B82: 波兰 | C82: PL | D82: 85 | E82: 15 | F82: 0.201 - 30 | G82: 0.201 | H82: 30 | I82: 0.001 | K82: 70 | L82: 15
A83: 欧洲 | B83: 葡萄牙 | C83: PT | D83: 107 | E83: 20 | F83: 0.001 - 30 | G83: 0.001 | H83: 30 | I83: 0.05 | K83: 105 | L83: 20
A84: 欧洲 | B84: 罗马尼亚 | C84: RO | D84: 85 | E84: 18 | F84: 0.001 - 30 | G84: 0.001 | H84: 30 | I84: 0.05 | K84: 80 | L84: 18
A85: 欧洲 | B85: 瑞典 | C85: SE/SW | D85: 91 | E85: 16 | F85: 0.001 - 0.3 | G85: 0.001 | H85: 0.3 | I85: 0.05 | K85: 98 | L85: 16
A86: 欧洲 | B86: 瑞典 | C86: SE/SW | D86: 88 | E86: 21 | F86: 0.301 - 2 | G86: 0.301 | H86: 2 | I86: 0.05 | K86: 85 | L86: 21
C87: SE/SW | D87: 88 | E87: 21 | F87: 2.001 - 20 | G87: 2.001 | H87: 20
A88: 欧洲 | B88: 斯洛文尼亚 | C88: SI | D88: 100 | E88: 24 | F88: 0.001 - 30 | G88: 0.001 | H88: 30 | I88: 0.05 | K88: 85 | L88: 26
A89: 欧洲 | B89: 斯洛伐克 | C89: SK | D89: 88 | E89: 20 | F89: 0.001 - 2 | G89: 0.001 | H89: 2 | I89: 0.05 | K89: 80 | L89: 21
D90: 88 | E90: 20 | F90: 2.001 - 30 | G90: 2.001 | H90: 30
A91: 欧洲 | B91: 乌克兰 | C91: UA | D91: 115 | E91: 20 | F91: 0.001 - 0.15 | G91: 0.001 | H91: 0.15 | I91: 0.05 | K91: 115 | L91: 20
A92: 欧洲 | B92: 乌克兰 | C92: UA | D92: 100 | E92: 12 | F92: 0.151 - 30 | G92: 0.151 | H92: 30 | I92: 0.05 | K92: 100 | L92: 12
A93: 南美洲 | B93: 巴西 | C93: BR | D93: 94 | E93: 38 | F93: 0.001 - 0.5 | G93: 0.001 | H93: 0.5 | I93: 0.05 | K93: 94 | L93: 35
A94: 南美洲 | B94: 巴西 | C94: BR | D94: 94 | E94: 40 | F94: 0.501 - 1 | G94: 0.501 | H94: 1 | I94: 0.05 | K94: 94 | L94: 37
A95: 南美洲 | B95: 巴西 | C95: BR | D95: 94 | E95: 45 | F95: 1.001 - 1.5 | G95: 1.001 | H95: 1.5 | I95: 0.05 | K95: 94 | L95: 41
A96: 南美洲 | B96: 巴西 | C96: BR | D96: 94 | E96: 49 | F96: 1.501 - 2 | G96: 1.501 | H96: 2 | I96: 0.05 | K96: 94 | L96: 45
A97: 南美洲 | B97: 巴西 | C97: BR | D97: 94 | E97: 65 | F97: 2.001 - 3 | G97: 2.001 | H97: 3 | I97: 0.05 | K97: 94 | L97: 60
C98: BR | D98: 94 | E98: 75 | F98: 3.001 - 5 | G98: 3.001 | H98: 5
A99: 南美洲 | B99: 智利 | C99: CL | D99: 95 | E99: 21 | F99: 0.001 - 0.5 | G99: 0.001 | H99: 0.5 | I99: 0.05 | K99: 95 | L99: 22
A100: 南美洲 | B100: 智利 | C100: CL | D100: 103 | E100: 25 | F100: 0.501 - 1 | G100: 0.501 | H100: 1 | I100: 0.05 | K100: 108 | L100: 25
A101: 南美洲 | B101: 智利 | C101: CL | D101: 103 | E101: 30 | F101: 1.001 - 2 | G101: 1.001 | H101: 2 | I101: 0.05 | K101: 108 | L101: 30
A102: 南美洲 | B102: 哥伦比亚 | C102: CO | D102: 134 | E102: 26 | F102: 0.001 - 2 | G102: 0.001 | H102: 2 | I102: 0.05 | K102: 134 | L102: 26
A103: 南美洲 | B103: 哥伦比亚 | C103: CO | D103: 134 | E103: 26 | F103: 2.001 - 3 | G103: 2.001 | H103: 3 | I103: 0.05 | K103: 134 | L103: 26
A104: 南美洲 | B104: 秘鲁 | C104: PE | D104: 185 | E104: 21 | F104: 0.001 - 2 | G104: 0.001 | H104: 2 | I104: 0.05 | K104: 185 | L104: 21
A105: 大洋洲 | B105: 新西兰 | C105: NZ | D105: 95 | E105: 17 | F105: 0.001 - 25 | G105: 0.001 | H105: 25 | I105: 0.001 | K105: 95 | L105: 17
A106: 亚洲 | B106: 中国香港 | C106: HK | D106: 15 | E106: 22 | F106: 0.001 - 2 | G106: 0.001 | H106: 2 | I106: 0.05 | K106: 15 | L106: 22
...

Sheet CNE带电化妆品
B1: 路向国 | D1: 包裹处理费 （RMB/票） | E1: 包裹运费 （RMB/KG） | F1: 重量段 （KG） | G1: 重量 min | H1: 重量 max | I1: 参考时效 （工作日） | J1: 旺季参考时效 （工作日） | K1: 包裹运费 （RMB/KG） | L1: 包裹处理费 （RMB/票） | M1: 尺寸限制 （CM） | N1: 备注说明 | O1: 渠道状态
B2: 美国 | C2: US | D2: 25 | E2: 120 | F2: 0-0.15 | G2: 0 | H2: 0.15 | I2: 8-12 | J2: 14-20 | K2: 129 | L2: 25 | M2: 15＜L≤55，10≤W≤40, H≤25 | N2: 1）起步50g, 2）圆柱体、不规则件，需加收34元/票附加费 3）L≤66且L+2（W+H）≤213cm的超尺寸包裹，需加收34元/票附加费 4）L＞66cm或L+2（W+H）>213cm不可发 | O2: 正常
B3: 美国 | C3: US | D3: 22 | E3: 120 | F3: 0.151-0.3 | G3: 0.151 | H3: 0.3 | K3: 129 | L3: 22
B4: 美国 | C4: US | D4: 22 | E4: 110 | F4: 0.301-0.453 | G4: 0.301 | H4: 0.453 | K4: 115 | L4: 22
B5: 美国 | C5: US | D5: 22 | E5: 110 | F5: 0.454-0.7 | G5: 0.454 | H5: 0.7 | K5: 108 | L5: 22
B6: 美国 | C6: US | D6: 12 | E6: 110 | F6: 0.701-1.814 | G6: 0.701 | H6: 1.814 | K6: 108 | L6: 12
B7: 美国 | C7: US | D7: 9 | E7: 122 | F7: 1.815-10 | G7: 1.815 | H7: 10 | K7: 124 | L7: 9
B8: 瑞士 | C8: CH | D8: 21 | E8: 118 | F8: 0-0.2 | G8: 0 | H8: 0.2 | I8: 6-10 | J8: 7-10 | K8: 118 | L8: 21 | M8: 15≤L＜60,L+W+H＜90 | N8: ①50G起步 ②禁发异形件 ③禁发液体 | O8: 正常
B9: 瑞士 | C9: CH | D9: 18 | E9: 118 | F9: 0.201-0.6 | G9: 0.201 | H9: 0.6 | K9: 118 | L9: 18
B10: 瑞士 | C10: CH | D10: 18 | E10: 108 | F10: 0.601-10 | G10: 0.601 | H10: 10 | K10: 108 | L10: 18
B11: 英国 | C11: UK/GB | D11: 16 | E11: 60 | F11: 0-0.3 | G11: 0 | H11: 0.3 | I11: 6-10 | J11: 12-16 | K11: 54 | L11: 16 | M11: 15≤L≤60,10≤W≤40 H≤40 | N11: （1）2区禁用,若单独申请开通发货需加收17元/票; 2区邮编:IV、HS、KA27-28、KW、PA20-49、PA60-78、PH17-26、PH30-44、 PH49-50、ZE、GY、IM （2）3区禁用,若单独申请开通发货需加收9元/票； 3区邮编:BT，TR21-25 若有需求开通偏远邮编发货,请联系销售经理 | O11: 正常
B12: 英国 | C12: UK/GB | D12: 16 | E12: 66 | F12: 0.301-5 | G12: 0.301 | H12: 5 | K12: 56 | L12: 16
B13: 法国 | C13: FR | D13: 21 | E13: 93 | F13: 0-0.4 | G13: 0 | H13: 5 | I13: 5-10 | J13: 11-16 | K13: 90 | L13: 21 | M13: 15≤L≤60,10≤W≤50 | N13: 禁止发圆柱体，异形件加收48元/票 | O13: 正常
B14: 法国 | C14: FR | D14: 21 | E14: 80 | F14: 0.401-5 | G14: 0.401 | H14: 3 | K14: 75 | L14: 21
B15: 德国 | C15: DE | D15: 22 | E15: 60 | F15: 0-0.3 | G15: 0 | H15: 5 | I15: 6-10 | J15: 12-16 | K15: 56 | L15: 22 | M15: 15≤L≤60,10≤W≤50 | N15: 异形包裹需加收180元/票附加费 | O15: 正常
B16: 德国 | C16: DE | D16: 22 | E16: 63 | F16: 0.301-3 | G16: 0.301 | H16: 5 | K16: 59 | L16: 22
B17: 德国 | C17: DE | D17: 22 | E17: 65 | F17: 3.001-5 | G17: 3.001 | H17: 5 | K17: 61 | L17: 22
B18: 意大利 | C18: IT | D18: 26 | E18: 85 | F18: 0-5 | G18: 0 | H18: 1 | I18: 6-10 | J18: 11-18 | K18: 75 | L18: 25 | M18: 15＜L≤60，L+W+H≤130 | O18: 正常
B19: 西班牙 | C19: ES | D19: 18 | E19: 71 | F19: 0-5 | G19: 0 | H19: 1 | I19: 6-12 | J19: 10-20 | K19: 67 | L19: 18 | M19: 15≤L≤60,10≤W≤50，L+H+W≤150 | N19: 禁发液体粉末膏体、化妆品类的产品，只可以发电货产品 | O19: 正常
B20: 奥地利 | C20: AT | D20: 23 | E20: 90 | F20: 0-0.3 | G20: 0 | H20: 5 | I20: 6-12 | J20: 10-20 | K20: 90 | L20: 23 | M20: 15≤L≤60,10≤W≤50 | N20: L＞60收超长费145元，限长80cm | O20: 正常
B21: 奥地利 | C21: AT | D21: 23 | E21: 80 | F21: 0.301-1 | G21: 0.301 | H21: 5 | K21: 80 | L21: 23
B22: 奥地利 | C22: AT | D22: 23 | E22: 75 | F22: 1.001-10 | G22: 1.001 | H22: 1 | K22: 75 | L22: 23
B23: 比利时 | C23: BE | D23: 23 | E23: 90 | F23: 0-0.3 | G23: 0 | H23: 5 | I23: 4-12 | J23: 10-20 | K23: 90 | L23: 23 | M23: 15≤L≤60,10≤W≤50，H≤40 | N23: 异形包裹需加收50元/票附加费，直径≥40cm或(直径x2+长)≥2m的异形包裹不可发 | O23: 正常
B24: 比利时 | C24: BE | D24: 21 | E24: 78 | F24: 0.301-1 | G24: 0.301 | H24: 5 | K24: 78 | L24: 21
B25: 比利时 | C25: BE | D25: 21 | E25: 72 | F25: 1.001-5 | G25: 1.001 | H25: 5 | K25: 72 | L25: 21
B26: 荷兰 | C26: NL | D26: 24 | E26: 82 | F26: 0-0.2 | G26: 0 | H26: 5 | I26: 4-12 | J26: 10-20 | K26: 78 | L26: 24 | M26: 15≤L≤60,10≤W≤50 | N26: 禁发异形件 | O26: 正常
B27: 荷兰 | C27: NL | D27: 21 | E27: 82 | F27: 0.201-0.5 | G27: 0.201 | H27: 5 | K27: 78 | L27: 21
B28: 荷兰 | C28: NL | D28: 21 | E28: 72 | F28: 0.501-5 | G28: 0.501 | H28: 5 | K28: 68 | L28: 21
B29: 立陶宛 | C29: LT | D29: 59 | E29: 80 | F29: 0-1 | G29: 0 | H29: 5 | I29: 4-12 | J29: 10-20 | K29: 80 | L29: 59 | M29: 15≤L≤60,10≤W≤50 | N29: 异形包裹需加收180元/票附加费 | O29: 正常
B30: 立陶宛 | C30: LT | D30: 58 | E30: 70 | F30: 1.001-5 | G30: 1.001 | H30: 1 | K30: 70 | L30: 58
B31: 斯洛伐克 | C31: SK | D31: 25 | E31: 68 | F31: 0-0.3 | G31: 0 | H31: 5 | I31: 4-12 | J31: 10-20 | K31: 68 | L31: 25 | M31: 15≤L≤60,10≤W≤50,H≤30 | N31: 1) 圆柱体、不规则件，且尺寸小于50cm*20cm(直径*高)，需加收55元/票附加费 2) L≤105cm且H≤55cm的超尺寸包裹，附加费55元/票 3) L>105cm或H>55cm不可发 | O31: 正常
B32: 斯洛伐克 | C32: SK | D32: 21 | E32: 72 | F32: 0.301-5 | G32: 0.301 | H32: 5 | K32: 72 | L32: 21
B33: 波兰 | C33: PL | D33: 16 | E33: 78 | F33: 0-0.2 | G33: 0 | H33: 5 | I33: 4-12 | J33: 10-20 | K33: 78 | L33: 16 | M33: 15≤L≤60,10≤W≤50 | N33: 异形包裹需加收52元/票附加费 | O33: 正常
B34: 波兰 | C34: PL | D34: 16 | E34: 70 | F34: 0.201-5 | G34: 0.201 | H34: 5 | K34: 70 | L34: 16
B35: 斯洛文尼亚 | C35: SI | D35: 26 | E35: 76 | F35: 0-0.3 | G35: 0 | H35: 5 | I35: 4-12 | J35: 10-20 | K35: 76 | L35: 26 | M35: 15≤L≤60,10≤W≤50,H≤30 | N35: 1) 圆柱体、不规则件，且尺寸小于50cm*20cm(直径*高)，需加收55元/票附加费 2) L≤105cm且H≤55cm的超尺寸包裹，附加费55元/票 3) L>105cm或H>55cm不可发 | O35: 正常
B36: 斯洛文尼亚 | C36: SI | D36: 26 | E36: 70 | F36: 0.301-5 | G36: 0.301 | H36: 5 | K36: 70 | L36: 26
B37: 爱沙尼亚 | C37: EE | D37: 70 | E37: 80 | F37: 0-0.5 | G37: 0 | H37: 5 | I37: 4-12 | J37: 10-20 | K37: 80 | L37: 70 | M37: 15≤L≤60,10≤W≤50 | O37: 正常
B38: 爱沙尼亚 | C38: EE | D38: 70 | E38: 74 | F38: 0.501-5 | G38: 0.501 | H38: 5 | K38: 74 | L38: 70
B39: 芬兰 | C39: FI | D39: 94 | E39: 84 | F39: 0-0.5 | G39: 0 | H39: 5 | I39: 4-12 | J39: 10-20 | K39: 84 | L39: 94 | M39: 15≤L≤60,10≤W≤50 | N39: 异形包裹需加收180元/票附加费 | O39: 正常
B40: 芬兰 | C40: FI | D40: 94 | E40: 74 | F40: 0.501-5 | G40: 0.501 | H40: 5 | K40: 74 | L40: 94
B41: 希腊 | C41: GR | D41: 66 | E41: 76 | F41: 0-5 | G41: 0 | H41: 1 | I41: 4-12 | J41: 10-20 | K41: 76 | L41: 66 | M41: 15≤L≤60,10≤W≤50 | N41: 异形包裹需加收180元/票附加费 | O41: 正常
B42: 捷克 | C42: CZ | D42: 21 | E42: 92 | F42: 0-0.5 | G42: 0 | H42: 2 | I42: 4-12 | J42: 10-20 | K42: 90 | L42: 21 | M42: 15≤L≤60,10≤W≤50,H≤30 | N42: 1) 圆柱体、不规则件，且尺寸小于50cm*20cm(直径*高)，需加收55元/票附加费 2) L≤105cm且H≤55cm的超尺寸包裹，附加费55元/票 3) L>105cm或H>55cm不可发 | O42: 正常
B43: 捷克 | C43: CZ | D43: 21 | E43: 80 | F43: 0.501-1 | G43: 0.501 | H43: 5 | K43: 75 | L43: 21
B44: 捷克 | C44: CZ | D44: 21 | E44: 72 | F44: 1.001-5 | G44: 1.001 | H44: 1 | K44: 65 | L44: 21
B45: 保加利亚 | C45: BG | D45: 22 | E45: 94 | F45: 0-0.2 | G45: 0 | H45: 2 | I45: 4-12 | J45: 10-20 | K45: 94 | L45: 22 | M45: 15≤L≤60,10≤W≤50,H≤30 | N45: 1) 圆柱体、不规则件，且尺寸小于50cm*20cm(直径*高)，需加收55元/票附加费 2) L≤105cm且H≤55cm的超尺寸包裹，附加费55元/票 3) L>105cm或H>55cm不可发 | O45: 正常
B46: 保加利亚 | C46: BG | D46: 22 | E46: 82 | F46: 0.201-0.5 | G46: 0.201 | H46: 5 | K46: 82 | L46: 22
B47: 保加利亚 | C47: BG | D47: 18 | E47: 76 | F47: 0.501-5 | G47: 0.501 | H47: 5 | K47: 76 | L47: 18
B48: 罗马尼亚 | C48: RO | D48: 24 | E48: 103 | F48: 0-0.3 | G48: 0 | H48: 0.3 | I48: 4-12 | J48: 10-20 | K48: 103 | L48: 24 | M48: 15≤L≤60,10≤W≤50,H≤30 | N48: 1) 圆柱体、不规则件，且尺寸小于50cm*20cm(直径*高)，需加收55元/票附加费 2) L≤105cm且H≤55cm的超尺寸包裹，附加费55元/票 3) L>105cm或H>55cm不可发 | O48: 正常
B49: 罗马尼亚 | C49: RO | D49: 21 | E49: 88 | F49: 0.301-0.5 | G49: 0.301 | H49: 0.5 | K49: 88 | L49: 21
B50: 罗马尼亚 | C50: RO | D50: 21 | E50: 82 | F50: 0.501-5 | G50: 0.501 | H50: 5 | K50: 82 | L50: 21
B51: 爱尔兰 | C51: IE | D51: 58 | E51: 88 | F51: 0-0.5 | G51: 0 | H51: 0.5 | I51: 4-12 | J51: 10-20 | K51: 88 | L51: 58 | M51: 15≤L≤60,10≤W≤50 | O51: 正常
B52: 爱尔兰 | C52: IE | D52: 50 | E52: 86 | F52: 0.501-5 | G52: 0.501 | H52: 5 | K52: 86 | L52: 50
B53: 瑞典 | C53: SE/SW | D53: 16 | E53: 88 | F53: 0-0.3 | G53: 0 | H53: 0.3 | I53: 4-12 | J53: 10-20 | K53: 86 | L53: 16 | M53: L＜60,L+W+H＜120 | N53: 异形包裹需加收180元/票附加费 | O53: 正常
B54: 瑞典 | C54: SE/SW | D54: 21 | E54: 75 | F54: 0.301-5 | G54: 0.301 | H54: 5 | K54: 72 | L54: 21
B55: 拉脱维亚 | C55: LV | D55: 68 | E55: 76 | F55: 0-5 | G55: 0 | H55: 5 | I55: 4-12 | J55: 10-20 | K55: 76 | L55: 68 | M55: 15≤L≤60,10≤W≤50 | O55: 正常
B56: 丹麦 | C56: DK | D56: 26 | E56: 88 | F56: 0-0.3 | G56: 0 | H56: 0.3 | I56: 4-12 | J56: 10-20 | K56: 85 | L56: 26 | M56: L＜60,L+2W+2H＜120 | O56: 正常
B57: 丹麦 | C57: DK | D57: 24 | E57: 80 | F57: 0.301-5 | G57: 0.301 | H57: 5 | K57: 76 | L57: 24
B58: 匈牙利 | C58: HU | D58: 21 | E58: 67 | F58: 0-5 | G58: 0 | H58: 5 | I58: 4-12 | J58: 10-20 | K58: 67 | L58: 21 | M58: 15≤L≤60,10≤W≤50,H≤30 | N58: 1) 圆柱体、不规则件，且尺寸小于50cm*20cm(直径*高)，需加收55元/票附加费 2) L≤105cm且H≤55cm的超尺寸包裹，附加费55元/票 3) L>105cm或H>55cm不可发 | O58: 正常
B59: 克罗地亚 | C59: CRO | D59: 25 | E59: 75 | F59: 0-5 | G59: 0 | H59: 5 | I59: 4-12 | J59: 10-20 | K59: 75 | L59: 25 | M59: 15≤L≤60,10≤W≤50,H≤30 | N59: 1) 圆柱体、不规则件，且尺寸小于50cm*20cm(直径*高)，需加收55元/票附加费 2) L≤105cm且H≤55cm的超尺寸包裹，附加费55元/票 3) L>105cm或H>55cm不可发 | O59: 正常
B60: 卢森堡 | C60: LU | D60: 26 | E60: 84 | F60: 0-0.4 | G60: 0 | H60: 0.4 | I60: 4-12 | J60: 10-20 | K60: 84 | L60: 26 | M60: 15≤L≤60,10≤W≤50，H≤40 | N60: 异形包裹需加收50元/票附加费，直径≥40cm或(直径x2+长)≥2m的异形包裹不可发 | O60: 正常
B61: 卢森堡 | C61: LU | D61: 26 | E61: 78 | F61: 0.401-5 | G61: 0.401 | H61: 5 | K61: 78 | L61: 26
B62: 加拿大 | C62: CA | D62: 22 | E62: 86 | F62: 0-1 | G62: 0 | H62: 1 | I62: 7-12 | J62: 10-15 | K62: 86 | L62: 22 | M62: 15≤L≤80,10≤W≤75 L+W+H≤150 | N62: ①50G起步 ②禁发圆柱体，木制品，包括狗项圈在内的动物背带牵引绳，轮胎 ③禁发液体粉末膏体、化妆品类的产品，只可以发电货产品 | O62: 恢复收寄
B63: 加拿大 | C63: CA | D63: 22 | E63: 94 | F63: 1.001-2 | G63: 1.001 | H63: 2 | K63: 94 | L63: 22
B64: 加拿大 | C64: CA | D64: 21 | E64: 86 | F64: 2.001-30 | G64: 2.001 | H64: 30 | K64: 86 | L64: 21
B65: 挪威 | C65: NO | D65: 23 | E65: 75 | F65: 0-0.1 | G65: 0 | H65: 0.1 | I65: 6-10 | J65: 7-12 | K65: 75 | L65: 23 | M65: 15≤L＜45,L+W+H＜90 | N65: 禁发三角形、圆柱形、圆锥和球形包裹以及无法用机器扫描的包裹 | O65: 正常
B66: 挪威 | C66: NO | D66: 21 | E66: 75 | F66: 0.1-0.3 | G66: 0.1 | H66: 0.3 | K66: 75 | L66: 21
B67: 挪威 | C67: NO | D67: 19 | E67: 70 | F67: 0.3-5 | G67: 0.3 | H67: 5 | K67: 70 | L67: 19
B68: 葡萄牙 | C68: PT | D68: 20 | E68: 67 | F68: 0-1 | G68: 0 | H68: 1 | I68: 6-12 | J68: 10-20 | K68: 65 | L68: 20 | M68: 15≤L≤60,10≤W≤50，L+H+W≤150 | O68: 正常
B69: 葡萄牙 | C69: PT | D69: 20 | E69: 76 | F69: 1.001-2 | G69: 1.001 | H69: 2 | K69: 74 | L69: 20
B70: 葡萄牙 | C70: PT | D70: 20 | E70: 70 | F70: 2.001-5 | G70: 2.001 | H70: 5 | K70: 68 | L70: 20
B71: 注意：疫情期间时效变动较大，详情请咨询业务代表或客服人员。
B72: 重要提示： 随着步入旺季，为了尽量保证货物正常转运，请您避免出现以下几种因货物无法上分拣设备需人工操作导致转运延迟的情况： 1、超大规格或小于10x15CM尺寸的货物； 2、不规则货物（例如：球形、三角形、圆柱形等）； 3、面单不合规或模糊褶皱； 4、账户欠费。 5、所有国家不接受亚马逊仓库地址及其他海外仓库地址。
B73: 注意事项： | G73: =LEFT(F73,5)
B74: 一、特货电货承接范围 | G74: =LEFT(F74,5)
B75: 1、发货须知： | D75: 特货电货承接范围! | L75: 特货电货承接范围!
B76: 二、计泡说明 | G76: =LEFT(F76,5)
B77: 1、计泡标准：货物单边>5CM且L+W+H＞50CM需计泡
B78: 2、计泡系数
B79: ①.单边>5CM且50CM<L+W+H≤70CM,记泡系数10000
B80: ②.单边>5CM且70CM<L+W+H≤90CM,记泡系数8000
B81: ③.L+W+H>90CM,记泡系数6000
B82: 注：三边之和小于50CM单件泡比过高或者批量单一品类泡货请提前沟通，否则我司有计泡的权利。
B83: 三、在线追踪 | G83: =LEFT(F83,5)
B84: 1、专线类挂号小包类可追踪；平邮小包类不可追踪；
B85: 2、查询网址如下：http://www.cne.com；http://www.17track.net
B86: 四、关税相关
B87: 1、清关模式：DDP模式，CNE预收VAT，不提供税单。
B88: 2、美国：不接受申报价值超过USD800的产品，且不接受同一个收件人名且同一地址，当天累计包裹申报价值超过USD800
B89: 3、日本：（1）不接受申报价值超过JPY10000（约等同USD95）的产品，不收所有真皮类包裹，包括但不仅限于，真皮外套，真皮皮鞋、真皮腰带等。如产生税金，由发件人支付，税金实报实销，不收取手续费。 （2）不接受公司性质的收件人地址，包裹内商品数量需符合正常个人自用范围，且每批次同一个收件人只能一个包裹，否则因此导致的查验和相关费用等风险由发件方自行承担。
B90: 4、欧盟国家：下单时若未提供IOSS：（1）与CNE签署代缴协议，由CNE进行VAT的预收和代缴，VAT计费规则是每日发给同一收件人包裹的合计申报价值≤150EUR 时，按照订单申报价值的20%收取；（2）下单时已提供IOSS，申报价值≤150EUR 时，CNE将不再征收VAT；（3）包裹申报价值＞EUR150 时，有无IOSS都要要征收VAT，另还会产生关税，产生关税以及产生的关税额度视所寄物品与当地海关的政策法规而定，CNE将会在海关账单下来的当月补扣该费用。
B91: 5、英国：自2021年1月1日起，所有发往英国的货物取消15GBP以下免征VAT的豁免政策，至此之后申报价值≤135 英镑的 B2C 进口货物需交纳VAT，申报价值＞135 英镑的进口货物需交纳VAT和关税（Duty）。
B92: 6、加拿大：申报价值超过CAD20（约等同15USD），则会产生关税，我司将依据客户申报价值收取20%关税。 | G92: =LEFT(F92,5)
B93: 7、挪威：不接受申报价值超过NOK3000（约等同EUR280）的产品，客户下单需提供VOEC号码。
B94: 8、瑞士：不接受申报价值超过CHF62（约等同EUR60）的产品，且不接受同一个收件人名且同一地址，当天累计包裹申报价值超过CHF 62。
B95: 五、查询标准
B96: 1、发货起30天内：30天内查询确认丢件或者国外一直不反馈调查结果超过30天，按照遗失进行赔偿。（具体调查服务及调查时间以当地服务商反馈为准）
B97: 2、发货起30-60天：只提供查询，若30天内国外确认丢件，则赔偿；没有确认，不赔偿。
B98: 3、发货起＞60天：不提供查询以及索赔服务。
B99: 4、不接受查询：易碎品；送达后破损或者少货；
B100: 5、调查时间：最长30天。
...

Sheet CNE全球优先
B1: 路向国 | D1: 包裹处理费 （RMB/票） | E1: 包裹运费 （RMB/KG） | F1: 重量段 （KG） | G1: 重量 min | H1: 重量 max | I1: 参考时效 （工作日） | J1: 旺季参考时效 （工作日） | K1: 包裹运费 （RMB/KG） | L1: 包裹处理费 （RMB/票） | M1: 尺寸限制 （CM） | N1: 备注说明
B2: 美国 | C2: US | D2: 28 | E2: 94 | F2: 0-0.1 | G2: 0 | H2: 0.1 | I2: 6-8 | J2: 8-10 | K2: 94 | L2: 28 | M2: 15≤L≤55，10≤W≤45，L+W+H≤115cm | N2: ①起步50g, ②圆柱体、不规则件、需加收28元/票附加费 ③L<76cm且L+W+H≤115cm的超尺寸包裹， 附加费28元/票 ④L≥ 76 CM或L+W+H> 115cm不可发
B3: 美国 | C3: US | D3: 26 | E3: 94 | F3: 0.101-0.2 | G3: 0.101 | H3: 1-0.2 | K3: 94 | L3: 26
B4: 美国 | C4: US | D4: 27 | E4: 94 | F4: 0.201-0.3 | G4: 0.201 | H4: 1-0.3 | K4: 94 | L4: 27
B5: 美国 | C5: US | D5: 30 | E5: 94 | F5: 0.301-0.453 | G5: 0.301 | H5: 0.453 | K5: 94 | L5: 30
B6: 美国 | C6: US | D6: 45 | E6: 81 | F6: 0.454-0.8 | G6: 0.454 | H6: 4-0.8 | K6: 81 | L6: 45
B7: 美国 | C7: US | D7: 45 | E7: 81 | F7: 0.801-10 | G7: 0.801 | H7: 10 | K7: 81 | L7: 45
B8: 英国 | C8: UK/GB | D8: 16 | E8: 50 | F8: 0-0.2 | G8: 0 | H8: 0.2 | I8: 3-5 | J8: 4-6 | K8: 50 | L8: 16 | M8: 15≤L≤50 L+W≤80 | N8: ①不规则加收45元/票， ②（1）2区禁用,若单独申请开通发货需加收17元/票; 2区邮编:IV、HS、KA27-28、KW、PA20-49、PA60-78、PH17-26、PH30-44、 PH49-50、ZE、GY、IM （2）3区禁用,若单独申请开通发货需加收9元/票； 3区邮编:BT，TR21-25 若有需求开通偏远邮编发货,请联系销售经理
B9: 英国 | C9: UK/GB | D9: 16 | E9: 57 | F9: 0.201-3 | G9: 0.201 | H9: 201-3 | K9: 57 | L9: 16
B10: 法国 | C10: FR | D10: 25 | E10: 52 | F10: 0-0.25 | G10: 0-0.2 | H10: 0.25 | I10: 4-6 | J10: 6-8 | K10: 52 | L10: 25 | M10: 15≤L≤60,10≤W≤60 L+W+H≤90 | N10: 禁发圆柱体，异形件加收48元/票
B11: 法国 | C11: FR | D11: 25 | E11: 57 | F11: 0.251-0.75 | G11: 0.251 | H11: 0.75 | K11: 57 | L11: 25
B12: 法国 | C12: FR | D12: 25 | E12: 57 | F12: 0.751-5 | G12: 0.751 | H12: 751-5 | K12: 57 | L12: 25
B13: 德国 | C13: DE | D13: 23 | E13: 70 | F13: 0-0.2 | G13: 0-0.2 | H13: 0.2 | I13: 4-6 | J13: 5-7 | K13: 70 | L13: 23 | M13: 15≤L≤60,10≤W≤60 L+W+H≤90 | N13: 异形包裹需加收180元/票附加费
B14: 德国 | C14: DE | D14: 23 | E14: 66 | F14: 0.201-0.5 | G14: 0.201 | H14: 1-0.5 | K14: 66 | L14: 23
B15: 德国 | C15: DE | D15: 23 | E15: 62 | F15: 0.501-5 | G15: 0.501 | H15: 501-5 | K15: 62 | L15: 23
B16: 注意：疫情期间时效变动较大，详情请咨询业务代表或客服人员。
B17: 重要提示： 随着步入旺季，为了尽量保证货物正常转运，请您避免出现以下几种因货物无法上分拣设备需人工操作导致转运延迟的情况： 1、超大规格或小于10x15CM尺寸的货物； 2、不规则货物（例如：球形、三角形、圆柱形等）； 3、面单不合规或模糊褶皱； 4、账户欠费。 5、所有国家不接受亚马逊仓库地址及其他海外仓库地址。
B18: 注意事项：
B19: 一、计泡说明
B20: 1、计泡标准：货物单边>5CM且L+W+H＞50CM需计泡
B21: 2、计泡系数
B22: ①.单边>5CM且50CM<L+W+H≤70CM,记泡系数10000
B23: ②.单边>5CM且70CM<L+W+H≤90CM,记泡系数8000
B24: ③.L+W+H>90CM,记泡系数6000
B25: 注：三边之和小于50CM单件泡比过高或者批量单一品类泡货请提前沟通，否则我司有计泡的权利。
B26: 二、在线追踪
B27: 1、专线类挂号小包类可追踪；平邮小包类不可追踪；
... B51: 3、退件重派有费用，重派原国家收取原运费，详情请咨询客服人员。

Sheet 华翰纯电
F1: 智惠选专线-纯电 | N1: 生效日期：2025.02.22 9:00 | O1: 返回目录
B2: 国家 | F2: 重量段KG | K2: 运费RMB/KG | L2: 挂号费RMB/票 | M2: 尺寸限制cm | N2: 参考时效（工作日）
B3: 美国 | C3: US | F3: 0.05≤W≤0.1 | G3: 0.05 | H3: 0.1 | K3: 142 | L3: 41 | M3: 最大尺寸≤50x40x25cm 长+2(宽+高)≤120cm 最小尺寸≥15x10x1cm 超过以上尺寸将收取超长附加费 超长附加费：加收 150元/票 | N3: 7-11
B4: 美国 | C4: US | F4: 0.1<W≤0.2 | G4: 0.1 | H4: 0.2 | K4: 142 | L4: 41
B5: 美国 | C5: US | F5: 0.2<W≤0.3 | G5: 0.2 | H5: 0.3 | K5: 142 | L5: 41
B6: 美国 | C6: US | F6: 0.3<W≤0.453 | G6: 0.3 | H6: 0.453 | K6: 142 | L6: 41
B7: 美国 | C7: US | F7: 0.453<W≤0.7 | G7: 0.453 | H7: 0.7 | K7: 162 | L7: 49
B8: 美国 | C8: US | F8: 0.7<W≤1 | G8: 0.7 | H8: 1 | K8: 152 | L8: 49
B9: 美国 | C9: US | F9: 1<W≤2 | G9: 1 | H9: 2 | K9: 142 | L9: 44
B10: 美国 | C10: US | F10: 2<W≤10 | G10: 2 | H10: 10 | K10: 142 | L10: 44
B11: 加拿大 | C11: CA | F11: 0.05≤W≤0.3 | G11: 0.05 | H11: 0.3 | K11: 128 | L11: 40 | M11: 最长边≤60cm；长+宽+高≤90cm 最小尺寸≥15x10x1cm | N11: 9-15
B12: 加拿大 | C12: CA | F12: 0.3<W≤0.75 | G12: 0.3 | H12: 0.75 | K12: 134 | L12: 47
B13: 加拿大 | C13: CA | F13: 0.75<W≤1 | G13: 0.75 | H13: 1 | K13: 134 | L13: 51
B14: 加拿大 | C14: CA | F14: 1<W≤1.5 | G14: 1 | H14: 1.5 | K14: 133 | L14: 53
B15: 加拿大 | C15: CA | F15: 1.5<W≤2 | G15: 1.5 | H15: 2 | K15: 133 | L15: 53
B16: 加拿大 | C16: CA | F16: 2<W≤10 | G16: 2 | H16: 10 | K16: 133 | L16: 53
B17: 墨西哥 | C17: MX | F17: 0.05≤W≤0.5 | G17: 0.05 | H17: 0.5 | K17: 138 | L17: 31 | M17: 最大尺寸≤45x40x40cm 最小尺寸≥15x10x1cm | N17: 12-17
B18: 墨西哥 | C18: MX | F18: 0.5<W≤1 | G18: 0.5 | H18: 1 | K18: 138 | L18: 31
B19: 墨西哥 | C19: MX | F19: 1<W≤5 | G19: 1 | H19: 5 | K19: 138 | L19: 31
B20: 英国 | C20: UK/GB | F20: 0.01≤W≤1 | G20: 0.01 | H20: 1 | K20: 133 | L20: 26 | M20: 最大尺寸<60x40x40cm 最小尺寸≥15x10x1cm | N20: 6-10
B21: 英国 | C21: UK/GB | F21: 1<W≤2 | G21: 1 | H21: 2 | K21: 133 | L21: 26 | O21: 英国-EVRI偏远邮编
B22: 英国 | C22: UK/GB | F22: 2<W≤10 | G22: 2 | H22: 10 | K22: 133 | L22: 26
B23: 德国 | C23: DE | F23: 0.01<W≤1 | G23: 0.01 | H23: 1 | K23: 123 | L23: 28 | M23: 0<W≤1：最大尺寸≤ 35x25x10cm 1<W≤10：最大尺寸≤ 60x50x40cm 最小尺寸≥15x10x1cm Packstation：尺寸限制<60x30x30cm | N23: 8-12
B24: 德国 | C24: DE | F24: 1<W≤2 | G24: 1 | H24: 2 | K24: 123 | L24: 28
B25: 德国 | C25: DE | F25: 2<W≤10 | G25: 2 | H25: 10 | K25: 123 | L25: 28
B26: 法国 | C26: FR | F26: 0.01≤W≤1 | G26: 0.01 | H26: 1 | K26: 154 | L26: 36 | M26: 最大尺寸≤60x50x40cm 最小尺寸≥15x10x1cm | N26: 8-12
B27: 法国 | C27: FR | F27: 1<W≤2 | G27: 1 | H27: 2 | K27: 154 | L27: 36
B28: 法国 | C28: FR | F28: 2<W≤10 | G28: 2 | H28: 10 | K28: 154 | L28: 36
B29: 意大利 | C29: IT | F29: 0.01≤W≤1 | G29: 0.01 | H29: 1 | K29: 141 | L29: 37 | M29: 最大尺寸≤60x50x40cm 最小尺寸≥15x10x1cm | N29: 8-12
B30: 意大利 | C30: IT | F30: 1<W≤2 | G30: 1 | H30: 2 | K30: 141 | L30: 37
B31: 意大利 | C31: IT | F31: 2<W≤10 | G31: 2 | H31: 10 | K31: 141 | L31: 37
B32: 西班牙 | C32: ES | F32: 0.01≤W≤1 | G32: 0.01 | H32: 1 | K32: 136 | L32: 30 | M32: 最大尺寸≤60x50x40cm 最小尺寸≥15x10x1cm | N32: 8-12
B33: 西班牙 | C33: ES | F33: 1<W≤2 | G33: 1 | H33: 2 | K33: 136 | L33: 30
B34: 西班牙 | C34: ES | F34: 2<W≤10 | G34: 2 | H34: 10 | K34: 136 | L34: 30
B35: 葡萄牙 | C35: PT | F35: 0.01≤W≤1 | G35: 0.01 | H35: 1 | K35: 137 | L35: 30 | M35: 最大尺寸≤60x50x40cm 最小尺寸≥15x10x1cm | N35: 8-12
B36: 葡萄牙 | C36: PT | F36: 1<W≤2 | G36: 1 | H36: 2 | K36: 137 | L36: 30
B37: 葡萄牙 | C37: PT | F37: 2<W≤10 | G37: 2 | H37: 10 | K37: 137 | L37: 30
B38: 荷兰 | C38: NL | F38: 0.01≤W≤1 | G38: 0.01 | H38: 1 | K38: 140 | L38: 47 | M38: 最大尺寸≤60x50x40cm 最小尺寸≥15x10x1cm | N38: 8-12
B39: 荷兰 | C39: NL | F39: 1<W≤2 | G39: 1 | H39: 2 | K39: 140 | L39: 47
B40: 荷兰 | C40: NL | F40: 2<W≤10 | G40: 2 | H40: 10 | K40: 140 | L40: 47
B41: 比利时 | C41: BE | F41: 0.01≤W≤1 | G41: 0.01 | H41: 1 | K41: 133 | L41: 34 | M41: 最大尺寸≤60x50x40cm 最小尺寸≥15x10x1cm | N41: 8-12
B42: 比利时 | C42: BE | F42: 1<W≤2 | G42: 1 | H42: 2 | K42: 133 | L42: 34
B43: 比利时 | C43: BE | F43: 2<W≤10 | G43: 2 | H43: 10 | K43: 133 | L43: 34
B44: 卢森堡 | C44: LU | F44: 0.01≤W≤1 | G44: 0.01 | H44: 1 | K44: 114 | L44: 33 | M44: 最大尺寸≤60x50x40cm 最小尺寸≥15x10x1cm | N44: 8-12
B45: 卢森堡 | C45: LU | F45: 1<W≤2 | G45: 1 | H45: 2 | K45: 114 | L45: 33
B46: 卢森堡 | C46: LU | F46: 2<W≤10 | G46: 2 | H46: 10 | K46: 114 | L46: 33
B47: 瑞典 | C47: SE/SW | F47: 0.01≤W≤1 | G47: 0.01 | H47: 1 | K47: 124 | L47: 48 | M47: 最大尺寸≤60x50x40cm 最小尺寸≥15x10x1cm | N47: 8-12
B48: 瑞典 | C48: SE/SW | F48: 1<W≤2 | G48: 1 | H48: 2 | K48: 124 | L48: 48
B49: 瑞典 | C49: SE/SW | F49: 2<W≤10 | G49: 2 | H49: 10 | K49: 124 | L49: 48
B50: 奥地利 | C50: AT | F50: 0.01≤W≤1 | G50: 0.01 | H50: 1 | K50: 120 | L50: 41 | M50: 最大尺寸≤60x50x40cm 最小尺寸≥15x10x1cm | N50: 8-12
B51: 奥地利 | C51: AT | F51: 1<W≤2 | G51: 1 | H51: 2 | K51: 120 | L51: 26
B52: 奥地利 | C52: AT | F52: 2<W≤10 | G52: 2 | H52: 10 | K52: 120 | L52: 26
B53: 捷克 | C53: CZ | F53: 0.01≤W≤1 | G53: 0.01 | H53: 1 | K53: 133 | L53: 47 | M53: 最大尺寸≤60x50x40cm 最小尺寸≥15x10x1cm | N53: 8-12
B54: 捷克 | C54: CZ | F54: 1<W≤2 | G54: 1 | H54: 2 | K54: 133 | L54: 47
B55: 捷克 | C55: CZ | F55: 2<W≤10 | G55: 2 | H55: 10 | K55: 133 | L55: 47
B56: 波兰 | C56: PL | F56: 0.01≤W≤1 | G56: 0.01 | H56: 1 | K56: 130 | L56: 48 | M56: 最大尺寸≤60x50x40cm 最小尺寸≥15x10x1cm | N56: 8-12
B57: 波兰 | C57: PL | F57: 1<W≤2 | G57: 1 | H57: 2 | K57: 130 | L57: 34
B58: 波兰 | C58: PL | F58: 2<W≤10 | G58: 2 | H58: 10 | K58: 130 | L58: 34
B59: 斯洛伐克 | C59: SK | F59: 0.01≤W≤1 | G59: 0.01 | H59: 1 | K59: 122 | L59: 35 | M59: 最大尺寸≤60x50x40cm 最小尺寸≥15x10x1cm | N59: 8-14
B60: 斯洛伐克 | C60: SK | F60: 1<W≤2 | G60: 1 | H60: 2 | K60: 122 | L60: 35
B61: 斯洛伐克 | C61: SK | F61: 2<W≤10 | G61: 2 | H61: 10 | K61: 122 | L61: 35
B62: 斯洛文尼亚 | C62: SI | F62: 0.01≤W≤1 | G62: 0.01 | H62: 1 | K62: 153 | L62: 78 | M62: 最大尺寸≤60x50x40cm 最小尺寸≥15x10x1cm | N62: 8-12
B63: 斯洛文尼亚 | C63: SI | F63: 1<W≤2 | G63: 1 | H63: 2 | K63: 153 | L63: 48
B64: 斯洛文尼亚 | C64: SI | F64: 2<W≤10 | G64: 2 | H64: 10 | K64: 153 | L64: 45
B65: 爱尔兰 | C65: IE | F65: 0.01≤W≤1 | G65: 0.01 | H65: 1 | K65: 125 | L65: 39 | M65: 最大尺寸≤60x50x40cm 最小尺寸≥15x10x1cm | N65: 8-14
B66: 爱尔兰 | C66: IE | F66: 1<W≤2 | G66: 1 | H66: 2 | K66: 125 | L66: 39
B67: 爱尔兰 | C67: IE | F67: 2<W≤10 | G67: 2 | H67: 10 | K67: 125 | L67: 39
B68: 匈牙利 | C68: HU | F68: 0.01≤W≤1 | G68: 0.01 | H68: 1 | K68: 119 | L68: 29 | M68: 最大尺寸≤60x50x40cm 最小尺寸≥15x10x1cm | N68: 8-12
B69: 匈牙利 | C69: HU | F69: 1<W≤2 | G69: 1 | H69: 2 | K69: 119 | L69: 29
B70: 匈牙利 | C70: HU | F70: 2<W≤10 | G70: 2 | H70: 10 | K70: 119 | L70: 29
B71: 立陶宛 | C71: LT | F71: 0.01≤W≤1 | G71: 0.01 | H71: 1 | K71: 143 | L71: 67 | M71: 最大尺寸≤60x50x40cm 最小尺寸≥15x10x1cm | N71: 8-14
B72: 立陶宛 | C72: LT | F72: 1<W≤2 | G72: 1 | H72: 2 | K72: 143 | L72: 51
B73: 立陶宛 | C73: LT | F73: 2<W≤10 | G73: 2 | H73: 10 | K73: 143 | L73: 31
B74: 丹麦 | C74: DK | F74: 0.01≤W≤1 | G74: 0.01 | H74: 1 | K74: 124 | L74: 40 | M74: 最大尺寸≤60x50x40cm 最小尺寸≥15x10x1cm | N74: 8-12
B75: 丹麦 | C75: DK | F75: 1<W≤2 | G75: 1 | H75: 2 | K75: 124 | L75: 30
B76: 丹麦 | C76: DK | F76: 2<W≤10 | G76: 2 | H76: 10 | K76: 124 | L76: 30
B77: 克罗地亚 | C77: CRO | F77: 0.01≤W≤1 | G77: 0.01 | H77: 1 | K77: 153 | L77: 119 | M77: 最大尺寸≤60x50x40cm 最小尺寸≥15x10x1cm | N77: 8-12
B78: 克罗地亚 | C78: CRO | F78: 1<W≤2 | G78: 1 | H78: 2 | K78: 153 | L78: 102
B79: 克罗地亚 | C79: CRO | F79: 2<W≤10 | G79: 2 | H79: 10 | K79: 136 | L79: 102
B80: 罗马尼亚 | C80: RO | F80: 0.01≤W≤1 | G80: 0.01 | H80: 1 | K80: 119 | L80: 31 | M80: 最大尺寸≤60x50x40cm 最小尺寸≥15x10x1cm | N80: 8-12
B81: 罗马尼亚 | C81: RO | F81: 1<W≤2 | G81: 1 | H81: 2 | K81: 119 | L81: 31
B82: 罗马尼亚 | C82: RO | F82: 2<W≤10 | G82: 2 | H82: 10 | K82: 119 | L82: 31
B83: 拉脱维亚 | C83: LV | F83: 0.01≤W≤1 | G83: 0.01 | H83: 1 | K83: 153 | L83: 87 | M83: 最大尺寸≤60x50x40cm 最小尺寸≥15x10x1cm | N83: 8-12
B84: 拉脱维亚 | C84: LV | F84: 1<W≤2 | G84: 1 | H84: 2 | K84: 158 | L84: 64
B85: 拉脱维亚 | C85: LV | F85: 2<W≤10 | G85: 2 | H85: 10 | K85: 136 | L85: 54
B86: 爱沙尼亚 | C86: EE | F86: 0.01≤W≤1 | G86: 0.01 | H86: 1 | K86: 141 | L86: 94 | M86: 最大尺寸≤60x50x40cm 最小尺寸≥15x10x1cm | N86: 8-12
B87: 爱沙尼亚 | C87: EE | F87: 1<W≤2 | G87: 1 | H87: 2 | K87: 158 | L87: 61
B88: 爱沙尼亚 | C88: EE | F88: 2<W≤10 | G88: 2 | H88: 10 | K88: 136 | L88: 61
B89: 芬兰 | C89: FI | F89: 0.01≤W≤1 | G89: 0.01 | H89: 1 | K89: 146 | L89: 66 | M89: 最大尺寸≤60x50x40cm 最小尺寸≥15x10x1cm | N89: 8-14
B90: 芬兰 | C90: FI | F90: 1<W≤2 | G90: 1 | H90: 2 | K90: 146 | L90: 50
B91: 芬兰 | C91: FI | F91: 2<W≤10 | G91: 2 | H91: 10 | K91: 136 | L91: 50
B92: 保加利亚 | C92: BG | F92: 0.01≤W≤1 | G92: 0.01 | H92: 1 | K92: 122 | L92: 30 | M92: 最大尺寸≤60x50x40cm 最小尺寸≥15x10x1cm | N92: 8-14
B93: 保加利亚 | C93: BG | F93: 1<W≤2 | G93: 1 | H93: 2 | K93: 122 | L93: 26
B94: 保加利亚 | C94: BG | F94: 2<W≤10 | G94: 2 | H94: 10 | K94: 122 | L94: 26
B95: 希腊 | C95: GR | F95: 0.01≤W≤1 | G95: 0.01 | H95: 1 | K95: 127 | L95: 31 | M95: 最大尺寸≤60x50x40cm 最小尺寸≥15x10x1cm | N95: 8-14
B96: 希腊 | C96: GR | F96: 1<W≤2 | G96: 1 | H96: 2 | K96: 127 | L96: 31
B97: 希腊 | C97: GR | F97: 2<W≤10 | G97: 2 | H97: 10 | K97: 127 | L97: 31
B98: 马耳他 | C98: MAL | F98: 0.01≤W≤1 | G98: 0.01 | H98: 1 | K98: 164 | L98: 54 | M98: 最大尺寸≤60x50x40cm 最小尺寸≥15x10x1cm | N98: 8-14
B99: 马耳他 | C99: MAL | F99: 1<W≤2 | G99: 1 | H99: 2 | K99: 158 | L99: 43
B100: 马耳他 | C100: MAL | F100: 2<W≤10 | G100: 2 | H100: 10 | K100: 158 | L100: 34
...

Sheet 华翰食品
F1: Specialpak甄选专线 | N1: 生效日期：2025.02.22 9:00
B2: 国家 | F2: 重量段KG | K2: 运费 RMB/KG | L2: 挂号费 RMB/票 | M2: 尺寸限制cm | N2: 参考时效（工作日）
B3: 美国 | C3: US | F3: 0.05≤W≤0.1 | G3: 0.05 | H3: 0.1 | K3: 126 | L3: 27 | M3: 最大尺寸≤55x40x25cm 长+宽+高≤90cm 最小尺寸≥15x10x1cm | N3: 8-10
B4: 美国 | C4: US | F4: 0.1<W≤0.2 | G4: 0.1 | H4: 0.2 | K4: 126 | L4: 27
B5: 美国 | C5: US | F5: 0.2<W≤0.3 | G5: 0.2 | H5: 0.3 | K5: 126 | L5: 27
B6: 美国 | C6: US | F6: 0.3<W≤0.453 | G6: 0.3 | H6: 0.453 | K6: 143 | L6: 22
B7: 美国 | C7: US | F7: 0.453<W≤0.7 | G7: 0.453 | H7: 0.7 | K7: 159 | L7: 22
B8: 美国 | C8: US | F8: 0.7<W≤1 | G8: 0.7 | H8: 1 | K8: 159 | L8: 22
B9: 美国 | C9: US | F9: 1<W≤2 | G9: 1 | H9: 2 | K9: 159 | L9: 15
B10: 加拿大 | C10: CA | F10: 0.05≤W≤0.3 | G10: 0.05 | H10: 0.3 | K10: 108 | L10: 30 | M10: 最长边≤60cm；长+宽+高≤90cm 最小尺寸≥15x10x1cm | N10: 9-15
B11: 加拿大 | C11: CA | F11: 0.3<W≤0.75 | G11: 0.3 | H11: 0.75 | K11: 108 | L11: 30
B12: 加拿大 | C12: CA | F12: 0.75<W≤1 | G12: 0.75 | H12: 1 | K12: 108 | L12: 30
B13: 加拿大 | C13: CA | F13: 1<W≤1.5 | G13: 1 | H13: 1.5 | K13: 108 | L13: 30
B14: 加拿大 | C14: CA | F14: 1.5<W≤2 | G14: 1.5 | H14: 2 | K14: 95 | L14: 30
B15: 英国 | C15: UK/GB | F15: 0.01≤W≤1 | G15: 0.01 | H15: 1 | K15: 131 | L15: 20 | M15: 最大尺寸<60x40x40cm 最小尺寸≥15x10x1cm | N15: 6-10
B16: 英国 | C16: UK/GB | F16: 1<W≤2 | G16: 1 | H16: 2 | K16: 120 | L16: 20 | O16: 英国-EVRI偏远邮编
B17: 英国 | C17: UK/GB | F17: 2<W≤10 | G17: 2 | H17: 10 | K17: 120 | L17: 20
B18: 德国 | C18: DE | F18: 0.05≤W≤1 | G18: 0.05 | H18: 1 | K18: 125 | L18: 26 | M18: 最长边≤60cm；长+宽+高≤90cm 最小尺寸≥15x10x1cm | N18: 6-8
B19: 德国 | C19: DE | F19: 1<W≤2 | G19: 1 | H19: 2 | K19: 125 | L19: 26
B20: 法国 | C20: FR | F20: 0.05≤W≤1 | G20: 0.05 | H20: 1 | K20: 154 | L20: 35 | M20: 最长边≤60cm；长+宽+高≤90cm 最小尺寸≥15x10x1cm | N20: 7-9
B21: 法国 | C21: FR | F21: 1<W≤2 | G21: 1 | H21: 2 | K21: 154 | L21: 35
B22: 意大利 | C22: IT | F22: 0.05≤W≤1 | G22: 0.05 | H22: 1 | K22: 141 | L22: 35 | M22: 最长边≤60cm；长+宽+高≤90cm 最小尺寸≥15x10x1cm | N22: 8-16
B23: 意大利 | C23: IT | F23: 1<W≤2 | G23: 1 | H23: 2 | K23: 141 | L23: 35
B24: 西班牙 | C24: ES | F24: 0.05≤W≤1 | G24: 0.05 | H24: 1 | K24: 135 | L24: 29 | M24: 最长边≤60cm；长+宽+高≤90cm 最小尺寸≥15x10x1cm | N24: 8-10
B25: 西班牙 | C25: ES | F25: 1<W≤2 | G25: 1 | H25: 2 | K25: 135 | L25: 29
B26: 葡萄牙 | C26: PT | F26: 0.05≤W≤1 | G26: 0.05 | H26: 1 | K26: 138 | L26: 28 | M26: 最长边≤60cm；长+宽+高≤90cm 最小尺寸≥15x10x1cm | N26: 8-16
B27: 葡萄牙 | C27: PT | F27: 1<W≤2 | G27: 1 | H27: 2 | K27: 138 | L27: 28
B28: 墨西哥 | C28: MX | F28: 0.05≤W≤0.5 | G28: 0.05 | H28: 0.5 | K28: 141 | L28: 23 | M28: 最大尺寸≤45x40x40cm 最小尺寸≥15x10x1cm | N28: 12-17
B29: 墨西哥 | C29: MX | F29: 0.5<W≤1 | G29: 0.5 | H29: 1 | K29: 141 | L29: 23
B30: 墨西哥 | C30: MX | F30: 1<W≤5 | G30: 1 | H30: 5 | K30: 141 | L30: 23

Sheet 华翰特货
F1: 智惠选专线-特货 | N1: 生效日期：2025.02.22 9:00 | O1: 返回目录
B2: 国家 | F2: 重量段KG | K2: 运费 RMB/KG | L2: 挂号费 RMB/票 | M2: 尺寸限制cm | N2: 参考时效（工作日）
B3: 美国 | C3: US | F3: 0.05≤W≤0.1 | G3: 0.05 | H3: 0.1 | K3: 147 | L3: 34 | M3: 最大尺寸≤55x45x38cm 长+2(宽+高)≤127cm 最小尺寸≥15x10x1cm 超过以上尺寸将收取超长附加费 超长附加费：加收 4.5 USD/包裹 | N3: 8-10
B4: 美国 | C4: US | F4: 0.1<W≤0.2 | G4: 0.1 | H4: 0.2 | K4: 147 | L4: 34
B5: 美国 | C5: US | F5: 0.2<W≤0.3 | G5: 0.2 | H5: 0.3 | K5: 147 | L5: 34
B6: 美国 | C6: US | F6: 0.3<W≤0.453 | G6: 0.3 | H6: 0.453 | K6: 174 | L6: 23
B7: 美国 | C7: US | F7: 0.453<W≤0.7 | G7: 0.453 | H7: 0.7 | K7: 194 | L7: 23
B8: 美国 | C8: US | F8: 0.7<W≤1 | G8: 0.7 | H8: 1 | K8: 182 | L8: 23
B9: 美国 | C9: US | F9: 1<W≤2 | G9: 1 | H9: 2 | K9: 179 | L9: 16
B10: 美国 | C10: US | F10: 2<W≤4.5 | G10: 2 | H10: 4.5 | K10: 174 | L10: 16
B11: 英国 | C11: =VLOOKUP(B11,'[13]Detailed Calculation table'!A:B,2,0) -> UK/GB | F11: 0.05≤W≤1.5 | G11: 0.05 | H11: 1.5 | K11: 107 | L11: 19
B12: 英国 | C12: =VLOOKUP(B12,'[13]Detailed Calculation table'!A:B,2,0) -> UK/GB | F12: 1.5<W≤2 | G12: 1.5 | H12: 2 | K12: 107 | L12: 19
B13: 墨西哥 | C13: =VLOOKUP(B13,'[13]Detailed Calculation table'!A:B,2,0) -> MX | F13: 0.05≤W≤0.5 | G13: 0.05 | H13: 0.5 | K13: 131 | L13: 25
B14: 墨西哥 | C14: =VLOOKUP(B14,'[13]Detailed Calculation table'!A:B,2,0) -> MX | F14: 0.5<W≤1 | G14: 0.5 | H14: 1 | K14: 131 | L14: 25
B15: 墨西哥 | C15: =VLOOKUP(B15,'[13]Detailed Calculation table'!A:B,2,0) -> MX | F15: 1<W≤5 | G15: 1 | H15: 5 | K15: 131 | L15: 25
B16: 德国 | C16: =VLOOKUP(B16,'[13]Detailed Calculation table'!A:B,2,0) -> DE | F16: 0.05≤W≤1 | G16: 0.05 | H16: 1 | K16: 116 | L16: 26
B17: 德国 | C17: =VLOOKUP(B17,'[13]Detailed Calculation table'!A:B,2,0) -> DE | F17: 1<W≤2 | G17: 1 | H17: 2 | K17: 116 | L17: 26
B18: 法国 | C18: =VLOOKUP(B18,'[13]Detailed Calculation table'!A:B,2,0) -> FR | F18: 0.05≤W≤1 | G18: 0.05 | H18: 1 | K18: 131 | L18: 32
B19: 法国 | C19: =VLOOKUP(B19,'[13]Detailed Calculation table'!A:B,2,0) -> FR | F19: 1<W≤2 | G19: 1 | H19: 2 | K19: 131 | L19: 32
B20: 意大利 | C20: =VLOOKUP(B20,'[13]Detailed Calculation table'!A:B,2,0) -> IT | F20: 0.05≤W≤1 | G20: 0.05 | H20: 1 | K20: 132 | L20: 35
B21: 意大利 | C21: =VLOOKUP(B21,'[13]Detailed Calculation table'!A:B,2,0) -> IT | F21: 1<W≤2 | G21: 1 | H21: 2 | K21: 132 | L21: 35
B22: 西班牙 | C22: =VLOOKUP(B22,'[13]Detailed Calculation table'!A:B,2,0) -> ES | F22: 0.05≤W≤1 | G22: 0.05 | H22: 1 | K22: 126 | L22: 29
... B49: 立陶宛 | C49: =VLOOKUP(B49,'[13]Detailed Calculation table'!A:B,2,0) -> LT | F49: 1<W≤2 | G49: 1 | H49: 2 | K49: 129 | L49: 49

Sheet CNE全球特惠
D1: CNE全球特惠
O3: 返回目录
B5: 路向国 | D5: 包裹处理费 （RMB/票） | E5: 包裹运费 （RMB/KG） | F5: 重量段 （KG） | I5: 参考时效 （工作日） | J5: 旺季参考时效 （工作日） | M5: 尺寸限制 （CM） | N5: 备注说明 | O5: 渠道状态
B6: 葡萄牙 | D6: 20 | E6: 55 | F6: 0-1KG | I6: 5-7 | J6: 7-12 | M6: 15≤L≤60,10≤W≤50，L+H+W≤150 | O6: 正常
D7: 20 | E7: 55 | F7: 1.001-15KG
B8: 奥地利 | D8: 23 | E8: 85 | F8: 0-0.2KG | I8: 5-7 | J8: 7-12 | M8: 15≤L≤100,10≤W≤60 | N8: L＞100收超长费145元，限长120cm | O8: 正常
D9: 23 | E9: 70 | F9: 0.201-0.5KG
D10: 23 | E10: 66 | F10: 0.501-30KG
B11: 斯洛文尼亚 | D11: 26 | E11: 66 | F11: 0-30KG | I11: 5-7 | J11: 7-16 | M11: 15≤L≤60,10≤W≤50,H≤30 | N11: 1) 圆柱体、不规则件，且尺寸小于50cm*20cm(直径*高)，需加收55元/票附加费 2) L≤105cm且H≤55cm的超尺寸包裹，附加费55元/票 3) L>105cm或H>55cm不可发 | O11: 正常
B12: 爱沙尼亚 | D12: 24 | E12: 80 | F12: 0-0.2KG | I12: 5-7 | J12: 7-16 | M12: 15≤L≤60,10≤W≤50,H≤30 | N12: 1) 圆柱体、不规则件，且尺寸小于50cm*20cm(直径*高)，需加收55元/票附加费 2) L≤105cm且H≤55cm的超尺寸包裹，附加费55元/票 3) L>105cm或H>55cm不可发 | O12: 正常
D13: 21 | E13: 78 | F13: 0.201-0.5KG
D14: 20 | E14: 68 | F14: 0.501-30KG
B15: 芬兰 | D15: 91 | E15: 102 | F15: 0-0.2KG | I15: 5-7 | J15: 7-16 | M15: 15≤L≤100,10≤W≤80 | N15: 异形包裹需加收180元/票附加费 | O15: 正常
D16: 88 | E16: 102 | F16: 0.201-0.6KG
D17: 75 | E17: 102 | F17: 0.601-30KG
B18: 希腊 | D18: 63 | E18: 117 | F18: 0-0.3KG | I18: 6-10 | J18: 10-14 | M18: 15≤L≤60,10≤W≤50，L+2*W+2*H≤200 | N18: L＞60收超长费50元，限长80cm，异形包裹需加收180元/票附加费 | O18: 正常
D19: 50 | E19: 122 | F19: 0.301-0.5KG
D20: 49 | E20: 108 | F20: 0.501-1KG
D21: 34 | E21: 109 | F21: 1.001-30KG
B22: 保加利亚 | D22: 21 | E22: 84 | F22: 0-0.5KG | I22: 5-7 | J22: 7-16 | M22: 15≤L≤60,10≤W≤50,H≤30 | N22: 1) 圆柱体、不规则件，且尺寸小于50cm*20cm(直径*高)，需加收55元/票附加费 2) L≤105cm且H≤55cm的超尺寸包裹，附加费55元/票 3) L>105cm或H>55cm不可发 | O22: 正常
D23: 17 | E23: 75 | F23: 0.501-1KG
D24: 17 | E24: 70 | F24: 1.001-30KG
B25: 罗马尼亚 | D25: 26 | E25: 90 | F25: 0-0.3KG | I25: 5-7 | J25: 7-16 | M25: 15≤L≤60,10≤W≤50,H≤30 | N25: 1) 圆柱体、不规则件，且尺寸小于50cm*20cm(直径*高)，需加收55元/票附加费 2) L≤105cm且H≤55cm的超尺寸包裹，附加费55元/票 3) L>105cm或H>55cm不可发 | O25: 正常
D26: 21 | E26: 79 | F26: 0.301-1KG
D27: 21 | E27: 76 | F27: 1.001-30KG
B28: 拉脱维亚 | D28: 46 | E28: 50 | F28: 0-30KG | I28: 5-7 | J28: 7-16 | M28: 15≤L≤60,10≤W≤50 | O28: 正常
B29: 克罗地亚 | D29: 25 | E29: 66 | F29: 0-30KG | I29: 5-7 | J29: 7-16 | M29: 15≤L≤60,10≤W≤50,H≤30 | N29: 1) 圆柱体、不规则件，且尺寸小于50cm*20cm(直径*高)，需加收55元/票附加费 2) L≤105cm且H≤55cm的超尺寸包裹，附加费55元/票 3) L>105cm或H>55cm不可发 | O29: 正常
B30: 卢森堡 | D30: 26 | E30: 78 | F30: 0-0.4KG | I30: 5-7 | J30: 7-16 | M30: 15≤L≤100,10≤W≤60 L+H+W<150 | N30: 异形包裹需加收50元/票附加费，直径≥40cm或(直径x2+长)≥2m的异形包裹不可发 | O30: 正常
D31: 26 | E31: 68 | F31: 0.401-30KG
B32: 澳大利亚 | C32: AU | D32: 44 | E32: 75 | F32: 0-0.2KG | G32: 0 | H32: 0.2 | I32: 4-10 | J32: 12-16 | K32: 75 | L32: 44 | M32: 15≤L≤105，10≤W≤70，H≤70 | O32: 正常
B33: 澳大利亚 | C33: AU | D33: 39 | E33: 75 | F33: 0.201-0.4KG | G33: 0.201 | H33: 0.4 | K33: 75 | L33: 39
B34: 澳大利亚 | C34: AU | D34: 37 | E34: 67 | F34: 0.401-20KG | G34: 0.401 | H34: 20 | K34: 67 | L34: 37
B35: 加拿大 | D35: 23 | E35: 52 | F35: 0-0.2KG | I35: 7-12 | J35: 10-15 | M35: 15≤L≤80,10≤W≤75 L+W+H≤150 | N35: ①50G起步 ②禁发圆柱体，木制品，包括狗项圈在内的动物背带牵引绳，轮胎 | O35: 正常
D36: 23 | E36: 60 | F36: 0.201-0.5KG
D37: 23 | E37: 66 | F37: 0.501-1KG
D38: 23 | E38: 72 | F38: 1.001-30KG
B39: 新西兰 | D39: 17 | E39: 77 | F39: 0-0.3KG | I39: 8-12 | J39: 12-16 | M39: 15≤L≤100，体积≤0.125m3 | N39: 偏远费加收20元/票 | O39: 正常
D40: 17 | E40: 70 | F40: 0.301-20KG
B41: 挪威 | D41: 21 | E41: 82 | F41: 0-0.1KG | I41: 6-10 | J41: 7-12 | M41: 15≤L＜45,L+W+H＜90 | N41: 禁发三角形、圆柱形、圆锥和球形包裹以及无法用机器扫描的包裹 | O41: 正常
D42: 20 | E42: 72 | F42: 0.101-0.4KG
D43: 19 | E43: 69 | F43: 0.401-5KG
B44: 注意：疫情期间时效变动较大，详情请咨询业务代表或客服人员。
B45: 重要提示： 随着步入旺季，为了尽量保证货物正常转运，请您避免出现以下几种因货物无法上分拣设备需人工操作导致转运延迟的情况： 1、超大规格或小于10x15CM尺寸的货物； 2、不规则货物（例如：球形、三角形、圆柱形等）； 3、面单不合规或模糊褶皱； 4、账户欠费。 5、所有国家不接受亚马逊仓库地址及其他海外仓库地址。
B46: 注意事项：
B47: 一、计泡说明
B48: 1、计泡标准：货物单边>5CM且L+W+H＞50CM需计泡（除日本），日本是L+W+H＞78CM需计泡。
B49: 2、计泡系数（除日本）
B50: ①.单边>5CM且50CM<L+W+H≤70CM,记泡系数10000
B51: ②.单边>5CM且70CM<L+W+H≤90CM,记泡系数8000
B52: ③.L+W+H>90CM,记泡系数6000
B53: 3、日本计泡系数
B54: ①.78CM<L+W+H≤90CM,记泡系数8000
B55: ②.L+W+H>90CM,记泡系数6000
... B90: 特别提示：如贵司同意接受我司服务，即视为贵司已详细阅读过以上内容，并接受各条款的约束。

Sheet 华翰智慧选特惠
F1: 智惠选专线-特惠 | N1: 生效日期：2025.05.26 9:00 | O1: 返回目录
B2: 国家 | F2: 重量段KG | K2: 运费 RMB/KG | L2: 挂号费 RMB/票 | M2: 尺寸限制cm | N2: 参考时效（工作日）
B3: 英国 | C3: UK/GB | F3: 0.01≤W≤1 | G3: 0.01 | H3: 1 | K3: 74 | L3: 16 | M3: 最大尺寸<60x40x40cm 最小尺寸≥15x10x1cm | N3: 6-10
B4: 英国 | C4: UK/GB | F4: 1<W≤2 | G4: 1 | H4: 2 | K4: 74 | L4: 16
B5: 加拿大 | C5: CA | F5: 0.05≤W≤0.3 | G5: 0.05 | H5: 0.3 | K5: 115 | L5: 28 | M5: 最长边≤60cm；长+宽+高≤90cm 最小尺寸≥15x10x1cm | N5: 9-15
B6: 加拿大 | C6: CA | F6: 0.3<W≤0.75 | G6: 0.3 | H6: ≤0.75 | K6: 115 | L6: 28
B7: 加拿大 | C7: CA | F7: 0.75<W≤1 | G7: 0.75 | H7: 1 | K7: 115 | L7: 28
B8: 加拿大 | C8: CA | F8: 1<W≤1.5 | G8: 1 | H8: ≤1.5 | K8: 115 | L8: 28
B9: 加拿大 | C9: CA | F9: 1.5<W≤2 | G9: 1.5 | H9: 2 | K9: 111 | L9: 28
B10: 墨西哥 | C10: MX | F10: 0.05≤W≤0.5 | G10: 0.05 | H10: 0.5 | K10: 119 | L10: 22.5 | M10: 最大尺寸≤45x40x40cm 最小尺寸≥15x10x1cm | N10: 12-17
B11: 墨西哥 | C11: MX | F11: 0.5<W≤1 | G11: 0.5 | H11: 1 | K11: 119 | L11: 22.5
B12: 墨西哥 | C12: MX | F12: 1<W≤5 | G12: 1 | H12: 5 | K12: 119 | L12: 22.5
B13: 德国 | C13: DE | F13: 0.01≤W≤1 | G13: 0.01 | H13: 1 | K13: 104 | L13: 22.5 | M13: 最长边≤60cm；长+宽+高≤90cm 最小尺寸≥15x10x1cm | N13: 6-8
B14: 德国 | C14: DE | F14: 1<W≤2 | G14: 1 | H14: 2 | K14: 104 | L14: 22.5
B15: 法国 | C15: FR | F15: 0.01≤W≤1 | G15: 0.01 | H15: 1 | K15: 88 | L15: 30 | M15: 最长边≤60cm；长+宽+高≤90cm 最小尺寸≥15x10x1cm | N15: 7-9
B16: 法国 | C16: FR | F16: 1<W≤2 | G16: 1 | H16: 2 | K16: 88 | L16: 30
B17: 意大利 | C17: IT | F17: 0.01≤W≤1 | G17: 0.01 | H17: 1 | K17: 116 | L17: 32.5 | M17: 最长边≤60cm；长+宽+高≤90cm 最小尺寸≥15x10x1cm | N17: 8-16
B18: 意大利 | C18: IT | F18: 1<W≤2 | G18: 1 | H18: 2 | K18: 116 | L18: 32.5
B19: 西班牙 | C19: ES | F19: 0.01≤W≤1 | G19: 0.01 | H19: 1 | K19: 113 | L19: 25 | M19: 最长边≤60cm；长+宽+高≤90cm 最小尺寸≥15x10x1cm | N19: 8-10
B20: 西班牙 | C20: ES | F20: 1<W≤2 | G20: 1 | H20: 2 | K20: 113 | L20: 25
B21: 葡萄牙 | C21: PT | F21: 0.01≤W≤1 | G21: 0.01 | H21: 1 | K21: 120 | L21: 25.5 | M21: 最长边≤60cm；长+宽+高≤90cm 最小尺寸≥15x10x1cm | N21: 8-16
B22: 葡萄牙 | C22: PT | F22: 1<W≤2 | G22: 1 | H22: 2 | K22: 120 | L22: 25.5
B23: 荷兰 | C23: NL | F23: 0.01≤W≤1 | G23: 0.01 | H23: 1 | K23: 112 | L23: 39 | M23: 最长边≤60cm；长+宽+高≤90cm 最小尺寸≥15x10x1cm | N23: 6-8
B24: 荷兰 | C24: NL | F24: 1<W≤2 | G24: 1 | H24: 2 | K24: 112 | L24: 39
B25: 比利时 | C25: BE | F25: 0.01≤W≤1 | G25: 0.01 | H25: 1 | K25: 110 | L25: 28 | M25: 最长边≤60cm；长+宽+高≤90cm 最小尺寸≥15x10x1cm | N25: 7-9
B26: 比利时 | C26: BE | F26: 1<W≤2 | G26: 1 | H26: 2 | K26: 110 | L26: 28
B27: 卢森堡 | C27: LU | F27: 0.01≤W≤1 | G27: 0.01 | H27: 1 | K27: 97 | L27: 29 | M27: 最长边≤60cm；长+宽+高≤90cm 最小尺寸≥15x10x1cm | N27: 6-8
B28: 卢森堡 | C28: LU | F28: 1<W≤2 | G28: 1 | H28: 2 | K28: 97 | L28: 29
B29: 瑞典 | C29: SE/SW | F29: 0.01≤W≤1 | G29: 0.01 | H29: 1 | K29: 107 | L29: 44 | M29: 最长边≤60cm；长+宽+高≤90cm 最小尺寸≥15x10x1cm | N29: 8-12
B30: 瑞典 | C30: SE/SW | F30: 1<W≤2 | G30: 1 | H30: 2 | K30: 107 | L30: 44
B31: 奥地利 | C31: AT | F31: 0.01≤W≤1 | G31: 0.01 | H31: 1 | K31: 102 | L31: 36 | M31: 最长边≤60cm；长+宽+高≤90cm 最小尺寸≥15x10x1cm | N31: 8-10
B32: 奥地利 | C32: AT | F32: 1<W≤2 | G32: 1 | H32: 2 | K32: 102 | L32: 23
B33: 捷克 | C33: CZ | F33: 0.01≤W≤1 | G33: 0.01 | H33: 1 | K33: 114 | L33: 43 | M33: 最长边≤60cm；长+宽+高≤90cm 最小尺寸≥15x10x1cm | N33: 8-10
B34: 捷克 | C34: CZ | F34: 1<W≤2 | G34: 1 | H34: 2 | K34: 114 | L34: 43
B35: 波兰 | C35: PL | F35: 0.01≤W≤1 | G35: 0.01 | H35: 1 | K35: 109 | L35: 42 | M35: 最长边≤60cm；长+宽+高≤90cm 最小尺寸≥15x10x1cm | N35: 8-12
B36: 波兰 | C36: PL | F36: 1<W≤2 | G36: 1 | H36: 2 | K36: 109 | L36: 32
B37: 斯洛伐克 | C37: SK | F37: 0.01≤W≤1 | G37: 0.01 | H37: 1 | K37: 104 | L37: 31 | M37: 最长边≤60cm；长+宽+高≤90cm 最小尺寸≥15x10x1cm | N37: 8-16
B38: 斯洛伐克 | C38: SK | F38: 1<W≤2 | G38: 1 | H38: 2 | K38: 104 | L38: 31
B39: 斯洛文尼亚 | C39: SI | F39: 0.01≤W≤1 | G39: 0.01 | H39: 1 | K39: 129 | L39: 72 | M39: 最长边≤60cm；长+宽+高≤90cm 最小尺寸≥15x10x1cm | N39: 8-10
B40: 斯洛文尼亚 | C40: SI | F40: 1<W≤2 | G40: 1 | H40: 2 | K40: 129 | L40: 44
B41: 爱尔兰 | C41: IE | F41: 0.01≤W≤1 | G41: 0.01 | H41: 1 | K41: 105 | L41: 34 | M41: 最长边≤60cm；长+宽+高≤90cm 最小尺寸≥15x10x1cm | N41: 8-15
B42: 爱尔兰 | C42: IE | F42: 1<W≤2 | G42: 1 | H42: 2 | K42: 105 | L42: 34
B43: 匈牙利 | C43: HU | F43: 0.01≤W≤1 | G43: 0.01 | H43: 1 | K43: 100 | L43: 25 | M43: 最长边≤60cm；长+宽+高≤90cm 最小尺寸≥15x10x1cm | N43: 8-12
B44: 匈牙利 | C44: HU | F44: 1<W≤2 | G44: 1 | H44: 2 | K44: 100 | L44: 25
B45: 立陶宛 | C45: LT | F45: 0.01≤W≤1 | G45: 0.01 | H45: 1 | K45: 122 | L45: 64 | M45: 最长边≤60cm；长+宽+高≤90cm 最小尺寸≥15x10x1cm | N45: 8-12
B46: 立陶宛 | C46: LT | F46: 1<W≤2 | G46: 1 | H46: 2 | K46: 122 | L46: 48
C47: AU | F47: 0.1≤W≤1 | G47: 0.1 | H47: 1 | K47: 91 | L47: 35
C48: AU | F48: 1<W≤2 | G48: 1 | H48: 2 | K48: 91 | L48: 35
C49: AU | F49: 2<W≤5 | G49: 2 | H49: 5 | K49: 91 | L49: 35
C50: US | F50: 0.05≤W≤0.1 | G50: 0.05 | H50: 0.1 | K50: 111 | L50: 24
C51: US | F51: 0.1<W≤0.2 | G51: 0.1 | H51: 0.2 | K51: 111 | L51: 24
C52: US | F52: 0.2<W≤0.3 | G52: 0.2 | H52: 0.3 | K52: 111 | L52: 24
C53: US | F53: 0.3<W≤0.453 | G53: 0.3 | H53: 0.453 | K53: 128 | L53: 19
C54: US | F54: 0.453<W≤0.7 | G54: 0.453 | H54: 0.7 | K54: 132 | L54: 18
C55: US | F55: 0.7<W≤1 | G55: 0.7 | H55: 1 | K55: 132 | L55: 14
C56: US | F56: 1<W≤2 | G56: 1 | H56: 2 | K56: 126 | L56: 12
C57: NZ | F57: 0<W≤1 | G57: 0 | H57: 1 | K57: 100 | L57: 26
C58: NZ | F58: 1<W≤2 | G58: 1 | H58: 2 | K58: 100 | L58: 26

Sheet 顺速宝Plus
A1: 顺速宝Plus价目表
B3: 澳大利亚(一区) | C3: AU | G3: 0 | H3: 2 | K3: 85 | L3: 20
B4: 澳大利亚(二区) | C4: AU | G4: 0 | H4: 2 | K4: 85 | L4: 25
B5: 澳大利亚(三区) | C5: AU | G5: 0 | H5: 2 | K5: 85 | L5: 50
B6: 澳大利亚(四区) | C6: AU | G6: 0 | H6: 2 | K6: 85 | L6: 60
B7: 奥地利 | C7: AT | G7: 0 | H7: 2 | K7: 85 | L7: 27
B8: 白俄罗斯 | C8: BY | G8: 0 | H8: 2 | K8: 155 | L8: 10
B9: 比利时 | C9: BE | G9: 0 | H9: 2 | K9: 105 | L9: 20
B10: 巴西 | C10: BR | G10: 0 | H10: 2 | K10: 95 | L10: 30
B11: 保加利亚 | C11: BG | G11: 0 | H11: 2 | K11: 95 | L11: 19
B12: 加拿大 | C12: CA | G12: 0 | H12: 2 | K12: 75 | L12: 25
B13: 捷克 | C13: CZ | G13: 0 | H13: 2 | K13: 75 | L13: 19
B14: 丹麦 | C14: DK | G14: 0 | H14: 2 | K14: 95 | L14: 28
... B42: 美国 | C42: US | G42: 0 | H42: 2 | K42: 115 | L42: 26

Sheet 蜂鸟普货
B1: 蜂鸟国际物流 - 欧洲经济普货线 渠道编码：欧洲经济P-HF 材积/6000
A2: 广州 | B2: 国家 | D2: 重量限制（KG） | I2: 运费（元/KG） | J2: 处理费（元/件） | M2: 尾程派送商 | N2: 尺寸限制（cm） | P2: 面单尺寸 | Q2: 时效
B3: 德国 | C3: =VLOOKUP(B3,#REF!,2,0) -> #REF! | D3: 0-0.4 | G3: 0 | H3: 0.4 | I3: 56.5 | J3: 28 | K3: 56.5 | L3: 28 | M3: DHL Paket | N3: L＜35.3，W＜25，H＜10 | P3: 10*10cm | Q3: 10-15 工作日
B4: 德国 | C4: =VLOOKUP(B4,#REF!,2,0) -> #REF! | D4: 0.401-1 | G4: 0.401 | H4: 1 | I4: 57.5 | K4: 57.5 | L4: 28
B5: 德国 | C5: =VLOOKUP(B5,#REF!,2,0) -> #REF! | D5: 1.001-30 | G5: 1.001 | H5: 30 | I5: 57 | K5: 57 | L5: 28 | N5: L＜100，W＜60，H＜60 | P5: 10*15cm
B6: 法国 | C6: =VLOOKUP(B6,#REF!,2,0) -> #REF! | D6: 0-0.4 | G6: 0 | H6: 0.4 | I6: 63.5 | J6: 29 | K6: 63.5 | L6: 29 | M6: Colis Prive | N6: L＜100，L + W + H≤150
B7: 法国 | C7: =VLOOKUP(B7,#REF!,2,0) -> #REF! | D7: 0.401-1 | G7: 0.401 | H7: 1 | I7: 64.5 | K7: 64.5 | L7: 29
B8: 法国 | C8: =VLOOKUP(B8,#REF!,2,0) -> #REF! | D8: 1.001-2 | G8: 1.001 | H8: 2 | I8: 64 | K8: 64 | L8: 29
B9: 波兰 | C9: =VLOOKUP(B9,#REF!,2,0) -> #REF! | D9: 0-0.4 | G9: 0 | H9: 0.4 | I9: 62.5 | J9: 16 | K9: 62.5 | L9: 16 | M9: Poland Post | N9: L + W + H ≤70，L≤50，H≤6
B10: 波兰 | C10: =VLOOKUP(B10,#REF!,2,0) -> #REF! | D10: 0.401-1 | G10: 0.401 | H10: 1 | I10: 63.5 | K10: 63.5 | L10: 16
B11: 波兰 | C11: =VLOOKUP(B11,#REF!,2,0) -> #REF! | D11: 1.001-30 | G11: 1.001 | H11: 30 | I11: 63 | J11: 21 | K11: 63 | L11: 21 | M11: IN POST | N11: L＜100，L + W + H≤220
B12: 西班牙 | C12: =VLOOKUP(B12,#REF!,2,0) -> #REF! | D12: 0-1 | G12: 0 | H12: 1 | I12: 63.5 | J12: 23 | K12: 63.5 | L12: 23 | M12: CTT | N12: L≤80，L + W + H＜180
B13: 西班牙 | C13: =VLOOKUP(B13,#REF!,2,0) -> #REF! | D13: 1.001-2 | G13: 1.001 | H13: 2 | I13: 64.5 | J13: 28 | K13: 64.5 | L13: 28
B14: 西班牙 | C14: =VLOOKUP(B14,#REF!,2,0) -> #REF! | D14: 2.001-30 | G14: 2.001 | H14: 30 | I14: 64 | K14: 64 | L14: 28
B15: 葡萄牙 | C15: =VLOOKUP(B15,#REF!,2,0) -> #REF! | D15: 0-1 | G15: 0 | H15: 1 | I15: 65 | J15: 23 | K15: 65 | L15: 23 | M15: CTT | N15: L≤80，L + W + H＜180
B16: 葡萄牙 | C16: =VLOOKUP(B16,#REF!,2,0) -> #REF! | D16: 1.001-15 | G16: 1.001 | H16: 15 | I16: 66 | J16: 25 | K16: 66 | L16: 25
B17: 意大利 | C17: =VLOOKUP(B17,#REF!,2,0) -> #REF! | D17: 0-0.4 | G17: 0 | H17: 0.4 | I17: 60 | J17: 67.5 | K17: 60 | L17: 67.5 | M17: DHL Packet International | N17: L＜100 W＜60 H＜60
B18: 意大利 | C18: =VLOOKUP(B18,#REF!,2,0) -> #REF! | D18: 0.401-1 | G18: 0.401 | H18: 1 | I18: 60.5 | K18: 60.5 | L18: 67.5
B19: 意大利 | C19: =VLOOKUP(B19,#REF!,2,0) -> #REF! | D19: 1.001-30 | G19: 1.001 | H19: 30 | I19: 60.5 | K19: 60.5 | L19: 67.5
B20: 荷兰 | C20: =VLOOKUP(B20,#REF!,2,0) -> #REF! | D20: 0-0.4 | G20: 0 | H20: 0.4 | I20: 59.5 | J20: 49 | K20: 59.5 | L20: 49
B21: 荷兰 | C21: =VLOOKUP(B21,#REF!,2,0) -> #REF! | D21: 0.401-1 | G21: 0.401 | H21: 1 | I21: 60.5 | K21: 60.5 | L21: 49
B22: 荷兰 | C22: =VLOOKUP(B22,#REF!,2,0) -> #REF! | D22: 1.001-30 | G22: 1.001 | H22: 30 | I22: 60 | K22: 60 | L22: 49
B23: 比利时 | C23: =VLOOKUP(B23,#REF!,2,0) -> #REF! | D23: 0-0.4 | G23: 0 | H23: 0.4 | I23: 59.5 | J23: 51.5 | K23: 59.5 | L23: 51.5
B24: 比利时 | C24: =VLOOKUP(B24,#REF!,2,0) -> #REF! | D24: 0.401-1 | G24: 0.401 | H24: 1 | I24: 60.5 | K24: 60.5 | L24: 51.5
B25: 比利时 | C25: =VLOOKUP(B25,#REF!,2,0) -> #REF! | D25: 1.001-30 | G25: 1.001 | H25: 30 | I25: 60 | K25: 60 | L25: 51.5
B26: 爱尔兰 | C26: =VLOOKUP(B26,#REF!,2,0) -> #REF! | D26: 0-0.4 | G26: 0 | H26: 0.4 | I26: 65 | J26: 52 | K26: 65 | L26: 52
B27: 爱尔兰 | C27: =VLOOKUP(B27,#REF!,2,0) -> #REF! | D27: 0.401-1 | G27: 0.401 | H27: 1 | I27: 66 | K27: 66 | L27: 52
B28: 爱尔兰 | C28: =VLOOKUP(B28,#REF!,2,0) -> #REF! | D28: 1.001-30 | G28: 1.001 | H28: 30 | I28: 65.5 | K28: 65.5 | L28: 52
B29: 匈牙利 | C29: =VLOOKUP(B29,#REF!,2,0) -> #REF! | D29: 0-0.4 | G29: 0 | H29: 0.4 | I29: 60.5 | J29: 42 | K29: 60.5 | L29: 42
B30: 匈牙利 | C30: =VLOOKUP(B30,#REF!,2,0) -> #REF! | D30: 0.401-1 | G30: 0.401 | H30: 1 | I30: 61.5 | K30: 61.5 | L30: 42
B31: 匈牙利 | C31: =VLOOKUP(B31,#REF!,2,0) -> #REF! | D31: 1.001-30 | G31: 1.001 | H31: 30 | I31: 61 | K31: 61 | L31: 42
B32: 瑞典 | C32: =VLOOKUP(B32,#REF!,2,0) -> #REF! | D32: 0-0.4 | G32: 0 | H32: 0.4 | I32: 60 | J32: 102 | K32: 60 | L32: 102
B33: 瑞典 | C33: =VLOOKUP(B33,#REF!,2,0) -> #REF! | D33: 0.401-1 | G33: 0.401 | H33: 1 | I33: 61 | K33: 61 | L33: 102
B34: 瑞典 | C34: =VLOOKUP(B34,#REF!,2,0) -> #REF! | D34: 1.001-30 | G34: 1.001 | H34: 30 | I34: 60.5 | K34: 60.5 | L34: 102
B35: 奥地利 | C35: =VLOOKUP(B35,#REF!,2,0) -> #REF! | D35: 0-0.4 | G35: 0 | H35: 0.4 | I35: 60 | J35: 48 | K35: 60 | L35: 48
B36: 奥地利 | C36: =VLOOKUP(B36,#REF!,2,0) -> #REF! | D36: 0.401-1 | G36: 0.401 | H36: 1 | I36: 61 | K36: 61 | L36: 48
B37: 奥地利 | C37: =VLOOKUP(B37,#REF!,2,0) -> #REF! | D37: 1.001-30 | G37: 1.001 | H37: 30 | I37: 60.5 | K37: 60.5 | L37: 48
B38: 保加利亚 | C38: =VLOOKUP(B38,#REF!,2,0) -> #REF! | D38: 0-0.4 | G38: 0 | H38: 0.4 | I38: 63.5 | J38: 47.5 | K38: 63.5 | L38: 47.5
B39: 保加利亚 | C39: =VLOOKUP(B39,#REF!,2,0) -> #REF! | D39: 0.401-1 | G39: 0.401 | H39: 1 | I39: 64.5 | K39: 64.5 | L39: 47.5
B40: 保加利亚 | C40: =VLOOKUP(B40,#REF!,2,0) -> #REF! | D40: 1.001-30 | G40: 1.001 | H40: 30 | I40: 64 | K40: 64 | L40: 47.5
B41: 芬兰 | C41: =VLOOKUP(B41,#REF!,2,0) -> #REF! | D41: 0-0.4 | G41: 0 | H41: 0.4 | I41: 61 | J41: 95 | K41: 61 | L41: 95
B42: 芬兰 | C42: =VLOOKUP(B42,#REF!,2,0) -> #REF! | D42: 0.401-1 | G42: 0.401 | H42: 1 | I42: 62 | K42: 62 | L42: 95
B43: 芬兰 | C43: =VLOOKUP(B43,#REF!,2,0) -> #REF! | D43: 1.001-30 | G43: 1.001 | H43: 30 | I43: 61.5 | K43: 61.5 | L43: 95
B44: 丹麦 | C44: =VLOOKUP(B44,#REF!,2,0) -> #REF! | D44: 0-0.4 | G44: 0 | H44: 0.4 | I44: 59.5 | J44: 80.5 | K44: 59.5 | L44: 80.5
B45: 丹麦 | C45: =VLOOKUP(B45,#REF!,2,0) -> #REF! | D45: 0.401-1 | G45: 0.401 | H45: 1 | I45: 60.5 | K45: 60.5 | L45: 80.5
B46: 丹麦 | C46: =VLOOKUP(B46,#REF!,2,0) -> #REF! | D46: 1.001-30 | G46: 1.001 | H46: 30 | I46: 60 | K46: 60 | L46: 80.5
B47: 罗马尼亚 | C47: =VLOOKUP(B47,#REF!,2,0) -> #REF! | D47: 0-0.4 | G47: 0 | H47: 0.4 | I47: 61.5 | J47: 57 | K47: 61.5 | L47: 57
B48: 罗马尼亚 | C48: =VLOOKUP(B48,#REF!,2,0) -> #REF! | D48: 0.401-1 | G48: 0.401 | H48: 1 | I48: 62.5 | K48: 62.5 | L48: 57
B49: 罗马尼亚 | C49: =VLOOKUP(B49,#REF!,2,0) -> #REF! | D49: 1.001-30 | G49: 1.001 | H49: 30 | I49: 62 | K49: 62 | L49: 57
B50: 立陶宛 | C50: =VLOOKUP(B50,#REF!,2,0) -> #REF! | D50: 0-0.4 | G50: 0 | H50: 0.4 | I50: 61.5 | J50: 57.5 | K50: 61.5 | L50: 57.5
B51: 立陶宛 | C51: =VLOOKUP(B51,#REF!,2,0) -> #REF! | D51: 0.401-1 | G51: 0.401 | H51: 1 | I51: 62.5 | K51: 62.5 | L51: 57.5
B52: 立陶宛 | C52: =VLOOKUP(B52,#REF!,2,0) -> #REF! | D52: 1.001-30 | G52: 1.001 | H52: 30 | I52: 62 | K52: 62 | L52: 57.5
B53: 捷克 | C53: =VLOOKUP(B53,#REF!,2,0) -> #REF! | D53: 0-0.4 | G53: 0 | H53: 0.4 | I53: 62 | J53: 36.5 | K53: 62 | L53: 36.5
B54: 捷克 | C54: =VLOOKUP(B54,#REF!,2,0) -> #REF! | D54: 0.401-1 | G54: 0.401 | H54: 1 | I54: 63 | K54: 63 | L54: 36.5
B55: 捷克 | C55: =VLOOKUP(B55,#REF!,2,0) -> #REF! | D55: 1.001-30 | G55: 1.001 | H55: 30 | I55: 62.5 | K55: 62.5 | L55: 36.5
B56: 希腊 | C56: =VLOOKUP(B56,#REF!,2,0) -> #REF! | D56: 0-0.4 | G56: 0 | H56: 0.4 | I56: 68.5 | J56: 56 | K56: 68.5 | L56: 56
B57: 希腊 | C57: =VLOOKUP(B57,#REF!,2,0) -> #REF! | D57: 0.401-1 | G57: 0.401 | H57: 1 | I57: 69.5 | K57: 69.5 | L57: 56
B58: 希腊 | C58: =VLOOKUP(B58,#REF!,2,0) -> #REF! | D58: 1.001-30 | G58: 1.001 | H58: 30 | I58: 69 | K58: 69 | L58: 56
B59: 斯洛伐克 | C59: =VLOOKUP(B59,#REF!,2,0) -> #REF! | D59: 0-0.4 | G59: 0 | H59: 0.4 | I59: 61 | J59: 42 | K59: 61 | L59: 42
B60: 斯洛伐克 | C60: =VLOOKUP(B60,#REF!,2,0) -> #REF! | D60: 0.401-1 | G60: 0.401 | H60: 1 | I60: 62 | K60: 62 | L60: 42
B61: 斯洛伐克 | C61: =VLOOKUP(B61,#REF!,2,0) -> #REF! | D61: 1.001-30 | G61: 1.001 | H61: 30 | I61: 61.5 | K61: 61.5 | L61: 42
B62: 克罗地亚 | C62: =VLOOKUP(B62,#REF!,2,0) -> #REF! | D62: 0-0.4 | G62: 0 | H62: 0.4 | I62: 65 | J62: 35 | K62: 65 | L62: 35
B63: 克罗地亚 | C63: =VLOOKUP(B63,#REF!,2,0) -> #REF! | D63: 0.401-1 | G63: 0.401 | H63: 1 | I63: 66 | K63: 66 | L63: 35
B64: 克罗地亚 | C64: =VLOOKUP(B64,#REF!,2,0) -> #REF! | D64: 1.001-30 | G64: 1.001 | H64: 30 | I64: 65.5 | K64: 65.5 | L64: 35
B65: 卢森堡 | C65: =VLOOKUP(B65,#REF!,2,0) -> #REF! | D65: 0-0.4 | G65: 0 | H65: 0.4 | I65: 60 | J65: 50 | K65: 60 | L65: 50
B66: 卢森堡 | C66: =VLOOKUP(B66,#REF!,2,0) -> #REF! | D66: 0.401-1 | G66: 0.401 | H66: 1 | I66: 61 | K66: 61 | L66: 50
B67: 卢森堡 | C67: =VLOOKUP(B67,#REF!,2,0) -> #REF! | D67: 1.001-30 | G67: 1.001 | H67: 30 | I67: 60.5 | K67: 60.5 | L67: 50
B68: 斯洛文尼亚 | C68: =VLOOKUP(B68,#REF!,2,0) -> #REF! | D68: 0-0.4 | G68: 0 | H68: 0.4 | I68: 60 | J68: 44 | K68: 60 | L68: 44
B69: 斯洛文尼亚 | C69: =VLOOKUP(B69,#REF!,2,0) -> #REF! | D69: 0.401-1 | G69: 0.401 | H69: 1 | I69: 61 | K69: 61 | L69: 44
B70: 斯洛文尼亚 | C70: =VLOOKUP(B70,#REF!,2,0) -> #REF! | D70: 1.001-30 | G70: 1.001 | H70: 30 | I70: 60.5 | K70: 60.5 | L70: 44
B71: 拉脱维亚 | C71: =VLOOKUP(B71,#REF!,2,0) -> #REF! | D71: 0-0.4 | G71: 0 | H71: 0.4 | I71: 61.5 | J71: 64.5 | K71: 61.5 | L71: 64.5
B72: 拉脱维亚 | C72: =VLOOKUP(B72,#REF!,2,0) -> #REF! | D72: 0.401-1 | G72: 0.401 | H72: 1 | I72: 62.5 | K72: 62.5 | L72: 64.5
B73: 拉脱维亚 | C73: =VLOOKUP(B73,#REF!,2,0) -> #REF! | D73: 1.001-30 | G73: 1.001 | H73: 30 | I73: 62 | K73: 62 | L73: 64.5
B74: 爱沙尼亚 | C74: =VLOOKUP(B74,#REF!,2,0) -> #REF! | D74: 0-0.4 | G74: 0 | H74: 0.4 | I74: 61.5 | J74: 66.5 | K74: 61.5 | L74: 66.5
B75: 爱沙尼亚 | C75: =VLOOKUP(B75,#REF!,2,0) -> #REF! | D75: 0.401-1 | G75: 0.401 | H75: 1 | I75: 62.5 | K75: 62.5 | L75: 66.5
B76: 爱沙尼亚 | C76: =VLOOKUP(B76,#REF!,2,0) -> #REF! | D76: 1.001-30 | G76: 1.001 | H76: 30 | I76: 62 | K76: 62 | L76: 66.5
B77: 马耳他 | C77: =VLOOKUP(B77,#REF!,2,0) -> #REF! | D77: 0-0.4 | G77: 0 | H77: 0.4 | I77: 77 | J77: 102.5 | K77: 77 | L77: 102.5
B78: 马耳他 | C78: =VLOOKUP(B78,#REF!,2,0) -> #REF! | D78: 0.401-1 | G78: 0.401 | H78: 1 | I78: 78 | K78: 78 | L78: 102.5
B79: 马耳他 | C79: =VLOOKUP(B79,#REF!,2,0) -> #REF! | D79: 1.001-30 | G79: 1.001 | H79: 30 | I79: 77.5 | K79: 77.5 | L79: 102.5
B80: 塞浦路斯 | C80: =VLOOKUP(B80,#REF!,2,0) -> #REF! | D80: 0-0.4 | G80: 0 | H80: 0.4 | I80: 82 | J80: 145 | K80: 82 | L80: 145
B81: 塞浦路斯 | C81: =VLOOKUP(B81,#REF!,2,0) -> #REF! | D81: 0.401-1 | G81: 0.401 | H81: 1 | I81: 82 | K81: 82 | L81: 145
B82: 塞浦路斯 | C82: =VLOOKUP(B82,#REF!,2,0) -> #REF! | D82: 1.001-30 | G82: 1.001 | H82: 30 | I82: 82 | K82: 82 | L82: 145

Sheet 华翰甄选
F1: Specialpak甄选专线 | N1: 生效日期：2025.05.26 9:00 | O1: 返回目录
B2: 国家 | F2: 重量段KG | K2: 运费 RMB/KG | L2: 挂号费 RMB/票 | M2: 尺寸限制cm | N2: 参考时效（工作日）
B3: 加拿大 | C3: CA | F3: 0.05≤W≤0.3 | G3: 0.05 | H3: 0.3 | K3: 104 | L3: 30 | M3: 最长边≤60cm；长+宽+高≤90cm 最小尺寸≥15x10x1cm | N3: 9-15
B4: 加拿大 | C4: CA | F4: 0.3<W≤0.75 | G4: 0.3 | H4: 0.75 | K4: 104 | L4: 30
B5: 加拿大 | C5: CA | F5: 0.75<W≤1 | G5: 0.75 | H5: 1 | K5: 104 | L5: 30
B6: 加拿大 | C6: CA | F6: 1<W≤1.5 | G6: 1 | H6: 1.5 | K6: 104 | L6: 30
B7: 加拿大 | C7: CA | F7: 1.5<W≤2 | G7: 1.5 | H7: 2 | K7: 95 | L7: 30
B8: 英国 | C8: UK/GB | F8: 0.01≤W≤1 | G8: 0.01 | H8: 1 | K8: 128 | L8: 19 | M8: 最大尺寸<60x40x40cm 最小尺寸≥15x10x1cm | N8: 6-10
B9: 英国 | C9: UK/GB | F9: 1<W≤2 | G9: 1 | H9: 2 | K9: 117 | L9: 19 | O9: 英国-EVRI偏远邮编
B10: 英国 | C10: UK/GB | F10: 2<W≤10 | G10: 2 | H10: 10 | K10: 117 | L10: 19
B11: 德国 | C11: DE | F11: 0.05≤W≤1 | G11: 0.05 | H11: 1 | K11: 123 | L11: 25 | M11: 最长边≤60cm；长+宽+高≤90cm 最小尺寸≥15x10x1cm | N11: 6-8
B12: 德国 | C12: DE | F12: 1<W≤2 | G12: 1 | H12: 2 | K12: 123 | L12: 25
B13: 法国 | C13: FR | F13: 0.05≤W≤1 | G13: 0.05 | H13: 1 | K13: 148 | L13: 34 | M13: 最长边≤60cm；长+宽+高≤90cm 最小尺寸≥15x10x1cm | N13: 7-9
B14: 法国 | C14: FR | F14: 1<W≤2 | G14: 1 | H14: 2 | K14: 148 | L14: 34
B15: 意大利 | C15: IT | F15: 0.05≤W≤1 | G15: 0.05 | H15: 1 | K15: 136 | L15: 34 | M15: 最长边≤60cm；长+宽+高≤90cm 最小尺寸≥15x10x1cm | N15: 8-16
B16: 意大利 | C16: IT | F16: 1<W≤2 | G16: 1 | H16: 2 | K16: 136 | L16: 34
B17: 西班牙 | C17: ES | F17: 0.05≤W≤1 | G17: 0.05 | H17: 1 | K17: 131 | L17: 28 | M17: 最长边≤60cm；长+宽+高≤90cm 最小尺寸≥15x10x1cm | N17: 8-10
B18: 西班牙 | C18: ES | F18: 1<W≤2 | G18: 1 | H18: 2 | K18: 131 | L18: 28
B19: 葡萄牙 | C19: PT | F19: 0.05≤W≤1 | G19: 0.05 | H19: 1 | K19: 135 | L19: 27 | M19: 最长边≤60cm；长+宽+高≤90cm 最小尺寸≥15x10x1cm | N19: 8-16
B20: 葡萄牙 | C20: PT | F20: 1<W≤2 | G20: 1 | H20: 2 | K20: 135 | L20: 27
B21: 墨西哥 | C21: MX | F21: 0.05≤W≤0.5 | G21: 0.05 | H21: 0.5 | K21: 136 | L21: 22 | M21: 最大尺寸≤45x40x40cm 最小尺寸≥15x10x1cm | N21: 12-17
B22: 墨西哥 | C22: MX | F22: 0.5<W≤1 | G22: 0.5 | H22: 1 | K22: 136 | L22: 22
B23: 墨西哥 | C23: MX | F23: 1<W≤5 | G23: 1 | H23: 5 | K23: 136 | L23: 22
B24: 美国 | C24: US | F24: 0.05≤W≤0.1 | G24: 0.05 | H24: 0.1 | K24: 128 | L24: 29
B25: 美国 | C25: US | F25: 0.1<W≤0.2 | G25: 0.1 | H25: 0.2 | K25: 128 | L25: 29
B26: 美国 | C26: US | F26: 0.2<W≤0.3 | G26: 0.2 | H26: 0.3 | K26: 128 | L26: 29
B27: 美国 | C27: US | F27: 0.3<W≤0.453 | G27: 0.3 | H27: 0.453 | K27: 145 | L27: 24
B28: 美国 | C28: US | F28: 0.453<W≤0.7 | G28: 0.453 | H28: 0.7 | K28: 161 | L28: 24
B29: 美国 | C29: US | F29: 0.7<W≤1 | G29: 0.7 | H29: 1 | K29: 161 | L29: 24
B30: 美国 | C30: US | F30: 1<W≤2 | G30: 1 | H30: 2 | K30: 161 | L30: 17

Sheet 华翰电子烟
F1: Specialpak电子烟专线 | N1: 生效日期：2025.02.22 9:00 | O1: 返回目录
B2: 国家 | F2: 重量段KG | K2: 运费 RMB/KG | L2: 挂号费 RMB/票 | M2: 尺寸限制cm | N2: 参考时效（工作日）
B3: 德国 | C3: DE | F3: 0.01≤W≤1 | G3: 0.01 | H3: 1 | K3: 111 | L3: 27 | M3: 最长边≤60cm；长+宽+高≤90cm 最小尺寸≥15x10x1cm | N3: 8-12
B4: 德国 | C4: DE | F4: 1<W≤2 | G4: 1 | H4: 2 | K4: 111 | L4: 27
B5: 法国 | C5: FR | F5: 0.01≤W≤1 | G5: 0.01 | H5: 1 | K5: 137 | L5: 35 | M5: 最长边≤60cm；长+宽+高≤90cm 最小尺寸≥15x10x1cm | N5: 8-12
B6: 法国 | C6: FR | F6: 1<W≤2 | G6: 1 | H6: 2 | K6: 137 | L6: 35
B7: 意大利 | C7: IT | F7: 0.01≤W≤1 | G7: 0.01 | H7: 1 | K7: 126 | L7: 36 | M7: 最长边≤60cm；长+宽+高≤90cm 最小尺寸≥15x10x1cm | N7: 8-12
B8: 意大利 | C8: IT | F8: 1<W≤2 | G8: 1 | H8: 2 | K8: 126 | L8: 36
B9: 西班牙 | C9: ES | F9: 0.01≤W≤1 | G9: 0.01 | H9: 1 | K9: 122 | L9: 29 | M9: 最长边≤60cm；长+宽+高≤90cm 最小尺寸≥15x10x1cm | N9: 8-12
B10: 西班牙 | C10: ES | F10: 1<W≤2 | G10: 1 | H10: 2 | K10: 122 | L10: 29
B11: 葡萄牙 | C11: PT | F11: 0.01≤W≤1 | G11: 0.01 | H11: 1 | K11: 124 | L11: 29 | M11: 最长边≤60cm；长+宽+高≤90cm 最小尺寸≥15x10x1cm | N11: 8-12
B12: 葡萄牙 | C12: PT | F12: 1<W≤2 | G12: 1 | H12: 2 | K12: 124 | L12: 29
B13: 荷兰 | C13: NL | F13: 0.01≤W≤1 | G13: 0.01 | H13: 1 | K13: 127 | L13: 46 | M13: 最长边≤60cm；长+宽+高≤90cm 最小尺寸≥15x10x1cm | N13: 8-12
B14: 荷兰 | C14: NL | F14: 1<W≤2 | G14: 1 | H14: 2 | K14: 127 | L14: 46
B15: 比利时 | C15: BE | F15: 0.01≤W≤1 | G15: 0.01 | H15: 1 | K15: 119 | L15: 32 | M15: 最长边≤60cm；长+宽+高≤90cm 最小尺寸≥15x10x1cm | N15: 8-12
B16: 比利时 | C16: BE | F16: 1<W≤2 | G16: 1 | H16: 2 | K16: 119 | L16: 32
B17: 卢森堡 | C17: LU | F17: 0.01≤W≤1 | G17: 0.01 | H17: 1 | K17: 104 | L17: 32 | M17: 最长边≤60cm；长+宽+高≤90cm 最小尺寸≥15x10x1cm | N17: 8-12
B18: 卢森堡 | C18: LU | F18: 1<W≤2 | G18: 1 | H18: 2 | K18: 104 | L18: 32
B19: 瑞典 | C19: SE/SW | F19: 0.01≤W≤1 | G19: 0.01 | H19: 1 | K19: 115 | L19: 48 | M19: 最长边≤60cm；长+宽+高≤90cm 最小尺寸≥15x10x1cm | N19: 8-12
B20: 瑞典 | C20: SE/SW | F20: 1<W≤2 | G20: 1 | H20: 2 | K20: 115 | L20: 48
B21: 奥地利 | C21: AT | F21: 0.01≤W≤1 | G21: 0.01 | H21: 1 | K21: 109 | L21: 40 | M21: 最长边≤60cm；长+宽+高≤90cm 最小尺寸≥15x10x1cm | N21: 8-12
B22: 奥地利 | C22: AT | F22: 1<W≤2 | G22: 1 | H22: 2 | K22: 109 | L22: 26
B23: 捷克 | C23: CZ | F23: 0.01≤W≤1 | G23: 0.01 | H23: 1 | K23: 121 | L23: 46 | M23: 最长边≤60cm；长+宽+高≤90cm 最小尺寸≥15x10x1cm | N23: 8-12
B24: 捷克 | C24: CZ | F24: 1<W≤2 | G24: 1 | H24: 2 | K24: 121 | L24: 46
B25: 波兰 | C25: PL | F25: 0.01≤W≤1 | G25: 0.01 | H25: 1 | K25: 117 | L25: 47 | M25: 最长边≤60cm；长+宽+高≤90cm 最小尺寸≥15x10x1cm | N25: 8-12
B26: 波兰 | C26: PL | F26: 1<W≤2 | G26: 1 | H26: 2 | K26: 117 | L26: 34
B27: 斯洛伐克 | C27: SK | F27: 0.01≤W≤1 | G27: 0.01 | H27: 1 | K27: 112 | L27: 34 | M27: 最长边≤60cm；长+宽+高≤90cm 最小尺寸≥15x10x1cm | N27: 8-14
B28: 斯洛伐克 | C28: SK | F28: 1<W≤2 | G28: 1 | H28: 2 | K28: 112 | L28: 34
B29: 斯洛文尼亚 | C29: SI | F29: 0.01≤W≤1 | G29: 0.01 | H29: 1 | K29: 138 | L29: 77 | M29: 最长边≤60cm；长+宽+高≤90cm 最小尺寸≥15x10x1cm | N29: 8-12
B30: 斯洛文尼亚 | C30: SI | F30: 1<W≤2 | G30: 1 | H30: 2 | K30: 138 | L30: 48
B31: 爱尔兰 | C31: IE | F31: 0.01≤W≤1 | G31: 0.01 | H31: 1 | K31: 115 | L31: 37 | M31: 最长边≤60cm；长+宽+高≤90cm 最小尺寸≥15x10x1cm | N31: 8-14
B32: 爱尔兰 | C32: IE | F32: 1<W≤2 | G32: 1 | H32: 2 | K32: 115 | L32: 37
B33: 匈牙利 | C33: HU | F33: 0.01≤W≤1 | G33: 0.01 | H33: 1 | K33: 109 | L33: 28 | M33: 最长边≤60cm；长+宽+高≤90cm 最小尺寸≥15x10x1cm | N33: 8-12
B34: 匈牙利 | C34: HU | F34: 1<W≤2 | G34: 1 | H34: 2 | K34: 109 | L34: 28
B35: 立陶宛 | C35: LT | F35: 0.01≤W≤1 | G35: 0.01 | H35: 1 | K35: 131 | L35: 67 | M35: 最长边≤60cm；长+宽+高≤90cm 最小尺寸≥15x10x1cm | N35: 8-14
B36: 立陶宛 | C36: LT | F36: 1<W≤2 | G36: 1 | H36: 2 | K36: 131 | L36: 51
B37: 丹麦 | C37: DK | F37: 0.01≤W≤1 | G37: 0.01 | H37: 1 | K37: 113 | L37: 40 | M37: 最长边≤60cm；长+宽+高≤90cm 最小尺寸≥15x10x1cm | N37: 8-12
B38: 丹麦 | C38: DK | F38: 1<W≤2 | G38: 1 | H38: 2 | K38: 113 | L38: 30
B39: 克罗地亚 | C39: CRO | F39: 0.01≤W≤1 | G39: 0.01 | H39: 1 | K39: 139 | L39: 119 | M39: 最长边≤60cm；长+宽+高≤90cm 最小尺寸≥15x10x1cm | N39: 8-12
B40: 克罗地亚 | C40: CRO | F40: 1<W≤2 | G40: 1 | H40: 2 | K40: 139 | L40: 102
B41: 罗马尼亚 | C41: RO | F41: 0.01≤W≤1 | G41: 0.01 | H41: 1 | K41: 108 | L41: 30 | M41: 最长边≤60cm；长+宽+高≤90cm 最小尺寸≥15x10x1cm | N41: 8-12
B42: 罗马尼亚 | C42: RO | F42: 1<W≤2 | G42: 1 | H42: 2 | K42: 108 | L42: 30
B43: 拉脱维亚 | C43: LV | F43: 0.01≤W≤1 | G43: 0.01 | H43: 1 | K43: 139 | L43: 87 | M43: 最长边≤60cm；长+宽+高≤90cm 最小尺寸≥15x10x1cm | N43: 8-12
B44: 拉脱维亚 | C44: LV | F44: 1<W≤2 | G44: 1 | H44: 2 | K44: 145 | L44: 64
B45: 爱沙尼亚 | C45: EE | F45: 0.01≤W≤1 | G45: 0.01 | H45: 1 | K45: 129 | L45: 94 | M45: 最长边≤60cm；长+宽+高≤90cm 最小尺寸≥15x10x1cm | N45: 8-12
B46: 爱沙尼亚 | C46: EE | F46: 1<W≤2 | G46: 1 | H46: 2 | K46: 145 | L46: 61
B47: 芬兰 | C47: FI | F47: 0.01≤W≤1 | G47: 0.01 | H47: 1 | K47: 134 | L47: 65 | M47: 最长边≤60cm；长+宽+高≤90cm 最小尺寸≥15x10x1cm | N47: 8-14
B48: 芬兰 | C48: FI | F48: 1<W≤2 | G48: 1 | H48: 2 | K48: 134 | L48: 50
B49: 保加利亚 | C49: BG | F49: 0.01≤W≤1 | G49: 0.01 | H49: 1 | K49: 111 | L49: 30 | M49: 最长边≤60cm；长+宽+高≤90cm 最小尺寸≥15x10x1cm | N49: 8-14
B50: 保加利亚 | C50: BG | F50: 1<W≤2 | G50: 1 | H50: 2 | K50: 111 | L50: 26
B51: 希腊 | C51: GR | F51: 0.01≤W≤1 | G51: 0.01 | H51: 1 | K51: 116 | L51: 30 | M51: 最长边≤60cm；长+宽+高≤90cm 最小尺寸≥15x10x1cm | N51: 8-14
B52: 希腊 | C52: GR | F52: 1<W≤2 | G52: 1 | H52: 2 | K52: 116 | L52: 30
B53: 马耳他 | C53: MAL | F53: 0.01≤W≤1 | G53: 0.01 | H53: 1 | K53: 150 | L53: 54 | M53: 最长边≤60cm；长+宽+高≤90cm 最小尺寸≥15x10x1cm | N53: 8-14
B54: 马耳他 | C54: MAL | F54: 1<W≤2 | G54: 1 | H54: 2 | K54: 150 | L54: 43
B55: 塞浦路斯 | C55: CY | F55: 0.01≤W≤1 | G55: 0.01 | H55: 1 | K55: 156 | L55: 83 | M55: 最长边≤60cm；长+宽+高≤90cm 最小尺寸≥15x10x1cm | N55: 8-14
B56: 塞浦路斯 | C56: CY | F56: 1<W≤2 | G56: 1 | H56: 2 | K56: 156 | L56: 66

Sheet 蜂鸟敏感
A1: 蜂鸟国际物流 - 欧美TK敏感（虚拟仓）
A2: 产品名称 | B2: 国家 | D2: 时效(工作日) | E2: 国家 | F2: 重量限制（kg） | I2: 处理费（元/件） | J2: 运费（元/kg） | K2: 尾程派送商 | L2: 尺寸限制（cm） | N2: 体积重计算系数 | O2: 面单尺寸 | P2: 备注
A3: 欧洲敏感TK专线 | B3: 英国 | C3: UK | D3: 6--9 | E3: 英国 | F3: 0.05-0.3 | G3: 0.05 | H3: 0.3 | I3: 24 | J3: 76 | K3: YODEL | L3: L＜60，W＜40，H＜40 L+2*(W+H)≤210 | N3: 8000 | O3: 10*15cm | P3: 英国不足50g 按50g计费
C4: UK | F4: 0.301-1 | G4: 0.301 | H4: 1 | I4: 24 | J4: 76
C5: UK | F5: 1.001-2 | G5: 1.001 | H5: 2 | I5: 24 | J5: 79.5
C6: UK | F6: 2.001-15 | G6: 2.001 | H6: 15 | I6: 24 | J6: 79.5
B7: 德国 | C7: DE | E7: 德国 | F7: 0-10 | G7: 0 | H7: 10 | I7: 32 | J7: 73.5 | K7: DHL Paket | L7: L＜100，W＜60，H＜60 | P7: 德国DHL Paket：下单预报要求如实申报重量，预报重量与实际重量差异100g将会产生附加费：2.2欧/票
B8: 法国 | C8: FR | E8: 法国 | F8: 0-10 | G8: 0 | H8: 10 | I8: 32 | J8: 79.5 | K8: Colis Prive | L8: L＜100，L + W + H≤150
